Workbook
Name TIPO_LANCAMENTO: 'CONFIGURAÇÕES'!$F$36:$F$37
Name SITUACAO: 'CONFIGURAÇÕES'!$G$36:$G$41
Name FORMA_PAGAMENTO: 'CONFIGURAÇÕES'!$H$36:$H$44
Name TIPO_CONTA: 'CONFIGURAÇÕES'!$I$36:$I$45
Name STATUS_CADASTRO: 'CONFIGURAÇÕES'!$J$36:$J$38
Name PERIODICIDADE: 'CONFIGURAÇÕES'!$K$36:$K$40
Name SISTEMA_AMORTIZACAO: 'CONFIGURAÇÕES'!$L$36:$L$37
Name TIPO_FLUXO: 'CONFIGURAÇÕES'!$M$36:$M$38
Name BANDEIRA: 'CONFIGURAÇÕES'!$N$36:$N$41
Name STATUS_CONCILIACAO: 'CONFIGURAÇÕES'!$O$36:$O$38
Name SIM_NAO: 'CONFIGURAÇÕES'!$P$36:$P$37
Name REGIME: 'CONFIGURAÇÕES'!$Q$36:$Q$39
Name UF: 'CONFIGURAÇÕES'!$R$36:$R$62
Name MESES: 'CONFIGURAÇÕES'!$S$36:$S$47
Name TIPO_OPERACAO: 'CONFIGURAÇÕES'!$T$36:$T$38
Name SUBGRUPOS: 'CONFIGURAÇÕES'!$U$36:$U$48
Name STATUS_CONTRATO: 'CONFIGURAÇÕES'!$V$36:$V$39
Name LINHAS_DRE: 'CONFIGURAÇÕES'!$W$36:$W$47
Name CLIENTES_NOMES: 'CADASTRO DE CLIENTES'!$B$6:$B$65
Name CLIENTES_FANTASIA: 'CADASTRO DE CLIENTES'!$C$6:$C$65
Name FORNECEDORES_NOMES: 'CADASTRO DE FORNECEDORES'!$B$6:$B$65
Name FORNECEDORES_FANTASIA: 'CADASTRO DE FORNECEDORES'!$C$6:$C$65
Name CATEGORIAS_PLANO: 'PLANO DE CONTAS'!$C$6:$C$85
Name SUBGRUPOS_PLANO: 'PLANO DE CONTAS'!$C$6:$C$85
Name SUBCATEGORIAS_PLANO: 'PLANO DE CONTAS'!$D$6:$D$85
Name LINHAS_DRE_PLANO: 'PLANO DE CONTAS'!$H$6:$H$85
Name GRUPOS_PLANO: 'PLANO DE CONTAS'!$B$6:$B$85
Name TIPOS_FLUXO_PLANO: 'PLANO DE CONTAS'!$G$6:$G$85
Name CENTROS_CUSTO: 'CENTRO DE CUSTOS'!$B$6:$B$25
Name CONTAS_BANCARIAS: 'CONTAS BANCÁRIAS'!$B$6:$B$13
Name CARTOES: 'CARTÕES'!$B$6:$B$15
Name CARTAO_LISTA: 'CARTÕES'!$B$6:$B$15
Name LANC_ID: 'LANÇAMENTOS'!$A$6:$A$2005
Name PE_MC_UNIT: 'PONTO DE EQUILÍBRIO'!$B$17
Name PE_RS: 'PONTO DE EQUILÍBRIO'!$B$18
Name PE_QTD: 'PONTO DE EQUILÍBRIO'!$B$19
Name MARGEM_SEGURANCA: 'PONTO DE EQUILÍBRIO'!$B$21
Name RECORRENTES_MES: 'DESPESAS RECORRENTES'!$C$137:$N$137

Sheet PAINEL DE CONTROLE
B2: =IF('CONFIGURAÇÕES'!$B$6="","GESTÃO FINANCEIRA EMPRESARIAL",'CONFIGURAÇÕES'!$B$6)
B4: Sistema completo de gestão financeira: lançamentos, contas a pagar e a receber, fluxo de caixa, DRE gerencial, orçamento, empréstimos, indicadores e dashboard executivo.
B5: ="Hoje: "&TEXT(TODAY(),"DD/MM/YYYY")&" | Ano de análise: "&'CONFIGURAÇÕES'!$B$18&" | Mês de análise: "&IF('CONFIGURAÇÕES'!$B$19=0,"ano completo",TEXT(DATE('CONFIGURAÇÕES'!$B$18,'CONFIGURAÇÕES'!$B$19,1),"MM/YYYY"))&" | Arquivo: Excel (xlsx) e Google Sheets"
B7: SITUAÇÃO ATUAL
B8: Saldo de caixa disponível | D8: Faturamento do mês de análise
B9: =SUM('CONTAS BANCÁRIAS'!$G$6:$G$13)+SUMIFS('LANÇAMENTOS'!$V$6:$V$2005,'LANÇAMENTOS'!$E$6:$E$2005,"Entrada",'LANÇAMENTOS'!$D$6:$D$2005,"<="&TODAY())-SUMIFS('LANÇAMENTOS'!$V$6:$V$2005,'LANÇAMENTOS'!$E$6:$E$2005,"Saída",'LANÇAMENTOS'!$D$6:$D$2005,"<="&TODAY()) | D9: =SUMIFS('LANÇAMENTOS'!$AE$6:$AE$2005,'LANÇAMENTOS'!$AF$6:$AF$2005,"Faturamento Bruto",'LANÇAMENTOS'!$AA$6:$AA$2005,'CONFIGURAÇÕES'!$B$18,'LANÇAMENTOS'!$Z$6:$Z$2005,'CONFIGURAÇÕES'!$B$19)
B11: A receber em aberto | D11: A pagar em aberto
B12: =SUMIFS('LANÇAMENTOS'!$W$6:$W$2005,'LANÇAMENTOS'!$E$6:$E$2005,"Entrada") | D12: =SUMIFS('LANÇAMENTOS'!$W$6:$W$2005,'LANÇAMENTOS'!$E$6:$E$2005,"Saída")
B15: MENU — CLIQUE NAS TELAS ABAIXO PARA NAVEGAR
B16: 📊 DASHBOARD | D16: ✍️ LANÇAR ENTRADA
B17: Visão executiva: cartões, gráficos e alertas. | D17: Registre uma receita na aba LANÇAMENTOS.
B19: ✍️ LANÇAR SAÍDA | D19: 📄 CONTAS A PAGAR
B20: Registre uma despesa na aba LANÇAMENTOS. | D20: Títulos a pagar, aging e prioridades.
B22: 📥 CONTAS A RECEBER | D22: 💧 FLUXO DE CAIXA
B23: Carteira, recebimentos e prazos. | D23: Entradas, saídas, saldos e projeções.
B25: 📈 DRE GERENCIAL | D25: 👥 CLIENTES
B26: Resultado por competência e margens. | D26: Cadastro e indicadores por cliente.
B28: 🏭 FORNECEDORES | D28: 🏦 BANCOS E CARTÕES
B29: Cadastro e indicadores por fornecedor. | D29: Contas, saldos, limites e faturas.
B31: 🧾 RELATÓRIOS | D31: ⚙️ CONFIGURAÇÕES
B32: Relatórios resumidos para imprimir. | D32: Empresa, metas, parâmetros e listas.
B34: Dica: os lançamentos são a base de tudo — cadastre cliente/fornecedor e categoria antes de lançar. Todas as demais abas se atualizam sozinhas.
B36: COMECE POR AQUI — ROTEIRO DE 6 PASSOS
B37: 1. Configurações | C37: Informe os dados da empresa, as metas e o ano/mês de análise. Confira as listas auxiliares que alimentam os menus suspensos.
B38: 2. Cadastros | C38: Cadastre clientes, fornecedores, plano de contas, centros de custo, contas bancárias e cartões.
B39: 3. Lançamentos | C39: Registre todas as entradas e saídas. Use os menus suspensos e preencha as células amarelas; as colunas cinzas são calculadas.
B40: 4. Conferência | C40: Verifique contas a pagar e a receber, a conciliação bancária e a coluna de validação dos lançamentos.
B41: 5. Análise | C41: Acompanhe o dashboard, o DRE, o fluxo de caixa, o orçamento e os indicadores.
B42: 6. Planejamento | C42: Use ponto de equilíbrio, projeção de caixa, simulador de cenários e despesas recorrentes para decidir.
B44: ⚠ Esta planilha acompanha DADOS DE EXEMPLO (empresa fictícia) para você testar todos os recursos. Antes de usar de verdade, apague os dados de exemplo — veja o passo a passo na aba INSTRUÇÕES.
B45: Versão 1.0 — 25 abas — Compatível com Microsoft Excel 2016+ e Google Sheets.

Sheet DASHBOARD
B1: =IF('CONFIGURAÇÕES'!$B$6="","DASHBOARD EXECUTIVO",'CONFIGURAÇÕES'!$B$6&" — DASHBOARD EXECUTIVO")
B3: ="Atualizado em "&TEXT(TODAY(),"DD/MM/YYYY")&" | Ano de análise: "&'CONFIGURAÇÕES'!$B$18&" | Mês de análise: "&IF('CONFIGURAÇÕES'!$B$19=0,"ano completo",TEXT(DATE('CONFIGURAÇÕES'!$B$18,'CONFIGURAÇÕES'!$B$19,1),"MM/AAAA"))&" | Todos os valores são calculados automaticamente a partir da aba LANÇAMENTOS."
B5: 🎛️ FILTROS — altere para analisar o período, o centro de custo, a categoria, a conta ou o tipo de operação
B6: Ano | D6: Mês (0 = ano todo) | F6: Centro de custo | H6: Categoria (subcategoria) | J6: Conta / cartão | L6: Tipo de operação | N6: ="Lançamentos no filtro: "&TEXT($B$146,"#,##0")
B7: ='CONFIGURAÇÕES'!$B$18 | D7: ='CONFIGURAÇÕES'!$B$19 | F7: Todos | H7: Todos | J7: Todos | L7: Todos
B10: 📌 INDICADORES PRINCIPAIS DO PERÍODO FILTRADO
B11: Faturamento do período | D11: Lucro líquido do período | F11: Margem líquida | H11: Saldo de caixa hoje | J11: A receber em aberto | L11: A pagar em aberto | N11: Vencido a receber | P11: Vencido a pagar
B12: =$B$131 | D12: =$B$140 | F12: =$B$141 | H12: =SUM('CONTAS BANCÁRIAS'!$G$6:$G$13)+SUMIFS('LANÇAMENTOS'!$V$6:$V$2005,'LANÇAMENTOS'!$E$6:$E$2005,"Entrada",'LANÇAMENTOS'!$D$6:$D$2005,"<="&TODAY())-SUMIFS('LANÇAMENTOS'!$V$6:$V$2005,'LANÇAMENTOS'!$E$6:$E$2005,"Saída",'LANÇAMENTOS'!$D$6:$D$2005,"<="&TODAY()) | J12: =$B$147 | L12: =$B$148 | N12: =$B$149 | P12: =$B$150
B13: Entradas de caixa do período | D13: Saídas de caixa do período | F13: Geração de caixa do período | H13: Orçado no período | J13: Realizado no período | L13: Consumo do orçamento | N13: Margem de contribuição | P13: Lançamentos no filtro
B14: =$B$142 | D14: =$B$143 | F14: =$B$144 | H14: =$B$151 | J14: =$B$152 | L14: =$B$153 | N14: =$B$139 | P14: =$B$146
B16: 🔔 ATENÇÃO DO GESTOR — SITUAÇÕES QUE EXIGEM DECISÃO
B17: ='INDICADORES'!$A$7 | I17: ='INDICADORES'!$B$7 | L17: ='INDICADORES'!$C$7 | N17: ='INDICADORES'!$A$16 | Q17: ='INDICADORES'!$B$16
B18: ='INDICADORES'!$A$8 | I18: ='INDICADORES'!$B$8 | L18: ='INDICADORES'!$C$8 | N18: ='INDICADORES'!$A$17 | Q18: ='INDICADORES'!$B$17
B19: ='INDICADORES'!$A$9 | I19: ='INDICADORES'!$B$9 | L19: ='INDICADORES'!$C$9 | N19: ='INDICADORES'!$A$18 | Q19: ='INDICADORES'!$B$18
B20: ='INDICADORES'!$A$10 | I20: ='INDICADORES'!$B$10 | L20: ='INDICADORES'!$C$10 | N20: ='INDICADORES'!$A$19 | Q20: ='INDICADORES'!$B$19
B21: ='INDICADORES'!$A$11 | I21: ='INDICADORES'!$B$11 | L21: ='INDICADORES'!$C$11 | N21: ='INDICADORES'!$A$20 | Q21: ='INDICADORES'!$B$20
B22: ='INDICADORES'!$A$12 | I22: ='INDICADORES'!$B$12 | L22: ='INDICADORES'!$C$12 | N22: ='INDICADORES'!$A$21 | Q22: ='INDICADORES'!$B$21
B23: ='INDICADORES'!$A$13 | I23: ='INDICADORES'!$B$13 | L23: ='INDICADORES'!$C$13 | N23: ='INDICADORES'!$A$22 | Q23: ='INDICADORES'!$B$22
B24: ='INDICADORES'!$A$14 | I24: ='INDICADORES'!$B$14 | L24: ='INDICADORES'!$C$14 | N24: ='INDICADORES'!$A$23 | Q24: ='INDICADORES'!$B$23
B25: ='INDICADORES'!$A$15 | I25: ='INDICADORES'!$B$15 | L25: ='INDICADORES'!$C$15 | N25: ='INDICADORES'!$A$24 | Q25: ='INDICADORES'!$B$24
B26: Painel completo com as 18 verificações, valores de referência e ações recomendadas na aba INDICADORES (bloco ATENÇÃO DO GESTOR).
B27: 📋 RESUMO EXECUTIVO DO PERÍODO FILTRADO
B28: Faturamento do período | D28: =$B$131 | F28: Impostos e devoluções | H28: =$B$132 | J28: Receita líquida | L28: =$B$136 | N28: Custos variáveis | P28: =$B$133
B29: Despesas fixas | D29: =$B$134 | F29: Despesas financeiras | H29: =$B$135 | J29: Impostos sobre o lucro | L29: =$B$138 | N29: Lucro líquido | P29: =$B$140
B31: 📈 GRÁFICOS GERENCIAIS — atualizam automaticamente com os lançamentos
B128: ÁREA DE APOIO — CÁLCULOS DO DASHBOARD (não editar; os cartões acima referenciam estas células)
B129: Valor calculado | C129: Linha calculada (base dos cartões acima)
B131: =SUMIFS('LANÇAMENTOS'!$AE$6:$AE$2005,'LANÇAMENTOS'!$AF$6:$AF$2005,"Faturamento Bruto",'LANÇAMENTOS'!$AA$6:$AA$2005,$B$7,'LANÇAMENTOS'!$Z$6:$Z$2005,IF($D$7=0,">0",$D$7),'LANÇAMENTOS'!$H$6:$H$2005,IF($F$7="Todos","*",$F$7),'LANÇAMENTOS'!$G$6:$G$2005,IF($H$7="Todos","*",$H$7),'LANÇAMENTOS'!$L$6:$L$2005,IF($J$7="Todos","*",$J$7),'LANÇAMENTOS'!$E$6:$E$2005,IF($L$7="Todos","*",$L$7)) | C131: Faturamento do período
B132: =SUMIFS('LANÇAMENTOS'!$AE$6:$AE$2005,'LANÇAMENTOS'!$AF$6:$AF$2005,"Impostos sobre Vendas",'LANÇAMENTOS'!$AA$6:$AA$2005,$B$7,'LANÇAMENTOS'!$Z$6:$Z$2005,IF($D$7=0,">0",$D$7),'LANÇAMENTOS'!$H$6:$H$2005,IF($F$7="Todos","*",$F$7),'LANÇAMENTOS'!$G$6:$G$2005,IF($H$7="Todos","*",$H$7),'LANÇAMENTOS'!$L$6:$L$2005,IF($J$7="Todos","*",$J$7),'LANÇAMENTOS'!$E$6:$E$2005,IF($L$7="Todos","*",$L$7))+SUMIFS('LANÇAMENTOS'!$AE$6:$AE$2005,'LANÇAMENTOS'!$AF$6:$AF$2005,"Devoluções",'LANÇAMENTOS'!$AA$6:$AA$2005,$B$7,'LANÇAMENTOS'!$Z$6:$Z$2005,IF($D$7=0,">0",$D$7),'LANÇAMENTOS'!$H$6:$H$2005,IF($F$7="Todos","*",$F$7),'LANÇAMENTOS'!$G$6:$G$2005,IF($H$7="Todos","*",$H$7),'LANÇAMENTOS'!$L$6:$L$2005,IF($J$7="Todos","*",$J$7),'LANÇAMENTOS'!$E$6:$E$2005,IF($L$7="Todos","*",$L$7)) | C132: Impostos e devoluções
B133: =SUMIFS('LANÇAMENTOS'!$AE$6:$AE$2005,'LANÇAMENTOS'!$AF$6:$AF$2005,"Custos Variáveis",'LANÇAMENTOS'!$AA$6:$AA$2005,$B$7,'LANÇAMENTOS'!$Z$6:$Z$2005,IF($D$7=0,">0",$D$7),'LANÇAMENTOS'!$H$6:$H$2005,IF($F$7="Todos","*",$F$7),'LANÇAMENTOS'!$G$6:$G$2005,IF($H$7="Todos","*",$H$7),'LANÇAMENTOS'!$L$6:$L$2005,IF($J$7="Todos","*",$J$7),'LANÇAMENTOS'!$E$6:$E$2005,IF($L$7="Todos","*",$L$7)) | C133: Custos variáveis
B134: =SUMIFS('LANÇAMENTOS'!$AE$6:$AE$2005,'LANÇAMENTOS'!$AF$6:$AF$2005,"Despesas Fixas",'LANÇAMENTOS'!$AA$6:$AA$2005,$B$7,'LANÇAMENTOS'!$Z$6:$Z$2005,IF($D$7=0,">0",$D$7),'LANÇAMENTOS'!$H$6:$H$2005,IF($F$7="Todos","*",$F$7),'LANÇAMENTOS'!$G$6:$G$2005,IF($H$7="Todos","*",$H$7),'LANÇAMENTOS'!$L$6:$L$2005,IF($J$7="Todos","*",$J$7),'LANÇAMENTOS'!$E$6:$E$2005,IF($L$7="Todos","*",$L$7)) | C134: Despesas fixas
B135: =SUMIFS('LANÇAMENTOS'!$AE$6:$AE$2005,'LANÇAMENTOS'!$AF$6:$AF$2005,"Despesas Financeiras",'LANÇAMENTOS'!$AA$6:$AA$2005,$B$7,'LANÇAMENTOS'!$Z$6:$Z$2005,IF($D$7=0,">0",$D$7),'LANÇAMENTOS'!$H$6:$H$2005,IF($F$7="Todos","*",$F$7),'LANÇAMENTOS'!$G$6:$G$2005,IF($H$7="Todos","*",$H$7),'LANÇAMENTOS'!$L$6:$L$2005,IF($J$7="Todos","*",$J$7),'LANÇAMENTOS'!$E$6:$E$2005,IF($L$7="Todos","*",$L$7)) | C135: Despesas financeiras
B136: =$B$131-$B$132 | C136: Receita líquida
B137: =SUMIFS('LANÇAMENTOS'!$AE$6:$AE$2005,'LANÇAMENTOS'!$AF$6:$AF$2005,"Receitas Financeiras",'LANÇAMENTOS'!$AA$6:$AA$2005,$B$7,'LANÇAMENTOS'!$Z$6:$Z$2005,IF($D$7=0,">0",$D$7),'LANÇAMENTOS'!$H$6:$H$2005,IF($F$7="Todos","*",$F$7),'LANÇAMENTOS'!$G$6:$G$2005,IF($H$7="Todos","*",$H$7),'LANÇAMENTOS'!$L$6:$L$2005,IF($J$7="Todos","*",$J$7),'LANÇAMENTOS'!$E$6:$E$2005,IF($L$7="Todos","*",$L$7))+SUMIFS('LANÇAMENTOS'!$AE$6:$AE$2005,'LANÇAMENTOS'!$AF$6:$AF$2005,"Outras Receitas Operacionais",'LANÇAMENTOS'!$AA$6:$AA$2005,$B$7,'LANÇAMENTOS'!$Z$6:$Z$2005,IF($D$7=0,">0",$D$7),'LANÇAMENTOS'!$H$6:$H$2005,IF($F$7="Todos","*",$F$7),'LANÇAMENTOS'!$G$6:$G$2005,IF($H$7="Todos","*",$H$7),'LANÇAMENTOS'!$L$6:$L$2005,IF($J$7="Todos","*",$J$7),'LANÇAMENTOS'!$E$6:$E$2005,IF($L$7="Todos","*",$L$7)) | C137: Receitas financeiras e outras
B138: =SUMIFS('LANÇAMENTOS'!$AE$6:$AE$2005,'LANÇAMENTOS'!$AF$6:$AF$2005,"Impostos sobre o Resultado",'LANÇAMENTOS'!$AA$6:$AA$2005,$B$7,'LANÇAMENTOS'!$Z$6:$Z$2005,IF($D$7=0,">0",$D$7),'LANÇAMENTOS'!$H$6:$H$2005,IF($F$7="Todos","*",$F$7),'LANÇAMENTOS'!$G$6:$G$2005,IF($H$7="Todos","*",$H$7),'LANÇAMENTOS'!$L$6:$L$2005,IF($J$7="Todos","*",$J$7),'LANÇAMENTOS'!$E$6:$E$2005,IF($L$7="Todos","*",$L$7)) | C138: Impostos sobre o lucro
B139: =IFERROR(($B$136-$B$133)/$B$136,"") | C139: Margem de contribuição %
B140: =$B$136-$B$133-$B$134-$B$135+$B$137-$B$138 | C140: Lucro líquido
B141: =IFERROR($B$140/$B$136,"") | C141: Margem líquida %
B142: =SUMIFS('LANÇAMENTOS'!$V$6:$V$2005,'LANÇAMENTOS'!$E$6:$E$2005,"Entrada",'LANÇAMENTOS'!$D$6:$D$2005,">="&DATE($B$7,IF($D$7=0,1,$D$7),1),'LANÇAMENTOS'!$D$6:$D$2005,"<="&IF($D$7=0,DATE($B$7,12,31),EOMONTH(DATE($B$7,$D$7,1),0)),'LANÇAMENTOS'!$H$6:$H$2005,IF($F$7="Todos","*",$F$7),'LANÇAMENTOS'!$G$6:$G$2005,IF($H$7="Todos","*",$H$7),'LANÇAMENTOS'!$L$6:$L$2005,IF($J$7="Todos","*",$J$7)) | C142: Entradas de caixa
B143: =SUMIFS('LANÇAMENTOS'!$V$6:$V$2005,'LANÇAMENTOS'!$E$6:$E$2005,"Saída",'LANÇAMENTOS'!$D$6:$D$2005,">="&DATE($B$7,IF($D$7=0,1,$D$7),1),'LANÇAMENTOS'!$D$6:$D$2005,"<="&IF($D$7=0,DATE($B$7,12,31),EOMONTH(DATE($B$7,$D$7,1),0)),'LANÇAMENTOS'!$H$6:$H$2005,IF($F$7="Todos","*",$F$7),'LANÇAMENTOS'!$G$6:$G$2005,IF($H$7="Todos","*",$H$7),'LANÇAMENTOS'!$L$6:$L$2005,IF($J$7="Todos","*",$J$7)) | C143: Saídas de caixa
B144: =$B$142-$B$143 | C144: Geração de caixa
B145: =$B$136-$B$133 | C145: Margem de contribuição (R$)
B146: =COUNTIFS('LANÇAMENTOS'!$AA$6:$AA$2005,$B$7,'LANÇAMENTOS'!$Z$6:$Z$2005,IF($D$7=0,">0",$D$7),'LANÇAMENTOS'!$H$6:$H$2005,IF($F$7="Todos","*",$F$7),'LANÇAMENTOS'!$G$6:$G$2005,IF($H$7="Todos","*",$H$7),'LANÇAMENTOS'!$L$6:$L$2005,IF($J$7="Todos","*",$J$7),'LANÇAMENTOS'!$E$6:$E$2005,IF($L$7="Todos","*",$L$7)) | C146: Lançamentos no filtro
B147: =SUMIFS('LANÇAMENTOS'!$W$6:$W$2005,'LANÇAMENTOS'!$E$6:$E$2005,"Entrada",'LANÇAMENTOS'!$G$6:$G$2005,IF($H$7="Todos","*",$H$7),'LANÇAMENTOS'!$L$6:$L$2005,IF($J$7="Todos","*",$J$7),'LANÇAMENTOS'!$H$6:$H$2005,IF($F$7="Todos","*",$F$7)) | C147: A receber em aberto
B148: =SUMIFS('LANÇAMENTOS'!$W$6:$W$2005,'LANÇAMENTOS'!$E$6:$E$2005,"Saída",'LANÇAMENTOS'!$G$6:$G$2005,IF($H$7="Todos","*",$H$7),'LANÇAMENTOS'!$L$6:$L$2005,IF($J$7="Todos","*",$J$7),'LANÇAMENTOS'!$H$6:$H$2005,IF($F$7="Todos","*",$F$7)) | C148: A pagar em aberto
B149: =SUMIFS('LANÇAMENTOS'!$W$6:$W$2005,'LANÇAMENTOS'!$E$6:$E$2005,"Entrada",'LANÇAMENTOS'!$W$6:$W$2005,">0",'LANÇAMENTOS'!$C$6:$C$2005,"<"&TODAY(),'LANÇAMENTOS'!$G$6:$G$2005,IF($H$7="Todos","*",$H$7)) | C149: Vencido a receber (títulos em atraso)
B150: =SUMIFS('LANÇAMENTOS'!$W$6:$W$2005,'LANÇAMENTOS'!$E$6:$E$2005,"Saída",'LANÇAMENTOS'!$W$6:$W$2005,">0",'LANÇAMENTOS'!$C$6:$C$2005,"<"&TODAY(),'LANÇAMENTOS'!$G$6:$G$2005,IF($H$7="Todos","*",$H$7)) | C150: Vencido a pagar (títulos em atraso)
B151: =IF($D$7=0,IFERROR(SUM('ORÇAMENTO X REALIZADO'!$O$7:$O$85),0),SUMIF('ORÇAMENTO X REALIZADO'!$B$48:$M$48,$D$7,'ORÇAMENTO X REALIZADO'!$B$49:$M$49)) | C151: Orçado no período
B152: =IF($D$7=0,IFERROR(SUM('ORÇAMENTO X REALIZADO'!$AB$7:$AB$85),0),SUMIF('ORÇAMENTO X REALIZADO'!$B$48:$M$48,$D$7,'ORÇAMENTO X REALIZADO'!$B$50:$M$50)) | C152: Realizado no período
B153: =IFERROR($B$152/$B$151,"") | C153: Consumo do orçamento (%)
B154: Os cartões usam exatamente estas células. Filtros: ano (B7), mês (D7, 0 = ano todo), centro de custo (F7), categoria (H7), conta (J7) e tipo (L7) — use 'Todos' para não filtrar.

Sheet CONFIGURAÇÕES
A1: CONFIGURAÇÕES DO SISTEMA FINANCEIRO
A2: Passo 1 do roteiro: informe os dados da empresa, as metas e os parâmetros. As listas auxiliares (colunas F a X) alimentam todos os menus suspensos da planilha.
A4: 1. IDENTIFICAÇÃO DA EMPRESA
A5: Razão social | B5: AURORA COMÉRCIO DE ALIMENTOS LTDA | E5: Empresa demonstrativa (dados fictícios)
A6: Nome fantasia | B6: Aurora Distribuidora
A7: CNPJ | B7: 12.345.678/0001-90
A8: Segmento de atuação | B8: Distribuição de alimentos e bebidas para revenda
A9: Regime tributário | B9: Simples Nacional | E9: Define o tratamento dos tributos
A10: Responsável financeiro | B10: Jefferson Andrade
A11: E-mail | B11: financeiro@auroradistribuidora.com.br
A12: Telefone | B12: (11) 4002-8922
A14: 2. PERÍODO DE REFERÊNCIA E FILTROS
A15: Data de referência (HOJE — automática) | B15: =TODAY() | E15: Todas as classificações automáticas (vencido, vence hoje, dias em atraso) usam esta data. | G15: Ano/mês de análise
A16: Ano atual | B16: =YEAR($B$15) | G16: B18 e B19 são os parâmetros usados pelo Dashboard e pelas análises.
A17: Mês atual | B17: =MONTH($B$15)
A18: Ano de análise (usado no Dashboard, DRE e relatórios) | B18: 2026
A19: Mês de análise (1 a 12 — 0 = todos os meses) | B19: 9
A21: 3. METAS E PARÂMETROS FINANCEIROS
A22: Meta de faturamento mensal | B22: 230000 | E22: Usada nos alertas de meta de faturamento e no orçamento.
A23: Meta de lucro líquido mensal | B23: 20000 | E23: Base do alerta de meta de lucro.
A24: Margem líquida mínima desejada | B24: 0.1 | E24: Margem abaixo deste valor gera alerta amarelo/vermelho.
A25: Saldo mínimo de caixa | B25: 30000 | E25: Alerta vermelho quando o saldo disponível ficar abaixo deste valor.
A26: Percentual máximo de inadimplência | B26: 0.05 | E26: Alerta quando o vencido a receber superar este percentual.
A27: Prazo médio de recebimento — alvo (dias) | B27: 30 | E27: Compare com o prazo médio real apurado na aba CONTAS A RECEBER.
A28: Prazo médio de pagamento — alvo (dias) | B28: 30 | E28: Compare com o prazo médio real apurado na aba CONTAS A PAGAR.
A29: Alíquota efetiva de impostos sobre vendas | B29: 0.085 | E29: Usada no Simples Nacional, no ponto de equilíbrio e no simulador de cenários.
A30: Taxa de juros mensal padrão (empréstimos) | B30: 0.014 | E30: Sugestão para novos contratos de crédito.
A31: Meta de crescimento mensal do faturamento | B31: 0.02 | E31: Usada na projeção de cenários.
A32: Reserva mínima de capital de giro (meses de despesa fixa) | B32: 2 | E32: Saldo recomendado = reserva × despesas fixas mensais.
A33: 4. LISTAS AUXILIARES — ALIMENTAM OS MENUS SUSPENSOS (para incluir um item, insira uma linha dentro da lista)
F34: Tipo de lançamento | G34: Situação | H34: Forma de pagamento | I34: Tipo de conta | J34: Status (cliente/fornecedor) | K34: Periodicidade | L34: Sistema de amortização | M34: Tipo de fluxo | N34: Bandeira do cartão | O34: Conciliação bancária | P34: Sim / Não | Q34: Regime tributário | R34: UF | S34: Meses | T34: Tipo de operação | U34: Categoria (grupo do plano de contas) | V34: Status do contrato | W34: Linhas do DRE
F36: Entrada | G36: Previsto | H36: Dinheiro | I36: Receita | J36: Ativo | K36: Mensal | L36: PRICE | M36: Operacional | N36: Visa | O36: Conciliado | P36: Sim | Q36: Simples Nacional | R36: AC | S36: Janeiro | T36: Todos | U36: Vendas | V36: Em andamento | W36: Faturamento Bruto
F37: Saída | G37: Pago | H37: PIX | I37: Custo | J37: Inativo | K37: Bimestral | L37: SAC | M37: Investimento | N37: Mastercard | O37: Pendente | P37: Não | Q37: MEI | R37: AL | S37: Fevereiro | T37: Entrada | U37: Outras Receitas | V37: Quitado | W37: Impostos sobre Vendas
G38: Recebido | H38: Transferência | I38: Despesa | J38: Bloqueado | K38: Trimestral | M38: Financiamento | N38: Elo | O38: Divergente | Q38: Lucro Presumido | R38: AM | S38: Março | T38: Saída | U38: Receitas Financeiras | V38: Renegociado | W38: Devoluções
G39: Vencido | H39: Boleto | I39: Imposto | K39: Semestral | N39: American Express | Q39: Lucro Real | R39: AP | S39: Abril | U39: Devoluções e Cancelamentos | V39: Em atraso | W39: Custos Variáveis
G40: Cancelado | H40: Cartão de débito | I40: Investimento | K40: Anual | N40: Hipercard | R40: BA | S40: Maio | U40: Custos Variáveis | W40: Despesas Fixas
G41: Parcial | H41: Cartão de crédito | I41: Pró-labore | N41: Outros | R41: CE | S41: Junho | U41: Despesas Administrativas | W41: Despesas Financeiras
H42: Crédito parcelado | I42: Empréstimo | R42: DF | S42: Julho | U42: Despesas com Pessoal | W42: Receitas Financeiras
H43: Débito automático | I43: Devolução | R43: ES | S43: Agosto | U43: Despesas Comerciais | W43: Outras Receitas Operacionais
H44: Outros | I44: Aporte de Capital | R44: GO | S44: Setembro | U44: Despesas Financeiras | W44: Impostos sobre o Resultado
I45: Distribuição de lucros | R45: MA | S45: Outubro | U45: Tributos | W45: Distribuição de Lucros
R46: MG | S46: Novembro | U46: Investimentos | W46: Investimentos (CAPEX)
R47: MS | S47: Dezembro | U47: Empréstimos e Financiamentos | W47: Financiamentos e Sócios (Principal)
R48: MT | U48: Patrimônio Líquido
R49: PA
R50: PB
R51: PE
R52: PI
R53: PR
R54: RJ
R55: RN
R56: RO
R57: RR
R58: RS
R59: SC
R60: SE
... R62: TO
F68: OBS.: os menus suspensos apontam para os intervalos nomeados acima. Para acrescentar uma opção, insira uma linha dentro da lista (a última linha) — o intervalo nomeado se expande automaticamente.

Sheet CADASTRO DE CLIENTES
A1: CADASTRO DE CLIENTES
A2: Preencha as colunas amarelas. As colunas cinzas (P a W) são calculadas automaticamente a partir da aba LANÇAMENTOS — mantenha a razão social idêntica à usada nos lançamentos.
B4: ⚠ DADOS DE EXEMPLO — os clientes abaixo são fictícios. Substitua pelos seus clientes reais.
A5: Código | B5: Razão social | C5: Nome fantasia | D5: CPF/CNPJ | E5: Telefone | F5: WhatsApp | G5: E-mail | H5: Cidade | I5: UF | J5: Segmento | K5: Vendedor | L5: Limite de crédito | M5: Data de cadastro | N5: Status | O5: Observações | P5: Total comprado | Q5: Qtd. de compras | R5: Ticket médio | S5: Última compra | T5: Valor em aberto | U5: Valor vencido | V5: Dias em atraso (maior) | W5: Situação
A6: CLI001 | B6: MERCADO BOA COMPRA LTDA | C6: Boa Compra Supermercados | D6: 12.345.678/0001-11 | E6: (11) 3456-7890 | F6: (11) 99876-5432 | G6: compras@boacompra.com.br | H6: São Paulo | I6: SP | J6: Supermercados | K6: Carlos Menezes | L6: 90000 | M6: 44997 | N6: Ativo | O6: Cliente âncora — pedidos semanais, boleto 30 dias | P6: =IF($B6="","",SUMIFS('LANÇAMENTOS'!$Q$6:$Q$2005,'LANÇAMENTOS'!$I$6:$I$2005,$B6)+IF($C6=$B6,0,SUMIFS('LANÇAMENTOS'!$Q$6:$Q$2005,'LANÇAMENTOS'!$I$6:$I$2005,$C6))) | Q6: =IF($B6="","",COUNTIFS('LANÇAMENTOS'!$I$6:$I$2005,$B6,'LANÇAMENTOS'!$P$6:$P$2005,1)+IF($C6=$B6,0,COUNTIFS('LANÇAMENTOS'!$I$6:$I$2005,$C6,'LANÇAMENTOS'!$P$6:$P$2005,1))) | R6: =IFERROR(IF($P6=0,"",$P6/$Q6),"") | S6: =IF($B6="","",IFERROR(IF(SUMPRODUCT(MAX(('LANÇAMENTOS'!$I$6:$I$2005=$B6)*'LANÇAMENTOS'!$B$6:$B$2005))>0,SUMPRODUCT(MAX(('LANÇAMENTOS'!$I$6:$I$2005=$B6)*'LANÇAMENTOS'!$B$6:$B$2005)),""),"")) | T6: =IF($B6="","",SUMIFS('LANÇAMENTOS'!$W$6:$W$2005,'LANÇAMENTOS'!$I$6:$I$2005,$B6,'LANÇAMENTOS'!$E$6:$E$2005,"Entrada")+IF($C6=$B6,0,SUMIFS('LANÇAMENTOS'!$W$6:$W$2005,'LANÇAMENTOS'!$I$6:$I$2005,$C6,'LANÇAMENTOS'!$E$6:$E$2005,"Entrada"))) | U6: =IF($B6="","",SUMIFS('LANÇAMENTOS'!$W$6:$W$2005,'LANÇAMENTOS'!$I$6:$I$2005,$B6,'LANÇAMENTOS'!$E$6:$E$2005,"Entrada",'LANÇAMENTOS'!$C$6:$C$2005,"<"&TODAY())+IF($C6=$B6,0,SUMIFS('LANÇAMENTOS'!$W$6:$W$2005,'LANÇAMENTOS'!$I$6:$I$2005,$C6,'LANÇAMENTOS'!$E$6:$E$2005,"Entrada",'LANÇAMENTOS'!$C$6:$C$2005,"<"&TODAY()))) | V6: =IF(OR($B6="",$U6=0),0,MAX(0,TODAY()-IFERROR(-SUMPRODUCT(MAX(('LANÇAMENTOS'!$I$6:$I$2005=$B6)*('LANÇAMENTOS'!$W$6:$W$2005>0)*('LANÇAMENTOS'!$C$6:$C$2005<TODAY())*(-'LANÇAMENTOS'!$C$6:$C$2005))),TODAY()))) | W6: =IF($B6="","",IF($N6="Bloqueado","⛔ Bloqueado",IF($U6>0,"⚠ Com valores vencidos","✔ Em dia")))
A7: CLI002 | B7: PADARIA PÃO DOURADO ME | C7: Pão Dourado | D7: 22.456.789/0001-22 | E7: (11) 2765-4321 | F7: (11) 99765-1122 | G7: financeiro@paodourado.com.br | H7: Santo André | I7: SP | J7: Padarias | K7: Ana Paula Souza | L7: 30000 | M7: 45446 | N7: Ativo | O7: Pagamento à vista (PIX) na entrega | P7: =IF($B7="","",SUMIFS('LANÇAMENTOS'!$Q$6:$Q$2005,'LANÇAMENTOS'!$I$6:$I$2005,$B7)+IF($C7=$B7,0,SUMIFS('LANÇAMENTOS'!$Q$6:$Q$2005,'LANÇAMENTOS'!$I$6:$I$2005,$C7))) | Q7: =IF($B7="","",COUNTIFS('LANÇAMENTOS'!$I$6:$I$2005,$B7,'LANÇAMENTOS'!$P$6:$P$2005,1)+IF($C7=$B7,0,COUNTIFS('LANÇAMENTOS'!$I$6:$I$2005,$C7,'LANÇAMENTOS'!$P$6:$P$2005,1))) | R7: =IFERROR(IF($P7=0,"",$P7/$Q7),"") | S7: =IF($B7="","",IFERROR(IF(SUMPRODUCT(MAX(('LANÇAMENTOS'!$I$6:$I$2005=$B7)*'LANÇAMENTOS'!$B$6:$B$2005))>0,SUMPRODUCT(MAX(('LANÇAMENTOS'!$I$6:$I$2005=$B7)*'LANÇAMENTOS'!$B$6:$B$2005)),""),"")) | T7: =IF($B7="","",SUMIFS('LANÇAMENTOS'!$W$6:$W$2005,'LANÇAMENTOS'!$I$6:$I$2005,$B7,'LANÇAMENTOS'!$E$6:$E$2005,"Entrada")+IF($C7=$B7,0,SUMIFS('LANÇAMENTOS'!$W$6:$W$2005,'LANÇAMENTOS'!$I$6:$I$2005,$C7,'LANÇAMENTOS'!$E$6:$E$2005,"Entrada"))) | U7: =IF($B7="","",SUMIFS('LANÇAMENTOS'!$W$6:$W$2005,'LANÇAMENTOS'!$I$6:$I$2005,$B7,'LANÇAMENTOS'!$E$6:$E$2005,"Entrada",'LANÇAMENTOS'!$C$6:$C$2005,"<"&TODAY())+IF($C7=$B7,0,SUMIFS('LANÇAMENTOS'!$W$6:$W$2005,'LANÇAMENTOS'!$I$6:$I$2005,$C7,'LANÇAMENTOS'!$E$6:$E$2005,"Entrada",'LANÇAMENTOS'!$C$6:$C$2005,"<"&TODAY()))) | V7: =IF(OR($B7="",$U7=0),0,MAX(0,TODAY()-IFERROR(-SUMPRODUCT(MAX(('LANÇAMENTOS'!$I$6:$I$2005=$B7)*('LANÇAMENTOS'!$W$6:$W$2005>0)*('LANÇAMENTOS'!$C$6:$C$2005<TODAY())*(-'LANÇAMENTOS'!$C$6:$C$2005))),TODAY()))) | W7: =IF($B7="","",IF($N7="Bloqueado","⛔ Bloqueado",IF($U7>0,"⚠ Com valores vencidos","✔ Em dia")))
A8: CLI003 | B8: RESTAURANTE SABOR CASEIRO LTDA | C8: Sabor Caseiro | D8: 33.567.890/0001-33 | E8: (11) 3322-1100 | F8: (11) 99654-7788 | G8: contato@saborcaseiro.com.br | H8: São Paulo | I8: SP | J8: Restaurantes | K8: Carlos Menezes | L8: 45000 | M8: 45250 | N8: Ativo | O8: Entrega 2x por semana, boleto 15 dias | P8: =IF($B8="","",SUMIFS('LANÇAMENTOS'!$Q$6:$Q$2005,'LANÇAMENTOS'!$I$6:$I$2005,$B8)+IF($C8=$B8,0,SUMIFS('LANÇAMENTOS'!$Q$6:$Q$2005,'LANÇAMENTOS'!$I$6:$I$2005,$C8))) | Q8: =IF($B8="","",COUNTIFS('LANÇAMENTOS'!$I$6:$I$2005,$B8,'LANÇAMENTOS'!$P$6:$P$2005,1)+IF($C8=$B8,0,COUNTIFS('LANÇAMENTOS'!$I$6:$I$2005,$C8,'LANÇAMENTOS'!$P$6:$P$2005,1))) | R8: =IFERROR(IF($P8=0,"",$P8/$Q8),"") | S8: =IF($B8="","",IFERROR(IF(SUMPRODUCT(MAX(('LANÇAMENTOS'!$I$6:$I$2005=$B8)*'LANÇAMENTOS'!$B$6:$B$2005))>0,SUMPRODUCT(MAX(('LANÇAMENTOS'!$I$6:$I$2005=$B8)*'LANÇAMENTOS'!$B$6:$B$2005)),""),"")) | T8: =IF($B8="","",SUMIFS('LANÇAMENTOS'!$W$6:$W$2005,'LANÇAMENTOS'!$I$6:$I$2005,$B8,'LANÇAMENTOS'!$E$6:$E$2005,"Entrada")+IF($C8=$B8,0,SUMIFS('LANÇAMENTOS'!$W$6:$W$2005,'LANÇAMENTOS'!$I$6:$I$2005,$C8,'LANÇAMENTOS'!$E$6:$E$2005,"Entrada"))) | U8: =IF($B8="","",SUMIFS('LANÇAMENTOS'!$W$6:$W$2005,'LANÇAMENTOS'!$I$6:$I$2005,$B8,'LANÇAMENTOS'!$E$6:$E$2005,"Entrada",'LANÇAMENTOS'!$C$6:$C$2005,"<"&TODAY())+IF($C8=$B8,0,SUMIFS('LANÇAMENTOS'!$W$6:$W$2005,'LANÇAMENTOS'!$I$6:$I$2005,$C8,'LANÇAMENTOS'!$E$6:$E$2005,"Entrada",'LANÇAMENTOS'!$C$6:$C$2005,"<"&TODAY()))) | V8: =IF(OR($B8="",$U8=0),0,MAX(0,TODAY()-IFERROR(-SUMPRODUCT(MAX(('LANÇAMENTOS'!$I$6:$I$2005=$B8)*('LANÇAMENTOS'!$W$6:$W$2005>0)*('LANÇAMENTOS'!$C$6:$C$2005<TODAY())*(-'LANÇAMENTOS'!$C$6:$C$2005))),TODAY()))) | W8: =IF($B8="","",IF($N8="Bloqueado","⛔ Bloqueado",IF($U8>0,"⚠ Com valores vencidos","✔ Em dia")))
A9: CLI004 | B9: HOTEL VISTA ALEGRE LTDA | C9: Hotel Vista Alegre | D9: 44.678.901/0001-44 | E9: (11) 2222-3344 | F9: (11) 99555-2211 | G9: compras@vistaalegrehotel.com.br | H9: Guarulhos | I9: SP | J9: Hotelaria | K9: Ana Paula Souza | L9: 50000 | M9: 45306 | N9: Bloqueado | O9: INADIMPLENTE — 3 faturas vencidas; bloqueado para novas vendas a prazo | P9: =IF($B9="","",SUMIFS('LANÇAMENTOS'!$Q$6:$Q$2005,'LANÇAMENTOS'!$I$6:$I$2005,$B9)+IF($C9=$B9,0,SUMIFS('LANÇAMENTOS'!$Q$6:$Q$2005,'LANÇAMENTOS'!$I$6:$I$2005,$C9))) | Q9: =IF($B9="","",COUNTIFS('LANÇAMENTOS'!$I$6:$I$2005,$B9,'LANÇAMENTOS'!$P$6:$P$2005,1)+IF($C9=$B9,0,COUNTIFS('LANÇAMENTOS'!$I$6:$I$2005,$C9,'LANÇAMENTOS'!$P$6:$P$2005,1))) | R9: =IFERROR(IF($P9=0,"",$P9/$Q9),"") | S9: =IF($B9="","",IFERROR(IF(SUMPRODUCT(MAX(('LANÇAMENTOS'!$I$6:$I$2005=$B9)*'LANÇAMENTOS'!$B$6:$B$2005))>0,SUMPRODUCT(MAX(('LANÇAMENTOS'!$I$6:$I$2005=$B9)*'LANÇAMENTOS'!$B$6:$B$2005)),""),"")) | T9: =IF($B9="","",SUMIFS('LANÇAMENTOS'!$W$6:$W$2005,'LANÇAMENTOS'!$I$6:$I$2005,$B9,'LANÇAMENTOS'!$E$6:$E$2005,"Entrada")+IF($C9=$B9,0,SUMIFS('LANÇAMENTOS'!$W$6:$W$2005,'LANÇAMENTOS'!$I$6:$I$2005,$C9,'LANÇAMENTOS'!$E$6:$E$2005,"Entrada"))) | U9: =IF($B9="","",SUMIFS('LANÇAMENTOS'!$W$6:$W$2005,'LANÇAMENTOS'!$I$6:$I$2005,$B9,'LANÇAMENTOS'!$E$6:$E$2005,"Entrada",'LANÇAMENTOS'!$C$6:$C$2005,"<"&TODAY())+IF($C9=$B9,0,SUMIFS('LANÇAMENTOS'!$W$6:$W$2005,'LANÇAMENTOS'!$I$6:$I$2005,$C9,'LANÇAMENTOS'!$E$6:$E$2005,"Entrada",'LANÇAMENTOS'!$C$6:$C$2005,"<"&TODAY()))) | V9: =IF(OR($B9="",$U9=0),0,MAX(0,TODAY()-IFERROR(-SUMPRODUCT(MAX(('LANÇAMENTOS'!$I$6:$I$2005=$B9)*('LANÇAMENTOS'!$W$6:$W$2005>0)*('LANÇAMENTOS'!$C$6:$C$2005<TODAY())*(-'LANÇAMENTOS'!$C$6:$C$2005))),TODAY()))) | W9: =IF($B9="","",IF($N9="Bloqueado","⛔ Bloqueado",IF($U9>0,"⚠ Com valores vencidos","✔ Em dia")))
A10: CLI005 | B10: EMPÓRIO NATURAL COMÉRCIO LTDA | C10: Empório Natural | D10: 55.789.012/0001-55 | E10: (11) 4002-7788 | F10: (11) 99444-3322 | G10: suprimentos@emporionatural.com.br | H10: Osasco | I10: SP | J10: Varejo de Alimentos | K10: Carlos Menezes | L10: 60000 | M10: 45543 | N10: Ativo | O10: Compras parceladas em 2x/3x — acompanhar limite | P10: =IF($B10="","",SUMIFS('LANÇAMENTOS'!$Q$6:$Q$2005,'LANÇAMENTOS'!$I$6:$I$2005,$B10)+IF($C10=$B10,0,SUMIFS('LANÇAMENTOS'!$Q$6:$Q$2005,'LANÇAMENTOS'!$I$6:$I$2005,$C10))) | Q10: =IF($B10="","",COUNTIFS('LANÇAMENTOS'!$I$6:$I$2005,$B10,'LANÇAMENTOS'!$P$6:$P$2005,1)+IF($C10=$B10,0,COUNTIFS('LANÇAMENTOS'!$I$6:$I$2005,$C10,'LANÇAMENTOS'!$P$6:$P$2005,1))) | R10: =IFERROR(IF($P10=0,"",$P10/$Q10),"") | S10: =IF($B10="","",IFERROR(IF(SUMPRODUCT(MAX(('LANÇAMENTOS'!$I$6:$I$2005=$B10)*'LANÇAMENTOS'!$B$6:$B$2005))>0,SUMPRODUCT(MAX(('LANÇAMENTOS'!$I$6:$I$2005=$B10)*'LANÇAMENTOS'!$B$6:$B$2005)),""),"")) | T10: =IF($B10="","",SUMIFS('LANÇAMENTOS'!$W$6:$W$2005,'LANÇAMENTOS'!$I$6:$I$2005,$B10,'LANÇAMENTOS'!$E$6:$E$2005,"Entrada")+IF($C10=$B10,0,SUMIFS('LANÇAMENTOS'!$W$6:$W$2005,'LANÇAMENTOS'!$I$6:$I$2005,$C10,'LANÇAMENTOS'!$E$6:$E$2005,"Entrada"))) | U10: =IF($B10="","",SUMIFS('LANÇAMENTOS'!$W$6:$W$2005,'LANÇAMENTOS'!$I$6:$I$2005,$B10,'LANÇAMENTOS'!$E$6:$E$2005,"Entrada",'LANÇAMENTOS'!$C$6:$C$2005,"<"&TODAY())+IF($C10=$B10,0,SUMIFS('LANÇAMENTOS'!$W$6:$W$2005,'LANÇAMENTOS'!$I$6:$I$2005,$C10,'LANÇAMENTOS'!$E$6:$E$2005,"Entrada",'LANÇAMENTOS'!$C$6:$C$2005,"<"&TODAY()))) | V10: =IF(OR($B10="",$U10=0),0,MAX(0,TODAY()-IFERROR(-SUMPRODUCT(MAX(('LANÇAMENTOS'!$I$6:$I$2005=$B10)*('LANÇAMENTOS'!$W$6:$W$2005>0)*('LANÇAMENTOS'!$C$6:$C$2005<TODAY())*(-'LANÇAMENTOS'!$C$6:$C$2005))),TODAY()))) | W10: =IF($B10="","",IF($N10="Bloqueado","⛔ Bloqueado",IF($U10>0,"⚠ Com valores vencidos","✔ Em dia")))
P11: =IF($B11="","",SUMIFS('LANÇAMENTOS'!$Q$6:$Q$2005,'LANÇAMENTOS'!$I$6:$I$2005,$B11)+IF($C11=$B11,0,SUMIFS('LANÇAMENTOS'!$Q$6:$Q$2005,'LANÇAMENTOS'!$I$6:$I$2005,$C11))) | Q11: =IF($B11="","",COUNTIFS('LANÇAMENTOS'!$I$6:$I$2005,$B11,'LANÇAMENTOS'!$P$6:$P$2005,1)+IF($C11=$B11,0,COUNTIFS('LANÇAMENTOS'!$I$6:$I$2005,$C11,'LANÇAMENTOS'!$P$6:$P$2005,1))) | R11: =IFERROR(IF($P11=0,"",$P11/$Q11),"") | S11: =IF($B11="","",IFERROR(IF(SUMPRODUCT(MAX(('LANÇAMENTOS'!$I$6:$I$2005=$B11)*'LANÇAMENTOS'!$B$6:$B$2005))>0,SUMPRODUCT(MAX(('LANÇAMENTOS'!$I$6:$I$2005=$B11)*'LANÇAMENTOS'!$B$6:$B$2005)),""),"")) | T11: =IF($B11="","",SUMIFS('LANÇAMENTOS'!$W$6:$W$2005,'LANÇAMENTOS'!$I$6:$I$2005,$B11,'LANÇAMENTOS'!$E$6:$E$2005,"Entrada")+IF($C11=$B11,0,SUMIFS('LANÇAMENTOS'!$W$6:$W$2005,'LANÇAMENTOS'!$I$6:$I$2005,$C11,'LANÇAMENTOS'!$E$6:$E$2005,"Entrada"))) | U11: =IF($B11="","",SUMIFS('LANÇAMENTOS'!$W$6:$W$2005,'LANÇAMENTOS'!$I$6:$I$2005,$B11,'LANÇAMENTOS'!$E$6:$E$2005,"Entrada",'LANÇAMENTOS'!$C$6:$C$2005,"<"&TODAY())+IF($C11=$B11,0,SUMIFS('LANÇAMENTOS'!$W$6:$W$2005,'LANÇAMENTOS'!$I$6:$I$2005,$C11,'LANÇAMENTOS'!$E$6:$E$2005,"Entrada",'LANÇAMENTOS'!$C$6:$C$2005,"<"&TODAY()))) | V11: =IF(OR($B11="",$U11=0),0,MAX(0,TODAY()-IFERROR(-SUMPRODUCT(MAX(('LANÇAMENTOS'!$I$6:$I$2005=$B11)*('LANÇAMENTOS'!$W$6:$W$2005>0)*('LANÇAMENTOS'!$C$6:$C$2005<TODAY())*(-'LANÇAMENTOS'!$C$6:$C$2005))),TODAY()))) | W11: =IF($B11="","",IF($N11="Bloqueado","⛔ Bloqueado",IF($U11>0,"⚠ Com valores vencidos","✔ Em dia")))
P12: =IF($B12="","",SUMIFS('LANÇAMENTOS'!$Q$6:$Q$2005,'LANÇAMENTOS'!$I$6:$I$2005,$B12)+IF($C12=$B12,0,SUMIFS('LANÇAMENTOS'!$Q$6:$Q$2005,'LANÇAMENTOS'!$I$6:$I$2005,$C12))) | Q12: =IF($B12="","",COUNTIFS('LANÇAMENTOS'!$I$6:$I$2005,$B12,'LANÇAMENTOS'!$P$6:$P$2005,1)+IF($C12=$B12,0,COUNTIFS('LANÇAMENTOS'!$I$6:$I$2005,$C12,'LANÇAMENTOS'!$P$6:$P$2005,1))) | R12: =IFERROR(IF($P12=0,"",$P12/$Q12),"") | S12: =IF($B12="","",IFERROR(IF(SUMPRODUCT(MAX(('LANÇAMENTOS'!$I$6:$I$2005=$B12)*'LANÇAMENTOS'!$B$6:$B$2005))>0,SUMPRODUCT(MAX(('LANÇAMENTOS'!$I$6:$I$2005=$B12)*'LANÇAMENTOS'!$B$6:$B$2005)),""),"")) | T12: =IF($B12="","",SUMIFS('LANÇAMENTOS'!$W$6:$W$2005,'LANÇAMENTOS'!$I$6:$I$2005,$B12,'LANÇAMENTOS'!$E$6:$E$2005,"Entrada")+IF($C12=$B12,0,SUMIFS('LANÇAMENTOS'!$W$6:$W$2005,'LANÇAMENTOS'!$I$6:$I$2005,$C12,'LANÇAMENTOS'!$E$6:$E$2005,"Entrada"))) | U12: =IF($B12="","",SUMIFS('LANÇAMENTOS'!$W$6:$W$2005,'LANÇAMENTOS'!$I$6:$I$2005,$B12,'LANÇAMENTOS'!$E$6:$E$2005,"Entrada",'LANÇAMENTOS'!$C$6:$C$2005,"<"&TODAY())+IF($C12=$B12,0,SUMIFS('LANÇAMENTOS'!$W$6:$W$2005,'LANÇAMENTOS'!$I$6:$I$2005,$C12,'LANÇAMENTOS'!$E$6:$E$2005,"Entrada",'LANÇAMENTOS'!$C$6:$C$2005,"<"&TODAY()))) | V12: =IF(OR($B12="",$U12=0),0,MAX(0,TODAY()-IFERROR(-SUMPRODUCT(MAX(('LANÇAMENTOS'!$I$6:$I$2005=$B12)*('LANÇAMENTOS'!$W$6:$W$2005>0)*('LANÇAMENTOS'!$C$6:$C$2005<TODAY())*(-'LANÇAMENTOS'!$C$6:$C$2005))),TODAY()))) | W12: =IF($B12="","",IF($N12="Bloqueado","⛔ Bloqueado",IF($U12>0,"⚠ Com valores vencidos","✔ Em dia")))
P13: =IF($B13="","",SUMIFS('LANÇAMENTOS'!$Q$6:$Q$2005,'LANÇAMENTOS'!$I$6:$I$2005,$B13)+IF($C13=$B13,0,SUMIFS('LANÇAMENTOS'!$Q$6:$Q$2005,'LANÇAMENTOS'!$I$6:$I$2005,$C13))) | Q13: =IF($B13="","",COUNTIFS('LANÇAMENTOS'!$I$6:$I$2005,$B13,'LANÇAMENTOS'!$P$6:$P$2005,1)+IF($C13=$B13,0,COUNTIFS('LANÇAMENTOS'!$I$6:$I$2005,$C13,'LANÇAMENTOS'!$P$6:$P$2005,1))) | R13: =IFERROR(IF($P13=0,"",$P13/$Q13),"") | S13: =IF($B13="","",IFERROR(IF(SUMPRODUCT(MAX(('LANÇAMENTOS'!$I$6:$I$2005=$B13)*'LANÇAMENTOS'!$B$6:$B$2005))>0,SUMPRODUCT(MAX(('LANÇAMENTOS'!$I$6:$I$2005=$B13)*'LANÇAMENTOS'!$B$6:$B$2005)),""),"")) | T13: =IF($B13="","",SUMIFS('LANÇAMENTOS'!$W$6:$W$2005,'LANÇAMENTOS'!$I$6:$I$2005,$B13,'LANÇAMENTOS'!$E$6:$E$2005,"Entrada")+IF($C13=$B13,0,SUMIFS('LANÇAMENTOS'!$W$6:$W$2005,'LANÇAMENTOS'!$I$6:$I$2005,$C13,'LANÇAMENTOS'!$E$6:$E$2005,"Entrada"))) | U13: =IF($B13="","",SUMIFS('LANÇAMENTOS'!$W$6:$W$2005,'LANÇAMENTOS'!$I$6:$I$2005,$B13,'LANÇAMENTOS'!$E$6:$E$2005,"Entrada",'LANÇAMENTOS'!$C$6:$C$2005,"<"&TODAY())+IF($C13=$B13,0,SUMIFS('LANÇAMENTOS'!$W$6:$W$2005,'LANÇAMENTOS'!$I$6:$I$2005,$C13,'LANÇAMENTOS'!$E$6:$E$2005,"Entrada",'LANÇAMENTOS'!$C$6:$C$2005,"<"&TODAY()))) | V13: =IF(OR($B13="",$U13=0),0,MAX(0,TODAY()-IFERROR(-SUMPRODUCT(MAX(('LANÇAMENTOS'!$I$6:$I$2005=$B13)*('LANÇAMENTOS'!$W$6:$W$2005>0)*('LANÇAMENTOS'!$C$6:$C$2005<TODAY())*(-'LANÇAMENTOS'!$C$6:$C$2005))),TODAY()))) | W13: =IF($B13="","",IF($N13="Bloqueado","⛔ Bloqueado",IF($U13>0,"⚠ Com valores vencidos","✔ Em dia")))
P14: =IF($B14="","",SUMIFS('LANÇAMENTOS'!$Q$6:$Q$2005,'LANÇAMENTOS'!$I$6:$I$2005,$B14)+IF($C14=$B14,0,SUMIFS('LANÇAMENTOS'!$Q$6:$Q$2005,'LANÇAMENTOS'!$I$6:$I$2005,$C14))) | Q14: =IF($B14="","",COUNTIFS('LANÇAMENTOS'!$I$6:$I$2005,$B14,'LANÇAMENTOS'!$P$6:$P$2005,1)+IF($C14=$B14,0,COUNTIFS('LANÇAMENTOS'!$I$6:$I$2005,$C14,'LANÇAMENTOS'!$P$6:$P$2005,1))) | R14: =IFERROR(IF($P14=0,"",$P14/$Q14),"") | S14: =IF($B14="","",IFERROR(IF(SUMPRODUCT(MAX(('LANÇAMENTOS'!$I$6:$I$2005=$B14)*'LANÇAMENTOS'!$B$6:$B$2005))>0,SUMPRODUCT(MAX(('LANÇAMENTOS'!$I$6:$I$2005=$B14)*'LANÇAMENTOS'!$B$6:$B$2005)),""),"")) | T14: =IF($B14="","",SUMIFS('LANÇAMENTOS'!$W$6:$W$2005,'LANÇAMENTOS'!$I$6:$I$2005,$B14,'LANÇAMENTOS'!$E$6:$E$2005,"Entrada")+IF($C14=$B14,0,SUMIFS('LANÇAMENTOS'!$W$6:$W$2005,'LANÇAMENTOS'!$I$6:$I$2005,$C14,'LANÇAMENTOS'!$E$6:$E$2005,"Entrada"))) | U14: =IF($B14="","",SUMIFS('LANÇAMENTOS'!$W$6:$W$2005,'LANÇAMENTOS'!$I$6:$I$2005,$B14,'LANÇAMENTOS'!$E$6:$E$2005,"Entrada",'LANÇAMENTOS'!$C$6:$C$2005,"<"&TODAY())+IF($C14=$B14,0,SUMIFS('LANÇAMENTOS'!$W$6:$W$2005,'LANÇAMENTOS'!$I$6:$I$2005,$C14,'LANÇAMENTOS'!$E$6:$E$2005,"Entrada",'LANÇAMENTOS'!$C$6:$C$2005,"<"&TODAY()))) | V14: =IF(OR($B14="",$U14=0),0,MAX(0,TODAY()-IFERROR(-SUMPRODUCT(MAX(('LANÇAMENTOS'!$I$6:$I$2005=$B14)*('LANÇAMENTOS'!$W$6:$W$2005>0)*('LANÇAMENTOS'!$C$6:$C$2005<TODAY())*(-'LANÇAMENTOS'!$C$6:$C$2005))),TODAY()))) | W14: =IF($B14="","",IF($N14="Bloqueado","⛔ Bloqueado",IF($U14>0,"⚠ Com valores vencidos","✔ Em dia")))
P15: =IF($B15="","",SUMIFS('LANÇAMENTOS'!$Q$6:$Q$2005,'LANÇAMENTOS'!$I$6:$I$2005,$B15)+IF($C15=$B15,0,SUMIFS('LANÇAMENTOS'!$Q$6:$Q$2005,'LANÇAMENTOS'!$I$6:$I$2005,$C15))) | Q15: =IF($B15="","",COUNTIFS('LANÇAMENTOS'!$I$6:$I$2005,$B15,'LANÇAMENTOS'!$P$6:$P$2005,1)+IF($C15=$B15,0,COUNTIFS('LANÇAMENTOS'!$I$6:$I$2005,$C15,'LANÇAMENTOS'!$P$6:$P$2005,1))) | R15: =IFERROR(IF($P15=0,"",$P15/$Q15),"") | S15: =IF($B15="","",IFERROR(IF(SUMPRODUCT(MAX(('LANÇAMENTOS'!$I$6:$I$2005=$B15)*'LANÇAMENTOS'!$B$6:$B$2005))>0,SUMPRODUCT(MAX(('LANÇAMENTOS'!$I$6:$I$2005=$B15)*'LANÇAMENTOS'!$B$6:$B$2005)),""),"")) | T15: =IF($B15="","",SUMIFS('LANÇAMENTOS'!$W$6:$W$2005,'LANÇAMENTOS'!$I$6:$I$2005,$B15,'LANÇAMENTOS'!$E$6:$E$2005,"Entrada")+IF($C15=$B15,0,SUMIFS('LANÇAMENTOS'!$W$6:$W$2005,'LANÇAMENTOS'!$I$6:$I$2005,$C15,'LANÇAMENTOS'!$E$6:$E$2005,"Entrada"))) | U15: =IF($B15="","",SUMIFS('LANÇAMENTOS'!$W$6:$W$2005,'LANÇAMENTOS'!$I$6:$I$2005,$B15,'LANÇAMENTOS'!$E$6:$E$2005,"Entrada",'LANÇAMENTOS'!$C$6:$C$2005,"<"&TODAY())+IF($C15=$B15,0,SUMIFS('LANÇAMENTOS'!$W$6:$W$2005,'LANÇAMENTOS'!$I$6:$I$2005,$C15,'LANÇAMENTOS'!$E$6:$E$2005,"Entrada",'LANÇAMENTOS'!$C$6:$C$2005,"<"&TODAY()))) | V15: =IF(OR($B15="",$U15=0),0,MAX(0,TODAY()-IFERROR(-SUMPRODUCT(MAX(('LANÇAMENTOS'!$I$6:$I$2005=$B15)*('LANÇAMENTOS'!$W$6:$W$2005>0)*('LANÇAMENTOS'!$C$6:$C$2005<TODAY())*(-'LANÇAMENTOS'!$C$6:$C$2005))),TODAY()))) | W15: =IF($B15="","",IF($N15="Bloqueado","⛔ Bloqueado",IF($U15>0,"⚠ Com valores vencidos","✔ Em dia")))
P16: =IF($B16="","",SUMIFS('LANÇAMENTOS'!$Q$6:$Q$2005,'LANÇAMENTOS'!$I$6:$I$2005,$B16)+IF($C16=$B16,0,SUMIFS('LANÇAMENTOS'!$Q$6:$Q$2005,'LANÇAMENTOS'!$I$6:$I$2005,$C16))) | Q16: =IF($B16="","",COUNTIFS('LANÇAMENTOS'!$I$6:$I$2005,$B16,'LANÇAMENTOS'!$P$6:$P$2005,1)+IF($C16=$B16,0,COUNTIFS('LANÇAMENTOS'!$I$6:$I$2005,$C16,'LANÇAMENTOS'!$P$6:$P$2005,1))) | R16: =IFERROR(IF($P16=0,"",$P16/$Q16),"") | S16: =IF($B16="","",IFERROR(IF(SUMPRODUCT(MAX(('LANÇAMENTOS'!$I$6:$I$2005=$B16)*'LANÇAMENTOS'!$B$6:$B$2005))>0,SUMPRODUCT(MAX(('LANÇAMENTOS'!$I$6:$I$2005=$B16)*'LANÇAMENTOS'!$B$6:$B$2005)),""),"")) | T16: =IF($B16="","",SUMIFS('LANÇAMENTOS'!$W$6:$W$2005,'LANÇAMENTOS'!$I$6:$I$2005,$B16,'LANÇAMENTOS'!$E$6:$E$2005,"Entrada")+IF($C16=$B16,0,SUMIFS('LANÇAMENTOS'!$W$6:$W$2005,'LANÇAMENTOS'!$I$6:$I$2005,$C16,'LANÇAMENTOS'!$E$6:$E$2005,"Entrada"))) | U16: =IF($B16="","",SUMIFS('LANÇAMENTOS'!$W$6:$W$2005,'LANÇAMENTOS'!$I$6:$I$2005,$B16,'LANÇAMENTOS'!$E$6:$E$2005,"Entrada",'LANÇAMENTOS'!$C$6:$C$2005,"<"&TODAY())+IF($C16=$B16,0,SUMIFS('LANÇAMENTOS'!$W$6:$W$2005,'LANÇAMENTOS'!$I$6:$I$2005,$C16,'LANÇAMENTOS'!$E$6:$E$2005,"Entrada",'LANÇAMENTOS'!$C$6:$C$2005,"<"&TODAY()))) | V16: =IF(OR($B16="",$U16=0),0,MAX(0,TODAY()-IFERROR(-SUMPRODUCT(MAX(('LANÇAMENTOS'!$I$6:$I$2005=$B16)*('LANÇAMENTOS'!$W$6:$W$2005>0)*('LANÇAMENTOS'!$C$6:$C$2005<TODAY())*(-'LANÇAMENTOS'!$C$6:$C$2005))),TODAY()))) | W16: =IF($B16="","",IF($N16="Bloqueado","⛔ Bloqueado",IF($U16>0,"⚠ Com valores vencidos","✔ Em dia")))
P17: =IF($B17="","",SUMIFS('LANÇAMENTOS'!$Q$6:$Q$2005,'LANÇAMENTOS'!$I$6:$I$2005,$B17)+IF($C17=$B17,0,SUMIFS('LANÇAMENTOS'!$Q$6:$Q$2005,'LANÇAMENTOS'!$I$6:$I$2005,$C17))) | Q17: =IF($B17="","",COUNTIFS('LANÇAMENTOS'!$I$6:$I$2005,$B17,'LANÇAMENTOS'!$P$6:$P$2005,1)+IF($C17=$B17,0,COUNTIFS('LANÇAMENTOS'!$I$6:$I$2005,$C17,'LANÇAMENTOS'!$P$6:$P$2005,1))) | R17: =IFERROR(IF($P17=0,"",$P17/$Q17),"") | S17: =IF($B17="","",IFERROR(IF(SUMPRODUCT(MAX(('LANÇAMENTOS'!$I$6:$I$2005=$B17)*'LANÇAMENTOS'!$B$6:$B$2005))>0,SUMPRODUCT(MAX(('LANÇAMENTOS'!$I$6:$I$2005=$B17)*'LANÇAMENTOS'!$B$6:$B$2005)),""),"")) | T17: =IF($B17="","",SUMIFS('LANÇAMENTOS'!$W$6:$W$2005,'LANÇAMENTOS'!$I$6:$I$2005,$B17,'LANÇAMENTOS'!$E$6:$E$2005,"Entrada")+IF($C17=$B17,0,SUMIFS('LANÇAMENTOS'!$W$6:$W$2005,'LANÇAMENTOS'!$I$6:$I$2005,$C17,'LANÇAMENTOS'!$E$6:$E$2005,"Entrada"))) | U17: =IF($B17="","",SUMIFS('LANÇAMENTOS'!$W$6:$W$2005,'LANÇAMENTOS'!$I$6:$I$2005,$B17,'LANÇAMENTOS'!$E$6:$E$2005,"Entrada",'LANÇAMENTOS'!$C$6:$C$2005,"<"&TODAY())+IF($C17=$B17,0,SUMIFS('LANÇAMENTOS'!$W$6:$W$2005,'LANÇAMENTOS'!$I$6:$I$2005,$C17,'LANÇAMENTOS'!$E$6:$E$2005,"Entrada",'LANÇAMENTOS'!$C$6:$C$2005,"<"&TODAY()))) | V17: =IF(OR($B17="",$U17=0),0,MAX(0,TODAY()-IFERROR(-SUMPRODUCT(MAX(('LANÇAMENTOS'!$I$6:$I$2005=$B17)*('LANÇAMENTOS'!$W$6:$W$2005>0)*('LANÇAMENTOS'!$C$6:$C$2005<TODAY())*(-'LANÇAMENTOS'!$C$6:$C$2005))),TODAY()))) | W17: =IF($B17="","",IF($N17="Bloqueado","⛔ Bloqueado",IF($U17>0,"⚠ Com valores vencidos","✔ Em dia")))
P18: =IF($B18="","",SUMIFS('LANÇAMENTOS'!$Q$6:$Q$2005,'LANÇAMENTOS'!$I$6:$I$2005,$B18)+IF($C18=$B18,0,SUMIFS('LANÇAMENTOS'!$Q$6:$Q$2005,'LANÇAMENTOS'!$I$6:$I$2005,$C18))) | Q18: =IF($B18="","",COUNTIFS('LANÇAMENTOS'!$I$6:$I$2005,$B18,'LANÇAMENTOS'!$P$6:$P$2005,1)+IF($C18=$B18,0,COUNTIFS('LANÇAMENTOS'!$I$6:$I$2005,$C18,'LANÇAMENTOS'!$P$6:$P$2005,1))) | R18: =IFERROR(IF($P18=0,"",$P18/$Q18),"") | S18: =IF($B18="","",IFERROR(IF(SUMPRODUCT(MAX(('LANÇAMENTOS'!$I$6:$I$2005=$B18)*'LANÇAMENTOS'!$B$6:$B$2005))>0,SUMPRODUCT(MAX(('LANÇAMENTOS'!$I$6:$I$2005=$B18)*'LANÇAMENTOS'!$B$6:$B$2005)),""),"")) | T18: =IF($B18="","",SUMIFS('LANÇAMENTOS'!$W$6:$W$2005,'LANÇAMENTOS'!$I$6:$I$2005,$B18,'LANÇAMENTOS'!$E$6:$E$2005,"Entrada")+IF($C18=$B18,0,SUMIFS('LANÇAMENTOS'!$W$6:$W$2005,'LANÇAMENTOS'!$I$6:$I$2005,$C18,'LANÇAMENTOS'!$E$6:$E$2005,"Entrada"))) | U18: =IF($B18="","",SUMIFS('LANÇAMENTOS'!$W$6:$W$2005,'LANÇAMENTOS'!$I$6:$I$2005,$B18,'LANÇAMENTOS'!$E$6:$E$2005,"Entrada",'LANÇAMENTOS'!$C$6:$C$2005,"<"&TODAY())+IF($C18=$B18,0,SUMIFS('LANÇAMENTOS'!$W$6:$W$2005,'LANÇAMENTOS'!$I$6:$I$2005,$C18,'LANÇAMENTOS'!$E$6:$E$2005,"Entrada",'LANÇAMENTOS'!$C$6:$C$2005,"<"&TODAY()))) | V18: =IF(OR($B18="",$U18=0),0,MAX(0,TODAY()-IFERROR(-SUMPRODUCT(MAX(('LANÇAMENTOS'!$I$6:$I$2005=$B18)*('LANÇAMENTOS'!$W$6:$W$2005>0)*('LANÇAMENTOS'!$C$6:$C$2005<TODAY())*(-'LANÇAMENTOS'!$C$6:$C$2005))),TODAY()))) | W18: =IF($B18="","",IF($N18="Bloqueado","⛔ Bloqueado",IF($U18>0,"⚠ Com valores vencidos","✔ Em dia")))
P19: =IF($B19="","",SUMIFS('LANÇAMENTOS'!$Q$6:$Q$2005,'LANÇAMENTOS'!$I$6:$I$2005,$B19)+IF($C19=$B19,0,SUMIFS('LANÇAMENTOS'!$Q$6:$Q$2005,'LANÇAMENTOS'!$I$6:$I$2005,$C19))) | Q19: =IF($B19="","",COUNTIFS('LANÇAMENTOS'!$I$6:$I$2005,$B19,'LANÇAMENTOS'!$P$6:$P$2005,1)+IF($C19=$B19,0,COUNTIFS('LANÇAMENTOS'!$I$6:$I$2005,$C19,'LANÇAMENTOS'!$P$6:$P$2005,1))) | R19: =IFERROR(IF($P19=0,"",$P19/$Q19),"") | S19: =IF($B19="","",IFERROR(IF(SUMPRODUCT(MAX(('LANÇAMENTOS'!$I$6:$I$2005=$B19)*'LANÇAMENTOS'!$B$6:$B$2005))>0,SUMPRODUCT(MAX(('LANÇAMENTOS'!$I$6:$I$2005=$B19)*'LANÇAMENTOS'!$B$6:$B$2005)),""),"")) | T19: =IF($B19="","",SUMIFS('LANÇAMENTOS'!$W$6:$W$2005,'LANÇAMENTOS'!$I$6:$I$2005,$B19,'LANÇAMENTOS'!$E$6:$E$2005,"Entrada")+IF($C19=$B19,0,SUMIFS('LANÇAMENTOS'!$W$6:$W$2005,'LANÇAMENTOS'!$I$6:$I$2005,$C19,'LANÇAMENTOS'!$E$6:$E$2005,"Entrada"))) | U19: =IF($B19="","",SUMIFS('LANÇAMENTOS'!$W$6:$W$2005,'LANÇAMENTOS'!$I$6:$I$2005,$B19,'LANÇAMENTOS'!$E$6:$E$2005,"Entrada",'LANÇAMENTOS'!$C$6:$C$2005,"<"&TODAY())+IF($C19=$B19,0,SUMIFS('LANÇAMENTOS'!$W$6:$W$2005,'LANÇAMENTOS'!$I$6:$I$2005,$C19,'LANÇAMENTOS'!$E$6:$E$2005,"Entrada",'LANÇAMENTOS'!$C$6:$C$2005,"<"&TODAY()))) | V19: =IF(OR($B19="",$U19=0),0,MAX(0,TODAY()-IFERROR(-SUMPRODUCT(MAX(('LANÇAMENTOS'!$I$6:$I$2005=$B19)*('LANÇAMENTOS'!$W$6:$W$2005>0)*('LANÇAMENTOS'!$C$6:$C$2005<TODAY())*(-'LANÇAMENTOS'!$C$6:$C$2005))),TODAY()))) | W19: =IF($B19="","",IF($N19="Bloqueado","⛔ Bloqueado",IF($U19>0,"⚠ Com valores vencidos","✔ Em dia")))
P20: =IF($B20="","",SUMIFS('LANÇAMENTOS'!$Q$6:$Q$2005,'LANÇAMENTOS'!$I$6:$I$2005,$B20)+IF($C20=$B20,0,SUMIFS('LANÇAMENTOS'!$Q$6:$Q$2005,'LANÇAMENTOS'!$I$6:$I$2005,$C20))) | Q20: =IF($B20="","",COUNTIFS('LANÇAMENTOS'!$I$6:$I$2005,$B20,'LANÇAMENTOS'!$P$6:$P$2005,1)+IF($C20=$B20,0,COUNTIFS('LANÇAMENTOS'!$I$6:$I$2005,$C20,'LANÇAMENTOS'!$P$6:$P$2005,1))) | R20: =IFERROR(IF($P20=0,"",$P20/$Q20),"") | S20: =IF($B20="","",IFERROR(IF(SUMPRODUCT(MAX(('LANÇAMENTOS'!$I$6:$I$2005=$B20)*'LANÇAMENTOS'!$B$6:$B$2005))>0,SUMPRODUCT(MAX(('LANÇAMENTOS'!$I$6:$I$2005=$B20)*'LANÇAMENTOS'!$B$6:$B$2005)),""),"")) | T20: =IF($B20="","",SUMIFS('LANÇAMENTOS'!$W$6:$W$2005,'LANÇAMENTOS'!$I$6:$I$2005,$B20,'LANÇAMENTOS'!$E$6:$E$2005,"Entrada")+IF($C20=$B20,0,SUMIFS('LANÇAMENTOS'!$W$6:$W$2005,'LANÇAMENTOS'!$I$6:$I$2005,$C20,'LANÇAMENTOS'!$E$6:$E$2005,"Entrada"))) | U20: =IF($B20="","",SUMIFS('LANÇAMENTOS'!$W$6:$W$2005,'LANÇAMENTOS'!$I$6:$I$2005,$B20,'LANÇAMENTOS'!$E$6:$E$2005,"Entrada",'LANÇAMENTOS'!$C$6:$C$2005,"<"&TODAY())+IF($C20=$B20,0,SUMIFS('LANÇAMENTOS'!$W$6:$W$2005,'LANÇAMENTOS'!$I$6:$I$2005,$C20,'LANÇAMENTOS'!$E$6:$E$2005,"Entrada",'LANÇAMENTOS'!$C$6:$C$2005,"<"&TODAY()))) | V20: =IF(OR($B20="",$U20=0),0,MAX(0,TODAY()-IFERROR(-SUMPRODUCT(MAX(('LANÇAMENTOS'!$I$6:$I$2005=$B20)*('LANÇAMENTOS'!$W$6:$W$2005>0)*('LANÇAMENTOS'!$C$6:$C$2005<TODAY())*(-'LANÇAMENTOS'!$C$6:$C$2005))),TODAY()))) | W20: =IF($B20="","",IF($N20="Bloqueado","⛔ Bloqueado",IF($U20>0,"⚠ Com valores vencidos","✔ Em dia")))
P21: =IF($B21="","",SUMIFS('LANÇAMENTOS'!$Q$6:$Q$2005,'LANÇAMENTOS'!$I$6:$I$2005,$B21)+IF($C21=$B21,0,SUMIFS('LANÇAMENTOS'!$Q$6:$Q$2005,'LANÇAMENTOS'!$I$6:$I$2005,$C21))) | Q21: =IF($B21="","",COUNTIFS('LANÇAMENTOS'!$I$6:$I$2005,$B21,'LANÇAMENTOS'!$P$6:$P$2005,1)+IF($C21=$B21,0,COUNTIFS('LANÇAMENTOS'!$I$6:$I$2005,$C21,'LANÇAMENTOS'!$P$6:$P$2005,1))) | R21: =IFERROR(IF($P21=0,"",$P21/$Q21),"") | S21: =IF($B21="","",IFERROR(IF(SUMPRODUCT(MAX(('LANÇAMENTOS'!$I$6:$I$2005=$B21)*'LANÇAMENTOS'!$B$6:$B$2005))>0,SUMPRODUCT(MAX(('LANÇAMENTOS'!$I$6:$I$2005=$B21)*'LANÇAMENTOS'!$B$6:$B$2005)),""),"")) | T21: =IF($B21="","",SUMIFS('LANÇAMENTOS'!$W$6:$W$2005,'LANÇAMENTOS'!$I$6:$I$2005,$B21,'LANÇAMENTOS'!$E$6:$E$2005,"Entrada")+IF($C21=$B21,0,SUMIFS('LANÇAMENTOS'!$W$6:$W$2005,'LANÇAMENTOS'!$I$6:$I$2005,$C21,'LANÇAMENTOS'!$E$6:$E$2005,"Entrada"))) | U21: =IF($B21="","",SUMIFS('LANÇAMENTOS'!$W$6:$W$2005,'LANÇAMENTOS'!$I$6:$I$2005,$B21,'LANÇAMENTOS'!$E$6:$E$2005,"Entrada",'LANÇAMENTOS'!$C$6:$C$2005,"<"&TODAY())+IF($C21=$B21,0,SUMIFS('LANÇAMENTOS'!$W$6:$W$2005,'LANÇAMENTOS'!$I$6:$I$2005,$C21,'LANÇAMENTOS'!$E$6:$E$2005,"Entrada",'LANÇAMENTOS'!$C$6:$C$2005,"<"&TODAY()))) | V21: =IF(OR($B21="",$U21=0),0,MAX(0,TODAY()-IFERROR(-SUMPRODUCT(MAX(('LANÇAMENTOS'!$I$6:$I$2005=$B21)*('LANÇAMENTOS'!$W$6:$W$2005>0)*('LANÇAMENTOS'!$C$6:$C$2005<TODAY())*(-'LANÇAMENTOS'!$C$6:$C$2005))),TODAY()))) | W21: =IF($B21="","",IF($N21="Bloqueado","⛔ Bloqueado",IF($U21>0,"⚠ Com valores vencidos","✔ Em dia")))
P22: =IF($B22="","",SUMIFS('LANÇAMENTOS'!$Q$6:$Q$2005,'LANÇAMENTOS'!$I$6:$I$2005,$B22)+IF($C22=$B22,0,SUMIFS('LANÇAMENTOS'!$Q$6:$Q$2005,'LANÇAMENTOS'!$I$6:$I$2005,$C22))) | Q22: =IF($B22="","",COUNTIFS('LANÇAMENTOS'!$I$6:$I$2005,$B22,'LANÇAMENTOS'!$P$6:$P$2005,1)+IF($C22=$B22,0,COUNTIFS('LANÇAMENTOS'!$I$6:$I$2005,$C22,'LANÇAMENTOS'!$P$6:$P$2005,1))) | R22: =IFERROR(IF($P22=0,"",$P22/$Q22),"") | S22: =IF($B22="","",IFERROR(IF(SUMPRODUCT(MAX(('LANÇAMENTOS'!$I$6:$I$2005=$B22)*'LANÇAMENTOS'!$B$6:$B$2005))>0,SUMPRODUCT(MAX(('LANÇAMENTOS'!$I$6:$I$2005=$B22)*'LANÇAMENTOS'!$B$6:$B$2005)),""),"")) | T22: =IF($B22="","",SUMIFS('LANÇAMENTOS'!$W$6:$W$2005,'LANÇAMENTOS'!$I$6:$I$2005,$B22,'LANÇAMENTOS'!$E$6:$E$2005,"Entrada")+IF($C22=$B22,0,SUMIFS('LANÇAMENTOS'!$W$6:$W$2005,'LANÇAMENTOS'!$I$6:$I$2005,$C22,'LANÇAMENTOS'!$E$6:$E$2005,"Entrada"))) | U22: =IF($B22="","",SUMIFS('LANÇAMENTOS'!$W$6:$W$2005,'LANÇAMENTOS'!$I$6:$I$2005,$B22,'LANÇAMENTOS'!$E$6:$E$2005,"Entrada",'LANÇAMENTOS'!$C$6:$C$2005,"<"&TODAY())+IF($C22=$B22,0,SUMIFS('LANÇAMENTOS'!$W$6:$W$2005,'LANÇAMENTOS'!$I$6:$I$2005,$C22,'LANÇAMENTOS'!$E$6:$E$2005,"Entrada",'LANÇAMENTOS'!$C$6:$C$2005,"<"&TODAY()))) | V22: =IF(OR($B22="",$U22=0),0,MAX(0,TODAY()-IFERROR(-SUMPRODUCT(MAX(('LANÇAMENTOS'!$I$6:$I$2005=$B22)*('LANÇAMENTOS'!$W$6:$W$2005>0)*('LANÇAMENTOS'!$C$6:$C$2005<TODAY())*(-'LANÇAMENTOS'!$C$6:$C$2005))),TODAY()))) | W22: =IF($B22="","",IF($N22="Bloqueado","⛔ Bloqueado",IF($U22>0,"⚠ Com valores vencidos","✔ Em dia")))
... P65: =IF($B65="","",SUMIFS('LANÇAMENTOS'!$Q$6:$Q$2005,'LANÇAMENTOS'!$I$6:$I$2005,$B65)+IF($C65=$B65,0,SUMIFS('LANÇAMENTOS'!$Q$6:$Q$2005,'LANÇAMENTOS'!$I$6:$I$2005,$C65))) | Q65: =IF($B65="","",COUNTIFS('LANÇAMENTOS'!$I$6:$I$2005,$B65,'LANÇAMENTOS'!$P$6:$P$2005,1)+IF($C65=$B65,0,COUNTIFS('LANÇAMENTOS'!$I$6:$I$2005,$C65,'LANÇAMENTOS'!$P$6:$P$2005,1))) | R65: =IFERROR(IF($P65=0,"",$P65/$Q65),"") | S65: =IF($B65="","",IFERROR(IF(SUMPRODUCT(MAX(('LANÇAMENTOS'!$I$6:$I$2005=$B65)*'LANÇAMENTOS'!$B$6:$B$2005))>0,SUMPRODUCT(MAX(('LANÇAMENTOS'!$I$6:$I$2005=$B65)*'LANÇAMENTOS'!$B$6:$B$2005)),""),"")) | T65: =IF($B65="","",SUMIFS('LANÇAMENTOS'!$W$6:$W$2005,'LANÇAMENTOS'!$I$6:$I$2005,$B65,'LANÇAMENTOS'!$E$6:$E$2005,"Entrada")+IF($C65=$B65,0,SUMIFS('LANÇAMENTOS'!$W$6:$W$2005,'LANÇAMENTOS'!$I$6:$I$2005,$C65,'LANÇAMENTOS'!$E$6:$E$2005,"Entrada"))) | U65: =IF($B65="","",SUMIFS('LANÇAMENTOS'!$W$6:$W$2005,'LANÇAMENTOS'!$I$6:$I$2005,$B65,'LANÇAMENTOS'!$E$6:$E$2005,"Entrada",'LANÇAMENTOS'!$C$6:$C$2005,"<"&TODAY())+IF($C65=$B65,0,SUMIFS('LANÇAMENTOS'!$W$6:$W$2005,'LANÇAMENTOS'!$I$6:$I$2005,$C65,'LANÇAMENTOS'!$E$6:$E$2005,"Entrada",'LANÇAMENTOS'!$C$6:$C$2005,"<"&TODAY()))) | V65: =IF(OR($B65="",$U65=0),0,MAX(0,TODAY()-IFERROR(-SUMPRODUCT(MAX(('LANÇAMENTOS'!$I$6:$I$2005=$B65)*('LANÇAMENTOS'!$W$6:$W$2005>0)*('LANÇAMENTOS'!$C$6:$C$2005<TODAY())*(-'LANÇAMENTOS'!$C$6:$C$2005))),TODAY()))) | W65: =IF($B65="","",IF($N65="Bloqueado","⛔ Bloqueado",IF($U65>0,"⚠ Com valores vencidos","✔ Em dia")))

Sheet CADASTRO DE FORNECEDORES
A1: CADASTRO DE FORNECEDORES
A2: Preencha as colunas amarelas. As colunas cinzas (P a T) são calculadas automaticamente a partir da aba LANÇAMENTOS.
B3: ⚠ DADOS DE EXEMPLO — fornecedores fictícios. Substitua pelos fornecedores reais.
A5: Código | B5: Razão social | C5: Nome fantasia | D5: CNPJ/CPF | E5: Contato | F5: Telefone | G5: E-mail | H5: Cidade | I5: UF | J5: Categoria principal | K5: Condição de pagamento | L5: Prazo médio (dias) | M5: Limite de crédito | N5: Status | O5: Observações | P5: Total comprado | Q5: Total pago | R5: Total em aberto | S5: Valor vencido | T5: Última compra
A6: FOR001 | B6: DISTRIBUIDORA CENTRAL DE ALIMENTOS S/A | C6: Central Foods | D6: 61.890.123/0001-66 | E6: Roberto Lima | F6: (11) 3701-2200 | G6: vendas@centralfoods.com.br | H6: São Paulo | I6: SP | J6: Mercadorias para Revenda | K6: Boleto 30 dias | L6: 30 | M6: 250000 | N6: Ativo | O6: Principal fornecedor de mercadorias | P6: =IF($B6="","",SUMIFS('LANÇAMENTOS'!$Q$6:$Q$2005,'LANÇAMENTOS'!$I$6:$I$2005,$B6,'LANÇAMENTOS'!$E$6:$E$2005,"Saída")) | Q6: =IF($B6="","",SUMIFS('LANÇAMENTOS'!$V$6:$V$2005,'LANÇAMENTOS'!$I$6:$I$2005,$B6,'LANÇAMENTOS'!$E$6:$E$2005,"Saída")) | R6: =IF($B6="","",SUMIFS('LANÇAMENTOS'!$W$6:$W$2005,'LANÇAMENTOS'!$I$6:$I$2005,$B6,'LANÇAMENTOS'!$E$6:$E$2005,"Saída")) | S6: =IF($B6="","",SUMIFS('LANÇAMENTOS'!$W$6:$W$2005,'LANÇAMENTOS'!$I$6:$I$2005,$B6,'LANÇAMENTOS'!$E$6:$E$2005,"Saída",'LANÇAMENTOS'!$C$6:$C$2005,"<"&TODAY())) | T6: =IF($B6="","",IFERROR(IF(SUMPRODUCT(MAX(('LANÇAMENTOS'!$I$6:$I$2005=$B6)*'LANÇAMENTOS'!$B$6:$B$2005))>0,SUMPRODUCT(MAX(('LANÇAMENTOS'!$I$6:$I$2005=$B6)*'LANÇAMENTOS'!$B$6:$B$2005)),""),""))
A7: FOR002 | B7: EMBALAGENS PAULISTA LTDA | C7: Embalagens Paulista | D7: 72.901.234/0001-77 | E7: Fernanda Dias | F7: (11) 2933-4455 | G7: comercial@embalagenspaulista.com.br | H7: São Bernardo do Campo | I7: SP | J7: Embalagens | K7: Boleto 15 dias | L7: 15 | M7: 40000 | N7: Ativo | P7: =IF($B7="","",SUMIFS('LANÇAMENTOS'!$Q$6:$Q$2005,'LANÇAMENTOS'!$I$6:$I$2005,$B7,'LANÇAMENTOS'!$E$6:$E$2005,"Saída")) | Q7: =IF($B7="","",SUMIFS('LANÇAMENTOS'!$V$6:$V$2005,'LANÇAMENTOS'!$I$6:$I$2005,$B7,'LANÇAMENTOS'!$E$6:$E$2005,"Saída")) | R7: =IF($B7="","",SUMIFS('LANÇAMENTOS'!$W$6:$W$2005,'LANÇAMENTOS'!$I$6:$I$2005,$B7,'LANÇAMENTOS'!$E$6:$E$2005,"Saída")) | S7: =IF($B7="","",SUMIFS('LANÇAMENTOS'!$W$6:$W$2005,'LANÇAMENTOS'!$I$6:$I$2005,$B7,'LANÇAMENTOS'!$E$6:$E$2005,"Saída",'LANÇAMENTOS'!$C$6:$C$2005,"<"&TODAY())) | T7: =IF($B7="","",IFERROR(IF(SUMPRODUCT(MAX(('LANÇAMENTOS'!$I$6:$I$2005=$B7)*'LANÇAMENTOS'!$B$6:$B$2005))>0,SUMPRODUCT(MAX(('LANÇAMENTOS'!$I$6:$I$2005=$B7)*'LANÇAMENTOS'!$B$6:$B$2005)),""),""))
A8: FOR003 | B8: TRANSPORTADORA RÁPIDA LOG LTDA | C8: Rápida Log | D8: 83.012.345/0001-88 | E8: José Almeida | F8: (11) 3011-9090 | G8: faturamento@rapidalog.com.br | H8: Guarulhos | I8: SP | J8: Fretes e Entregas sobre Vendas | K8: Boleto 15 dias | L8: 15 | M8: 60000 | N8: Ativo | O8: Frete faturado por nota fiscal | P8: =IF($B8="","",SUMIFS('LANÇAMENTOS'!$Q$6:$Q$2005,'LANÇAMENTOS'!$I$6:$I$2005,$B8,'LANÇAMENTOS'!$E$6:$E$2005,"Saída")) | Q8: =IF($B8="","",SUMIFS('LANÇAMENTOS'!$V$6:$V$2005,'LANÇAMENTOS'!$I$6:$I$2005,$B8,'LANÇAMENTOS'!$E$6:$E$2005,"Saída")) | R8: =IF($B8="","",SUMIFS('LANÇAMENTOS'!$W$6:$W$2005,'LANÇAMENTOS'!$I$6:$I$2005,$B8,'LANÇAMENTOS'!$E$6:$E$2005,"Saída")) | S8: =IF($B8="","",SUMIFS('LANÇAMENTOS'!$W$6:$W$2005,'LANÇAMENTOS'!$I$6:$I$2005,$B8,'LANÇAMENTOS'!$E$6:$E$2005,"Saída",'LANÇAMENTOS'!$C$6:$C$2005,"<"&TODAY())) | T8: =IF($B8="","",IFERROR(IF(SUMPRODUCT(MAX(('LANÇAMENTOS'!$I$6:$I$2005=$B8)*'LANÇAMENTOS'!$B$6:$B$2005))>0,SUMPRODUCT(MAX(('LANÇAMENTOS'!$I$6:$I$2005=$B8)*'LANÇAMENTOS'!$B$6:$B$2005)),""),""))
A9: FOR004 | B9: TECNOLOGIA E SISTEMAS ABC LTDA | C9: ABC Sistemas | D9: 94.123.456/0001-99 | E9: Marcelo Prado | F9: (11) 4063-1122 | G9: suporte@abcsistemas.com.br | H9: São Paulo | I9: SP | J9: Sistemas e Softwares | K9: Cartão de crédito | L9: 0 | M9: 15000 | N9: Ativo | O9: ERP, emissão de NF-e e BI | P9: =IF($B9="","",SUMIFS('LANÇAMENTOS'!$Q$6:$Q$2005,'LANÇAMENTOS'!$I$6:$I$2005,$B9,'LANÇAMENTOS'!$E$6:$E$2005,"Saída")) | Q9: =IF($B9="","",SUMIFS('LANÇAMENTOS'!$V$6:$V$2005,'LANÇAMENTOS'!$I$6:$I$2005,$B9,'LANÇAMENTOS'!$E$6:$E$2005,"Saída")) | R9: =IF($B9="","",SUMIFS('LANÇAMENTOS'!$W$6:$W$2005,'LANÇAMENTOS'!$I$6:$I$2005,$B9,'LANÇAMENTOS'!$E$6:$E$2005,"Saída")) | S9: =IF($B9="","",SUMIFS('LANÇAMENTOS'!$W$6:$W$2005,'LANÇAMENTOS'!$I$6:$I$2005,$B9,'LANÇAMENTOS'!$E$6:$E$2005,"Saída",'LANÇAMENTOS'!$C$6:$C$2005,"<"&TODAY())) | T9: =IF($B9="","",IFERROR(IF(SUMPRODUCT(MAX(('LANÇAMENTOS'!$I$6:$I$2005=$B9)*'LANÇAMENTOS'!$B$6:$B$2005))>0,SUMPRODUCT(MAX(('LANÇAMENTOS'!$I$6:$I$2005=$B9)*'LANÇAMENTOS'!$B$6:$B$2005)),""),""))
A10: FOR005 | B10: IMÓVEIS E LOCAÇÕES PINHEIROS LTDA | C10: Locadora Pinheiros | D10: 15.234.567/0001-10 | E10: Cláudia Rossi | F10: (11) 3812-7777 | G10: locacao@pinheirosimoveis.com.br | H10: São Paulo | I10: SP | J10: Aluguel | K10: Boleto 5 dias | L10: 5 | M10: 0 | N10: Ativo | O10: Contrato de locação do galpão — reajuste anual em janeiro | P10: =IF($B10="","",SUMIFS('LANÇAMENTOS'!$Q$6:$Q$2005,'LANÇAMENTOS'!$I$6:$I$2005,$B10,'LANÇAMENTOS'!$E$6:$E$2005,"Saída")) | Q10: =IF($B10="","",SUMIFS('LANÇAMENTOS'!$V$6:$V$2005,'LANÇAMENTOS'!$I$6:$I$2005,$B10,'LANÇAMENTOS'!$E$6:$E$2005,"Saída")) | R10: =IF($B10="","",SUMIFS('LANÇAMENTOS'!$W$6:$W$2005,'LANÇAMENTOS'!$I$6:$I$2005,$B10,'LANÇAMENTOS'!$E$6:$E$2005,"Saída")) | S10: =IF($B10="","",SUMIFS('LANÇAMENTOS'!$W$6:$W$2005,'LANÇAMENTOS'!$I$6:$I$2005,$B10,'LANÇAMENTOS'!$E$6:$E$2005,"Saída",'LANÇAMENTOS'!$C$6:$C$2005,"<"&TODAY())) | T10: =IF($B10="","",IFERROR(IF(SUMPRODUCT(MAX(('LANÇAMENTOS'!$I$6:$I$2005=$B10)*'LANÇAMENTOS'!$B$6:$B$2005))>0,SUMPRODUCT(MAX(('LANÇAMENTOS'!$I$6:$I$2005=$B10)*'LANÇAMENTOS'!$B$6:$B$2005)),""),""))
A11: FOR006 | B11: ENEL DISTRIBUIÇÃO SÃO PAULO | C11: Enel SP | D11: 61.695.227/0001-93 | E11: Central de Atendimento | F11: 0800 727 2116 | G11: atendimento@enel.com | H11: São Paulo | I11: SP | J11: Energia Elétrica | K11: Débito automático | L11: 10 | M11: 0 | N11: Ativo | O11: Concessionária de energia elétrica | P11: =IF($B11="","",SUMIFS('LANÇAMENTOS'!$Q$6:$Q$2005,'LANÇAMENTOS'!$I$6:$I$2005,$B11,'LANÇAMENTOS'!$E$6:$E$2005,"Saída")) | Q11: =IF($B11="","",SUMIFS('LANÇAMENTOS'!$V$6:$V$2005,'LANÇAMENTOS'!$I$6:$I$2005,$B11,'LANÇAMENTOS'!$E$6:$E$2005,"Saída")) | R11: =IF($B11="","",SUMIFS('LANÇAMENTOS'!$W$6:$W$2005,'LANÇAMENTOS'!$I$6:$I$2005,$B11,'LANÇAMENTOS'!$E$6:$E$2005,"Saída")) | S11: =IF($B11="","",SUMIFS('LANÇAMENTOS'!$W$6:$W$2005,'LANÇAMENTOS'!$I$6:$I$2005,$B11,'LANÇAMENTOS'!$E$6:$E$2005,"Saída",'LANÇAMENTOS'!$C$6:$C$2005,"<"&TODAY())) | T11: =IF($B11="","",IFERROR(IF(SUMPRODUCT(MAX(('LANÇAMENTOS'!$I$6:$I$2005=$B11)*'LANÇAMENTOS'!$B$6:$B$2005))>0,SUMPRODUCT(MAX(('LANÇAMENTOS'!$I$6:$I$2005=$B11)*'LANÇAMENTOS'!$B$6:$B$2005)),""),""))
A12: FOR007 | B12: SABESP — SANEAMENTO BÁSICO DO ESTADO DE SÃO PAULO | C12: Sabesp | D12: 43.776.517/0001-80 | E12: Central de Atendimento | F12: 0800 055 0195 | G12: atendimento@sabesp.com.br | H12: São Paulo | I12: SP | J12: Água e Saneamento | K12: Débito automático | L12: 12 | M12: 0 | N12: Ativo | O12: Concessionária de água | P12: =IF($B12="","",SUMIFS('LANÇAMENTOS'!$Q$6:$Q$2005,'LANÇAMENTOS'!$I$6:$I$2005,$B12,'LANÇAMENTOS'!$E$6:$E$2005,"Saída")) | Q12: =IF($B12="","",SUMIFS('LANÇAMENTOS'!$V$6:$V$2005,'LANÇAMENTOS'!$I$6:$I$2005,$B12,'LANÇAMENTOS'!$E$6:$E$2005,"Saída")) | R12: =IF($B12="","",SUMIFS('LANÇAMENTOS'!$W$6:$W$2005,'LANÇAMENTOS'!$I$6:$I$2005,$B12,'LANÇAMENTOS'!$E$6:$E$2005,"Saída")) | S12: =IF($B12="","",SUMIFS('LANÇAMENTOS'!$W$6:$W$2005,'LANÇAMENTOS'!$I$6:$I$2005,$B12,'LANÇAMENTOS'!$E$6:$E$2005,"Saída",'LANÇAMENTOS'!$C$6:$C$2005,"<"&TODAY())) | T12: =IF($B12="","",IFERROR(IF(SUMPRODUCT(MAX(('LANÇAMENTOS'!$I$6:$I$2005=$B12)*'LANÇAMENTOS'!$B$6:$B$2005))>0,SUMPRODUCT(MAX(('LANÇAMENTOS'!$I$6:$I$2005=$B12)*'LANÇAMENTOS'!$B$6:$B$2005)),""),""))
A13: FOR008 | B13: TELEFÔNICA BRASIL S.A. (VIVO EMPRESAS) | C13: Vivo Empresas | D13: 02.558.157/0001-62 | E13: Gestor de Contas | F13: 1058 | G13: empresas@vivo.com.br | H13: São Paulo | I13: SP | J13: Internet e Telefonia | K13: Cartão de crédito | L13: 0 | M13: 0 | N13: Ativo | O13: Link dedicado e telefonia móvel | P13: =IF($B13="","",SUMIFS('LANÇAMENTOS'!$Q$6:$Q$2005,'LANÇAMENTOS'!$I$6:$I$2005,$B13,'LANÇAMENTOS'!$E$6:$E$2005,"Saída")) | Q13: =IF($B13="","",SUMIFS('LANÇAMENTOS'!$V$6:$V$2005,'LANÇAMENTOS'!$I$6:$I$2005,$B13,'LANÇAMENTOS'!$E$6:$E$2005,"Saída")) | R13: =IF($B13="","",SUMIFS('LANÇAMENTOS'!$W$6:$W$2005,'LANÇAMENTOS'!$I$6:$I$2005,$B13,'LANÇAMENTOS'!$E$6:$E$2005,"Saída")) | S13: =IF($B13="","",SUMIFS('LANÇAMENTOS'!$W$6:$W$2005,'LANÇAMENTOS'!$I$6:$I$2005,$B13,'LANÇAMENTOS'!$E$6:$E$2005,"Saída",'LANÇAMENTOS'!$C$6:$C$2005,"<"&TODAY())) | T13: =IF($B13="","",IFERROR(IF(SUMPRODUCT(MAX(('LANÇAMENTOS'!$I$6:$I$2005=$B13)*'LANÇAMENTOS'!$B$6:$B$2005))>0,SUMPRODUCT(MAX(('LANÇAMENTOS'!$I$6:$I$2005=$B13)*'LANÇAMENTOS'!$B$6:$B$2005)),""),""))
A14: FOR009 | B14: CONTABILIDADE AURORA ASSESSORIA CONTÁBIL LTDA | C14: Contabilidade Aurora | D14: 18.447.902/0001-34 | E14: Sérgio Tavares | F14: (11) 3151-8080 | G14: contato@contabilaurora.com.br | H14: São Paulo | I14: SP | J14: Contabilidade | K14: PIX mensal | L14: 0 | M14: 0 | N14: Ativo | O14: Assessoria contábil e fiscal | P14: =IF($B14="","",SUMIFS('LANÇAMENTOS'!$Q$6:$Q$2005,'LANÇAMENTOS'!$I$6:$I$2005,$B14,'LANÇAMENTOS'!$E$6:$E$2005,"Saída")) | Q14: =IF($B14="","",SUMIFS('LANÇAMENTOS'!$V$6:$V$2005,'LANÇAMENTOS'!$I$6:$I$2005,$B14,'LANÇAMENTOS'!$E$6:$E$2005,"Saída")) | R14: =IF($B14="","",SUMIFS('LANÇAMENTOS'!$W$6:$W$2005,'LANÇAMENTOS'!$I$6:$I$2005,$B14,'LANÇAMENTOS'!$E$6:$E$2005,"Saída")) | S14: =IF($B14="","",SUMIFS('LANÇAMENTOS'!$W$6:$W$2005,'LANÇAMENTOS'!$I$6:$I$2005,$B14,'LANÇAMENTOS'!$E$6:$E$2005,"Saída",'LANÇAMENTOS'!$C$6:$C$2005,"<"&TODAY())) | T14: =IF($B14="","",IFERROR(IF(SUMPRODUCT(MAX(('LANÇAMENTOS'!$I$6:$I$2005=$B14)*'LANÇAMENTOS'!$B$6:$B$2005))>0,SUMPRODUCT(MAX(('LANÇAMENTOS'!$I$6:$I$2005=$B14)*'LANÇAMENTOS'!$B$6:$B$2005)),""),""))
A15: FOR010 | B15: AGÊNCIA PULSO DIGITAL LTDA | C15: Pulso Digital | D15: 29.334.556/0001-71 | E15: Renata Campos | F15: (11) 99123-4567 | G15: contato@pulsodigital.com.br | H15: São Paulo | I15: SP | J15: Marketing Digital | K15: Cartão de crédito | L15: 0 | M15: 20000 | N15: Ativo | O15: Gestão de mídia paga | P15: =IF($B15="","",SUMIFS('LANÇAMENTOS'!$Q$6:$Q$2005,'LANÇAMENTOS'!$I$6:$I$2005,$B15,'LANÇAMENTOS'!$E$6:$E$2005,"Saída")) | Q15: =IF($B15="","",SUMIFS('LANÇAMENTOS'!$V$6:$V$2005,'LANÇAMENTOS'!$I$6:$I$2005,$B15,'LANÇAMENTOS'!$E$6:$E$2005,"Saída")) | R15: =IF($B15="","",SUMIFS('LANÇAMENTOS'!$W$6:$W$2005,'LANÇAMENTOS'!$I$6:$I$2005,$B15,'LANÇAMENTOS'!$E$6:$E$2005,"Saída")) | S15: =IF($B15="","",SUMIFS('LANÇAMENTOS'!$W$6:$W$2005,'LANÇAMENTOS'!$I$6:$I$2005,$B15,'LANÇAMENTOS'!$E$6:$E$2005,"Saída",'LANÇAMENTOS'!$C$6:$C$2005,"<"&TODAY())) | T15: =IF($B15="","",IFERROR(IF(SUMPRODUCT(MAX(('LANÇAMENTOS'!$I$6:$I$2005=$B15)*'LANÇAMENTOS'!$B$6:$B$2005))>0,SUMPRODUCT(MAX(('LANÇAMENTOS'!$I$6:$I$2005=$B15)*'LANÇAMENTOS'!$B$6:$B$2005)),""),""))
A16: FOR011 | B16: GOOGLE BRASIL INTERNET LTDA | C16: Google Ads | D16: 06.990.590/0001-23 | E16: Suporte | F16: — | G16: ads@google.com | H16: São Paulo | I16: SP | J16: Publicidade e Anúncios | K16: Cartão de crédito | L16: 0 | M16: 0 | N16: Ativo | O16: Anúncios e campanhas digitais | P16: =IF($B16="","",SUMIFS('LANÇAMENTOS'!$Q$6:$Q$2005,'LANÇAMENTOS'!$I$6:$I$2005,$B16,'LANÇAMENTOS'!$E$6:$E$2005,"Saída")) | Q16: =IF($B16="","",SUMIFS('LANÇAMENTOS'!$V$6:$V$2005,'LANÇAMENTOS'!$I$6:$I$2005,$B16,'LANÇAMENTOS'!$E$6:$E$2005,"Saída")) | R16: =IF($B16="","",SUMIFS('LANÇAMENTOS'!$W$6:$W$2005,'LANÇAMENTOS'!$I$6:$I$2005,$B16,'LANÇAMENTOS'!$E$6:$E$2005,"Saída")) | S16: =IF($B16="","",SUMIFS('LANÇAMENTOS'!$W$6:$W$2005,'LANÇAMENTOS'!$I$6:$I$2005,$B16,'LANÇAMENTOS'!$E$6:$E$2005,"Saída",'LANÇAMENTOS'!$C$6:$C$2005,"<"&TODAY())) | T16: =IF($B16="","",IFERROR(IF(SUMPRODUCT(MAX(('LANÇAMENTOS'!$I$6:$I$2005=$B16)*'LANÇAMENTOS'!$B$6:$B$2005))>0,SUMPRODUCT(MAX(('LANÇAMENTOS'!$I$6:$I$2005=$B16)*'LANÇAMENTOS'!$B$6:$B$2005)),""),""))
A17: FOR012 | B17: BENEFÍCIOS BRASIL ADMINISTRADORA LTDA | C17: Benefícios Brasil | D17: 09.876.543/0001-21 | E17: Time de Atendimento | F17: (11) 4004-1010 | G17: empresas@beneficiosbrasil.com.br | H17: São Paulo | I17: SP | J17: Benefícios (VT/VA/Plano de Saúde) | K17: Transferência | L17: 5 | M17: 0 | N17: Ativo | O17: Vale-transporte, alimentação e plano de saúde | P17: =IF($B17="","",SUMIFS('LANÇAMENTOS'!$Q$6:$Q$2005,'LANÇAMENTOS'!$I$6:$I$2005,$B17,'LANÇAMENTOS'!$E$6:$E$2005,"Saída")) | Q17: =IF($B17="","",SUMIFS('LANÇAMENTOS'!$V$6:$V$2005,'LANÇAMENTOS'!$I$6:$I$2005,$B17,'LANÇAMENTOS'!$E$6:$E$2005,"Saída")) | R17: =IF($B17="","",SUMIFS('LANÇAMENTOS'!$W$6:$W$2005,'LANÇAMENTOS'!$I$6:$I$2005,$B17,'LANÇAMENTOS'!$E$6:$E$2005,"Saída")) | S17: =IF($B17="","",SUMIFS('LANÇAMENTOS'!$W$6:$W$2005,'LANÇAMENTOS'!$I$6:$I$2005,$B17,'LANÇAMENTOS'!$E$6:$E$2005,"Saída",'LANÇAMENTOS'!$C$6:$C$2005,"<"&TODAY())) | T17: =IF($B17="","",IFERROR(IF(SUMPRODUCT(MAX(('LANÇAMENTOS'!$I$6:$I$2005=$B17)*'LANÇAMENTOS'!$B$6:$B$2005))>0,SUMPRODUCT(MAX(('LANÇAMENTOS'!$I$6:$I$2005=$B17)*'LANÇAMENTOS'!$B$6:$B$2005)),""),""))
A18: FOR013 | B18: RECEITA FEDERAL DO BRASIL | C18: Receita Federal | D18: 00.394.460/0001-85 | E18: — | F18: — | G18: — | H18: Brasília | I18: DF | J18: Tributos | K18: DAS/débito automático | L18: 20 | M18: 0 | N18: Ativo | O18: Tributos federais — Simples Nacional | P18: =IF($B18="","",SUMIFS('LANÇAMENTOS'!$Q$6:$Q$2005,'LANÇAMENTOS'!$I$6:$I$2005,$B18,'LANÇAMENTOS'!$E$6:$E$2005,"Saída")) | Q18: =IF($B18="","",SUMIFS('LANÇAMENTOS'!$V$6:$V$2005,'LANÇAMENTOS'!$I$6:$I$2005,$B18,'LANÇAMENTOS'!$E$6:$E$2005,"Saída")) | R18: =IF($B18="","",SUMIFS('LANÇAMENTOS'!$W$6:$W$2005,'LANÇAMENTOS'!$I$6:$I$2005,$B18,'LANÇAMENTOS'!$E$6:$E$2005,"Saída")) | S18: =IF($B18="","",SUMIFS('LANÇAMENTOS'!$W$6:$W$2005,'LANÇAMENTOS'!$I$6:$I$2005,$B18,'LANÇAMENTOS'!$E$6:$E$2005,"Saída",'LANÇAMENTOS'!$C$6:$C$2005,"<"&TODAY())) | T18: =IF($B18="","",IFERROR(IF(SUMPRODUCT(MAX(('LANÇAMENTOS'!$I$6:$I$2005=$B18)*'LANÇAMENTOS'!$B$6:$B$2005))>0,SUMPRODUCT(MAX(('LANÇAMENTOS'!$I$6:$I$2005=$B18)*'LANÇAMENTOS'!$B$6:$B$2005)),""),""))
A19: FOR014 | B19: PREFEITURA DE SÃO PAULO | C19: Prefeitura SP | D19: 46.395.000/0001-39 | E19: — | F19: 156 | G19: — | H19: São Paulo | I19: SP | J19: Tributos | K19: Guia municipal | L19: 10 | M19: 0 | N19: Ativo | O19: Taxas municipais, ISS e alvará | P19: =IF($B19="","",SUMIFS('LANÇAMENTOS'!$Q$6:$Q$2005,'LANÇAMENTOS'!$I$6:$I$2005,$B19,'LANÇAMENTOS'!$E$6:$E$2005,"Saída")) | Q19: =IF($B19="","",SUMIFS('LANÇAMENTOS'!$V$6:$V$2005,'LANÇAMENTOS'!$I$6:$I$2005,$B19,'LANÇAMENTOS'!$E$6:$E$2005,"Saída")) | R19: =IF($B19="","",SUMIFS('LANÇAMENTOS'!$W$6:$W$2005,'LANÇAMENTOS'!$I$6:$I$2005,$B19,'LANÇAMENTOS'!$E$6:$E$2005,"Saída")) | S19: =IF($B19="","",SUMIFS('LANÇAMENTOS'!$W$6:$W$2005,'LANÇAMENTOS'!$I$6:$I$2005,$B19,'LANÇAMENTOS'!$E$6:$E$2005,"Saída",'LANÇAMENTOS'!$C$6:$C$2005,"<"&TODAY())) | T19: =IF($B19="","",IFERROR(IF(SUMPRODUCT(MAX(('LANÇAMENTOS'!$I$6:$I$2005=$B19)*'LANÇAMENTOS'!$B$6:$B$2005))>0,SUMPRODUCT(MAX(('LANÇAMENTOS'!$I$6:$I$2005=$B19)*'LANÇAMENTOS'!$B$6:$B$2005)),""),""))
... A35: FOR030 | B35: SÓCIOS — PRÓ-LABORE E DISTRIBUIÇÕES | C35: Sócios administradores | D35: — | E35: Jefferson Andrade | F35: (11) 99999-0000 | G35: socios@aurora.com.br | H35: São Paulo | I35: SP | J35: Pró-labore | K35: Transferência mensal | L35: 5 | M35: 0 | N35: Ativo | O35: Pró-labore e retiradas dos sócios | P35: =IF($B35="","",SUMIFS('LANÇAMENTOS'!$Q$6:$Q$2005,'LANÇAMENTOS'!$I$6:$I$2005,$B35,'LANÇAMENTOS'!$E$6:$E$2005,"Saída")) | Q35: =IF($B35="","",SUMIFS('LANÇAMENTOS'!$V$6:$V$2005,'LANÇAMENTOS'!$I$6:$I$2005,$B35,'LANÇAMENTOS'!$E$6:$E$2005,"Saída")) | R35: =IF($B35="","",SUMIFS('LANÇAMENTOS'!$W$6:$W$2005,'LANÇAMENTOS'!$I$6:$I$2005,$B35,'LANÇAMENTOS'!$E$6:$E$2005,"Saída")) | S35: =IF($B35="","",SUMIFS('LANÇAMENTOS'!$W$6:$W$2005,'LANÇAMENTOS'!$I$6:$I$2005,$B35,'LANÇAMENTOS'!$E$6:$E$2005,"Saída",'LANÇAMENTOS'!$C$6:$C$2005,"<"&TODAY())) | T35: =IF($B35="","",IFERROR(IF(SUMPRODUCT(MAX(('LANÇAMENTOS'!$I$6:$I$2005=$B35)*'LANÇAMENTOS'!$B$6:$B$2005))>0,SUMPRODUCT(MAX(('LANÇAMENTOS'!$I$6:$I$2005=$B35)*'LANÇAMENTOS'!$B$6:$B$2005)),""),""))
P36: =IF($B36="","",SUMIFS('LANÇAMENTOS'!$Q$6:$Q$2005,'LANÇAMENTOS'!$I$6:$I$2005,$B36,'LANÇAMENTOS'!$E$6:$E$2005,"Saída")) | Q36: =IF($B36="","",SUMIFS('LANÇAMENTOS'!$V$6:$V$2005,'LANÇAMENTOS'!$I$6:$I$2005,$B36,'LANÇAMENTOS'!$E$6:$E$2005,"Saída")) | R36: =IF($B36="","",SUMIFS('LANÇAMENTOS'!$W$6:$W$2005,'LANÇAMENTOS'!$I$6:$I$2005,$B36,'LANÇAMENTOS'!$E$6:$E$2005,"Saída")) | S36: =IF($B36="","",SUMIFS('LANÇAMENTOS'!$W$6:$W$2005,'LANÇAMENTOS'!$I$6:$I$2005,$B36,'LANÇAMENTOS'!$E$6:$E$2005,"Saída",'LANÇAMENTOS'!$C$6:$C$2005,"<"&TODAY())) | T36: =IF($B36="","",IFERROR(IF(SUMPRODUCT(MAX(('LANÇAMENTOS'!$I$6:$I$2005=$B36)*'LANÇAMENTOS'!$B$6:$B$2005))>0,SUMPRODUCT(MAX(('LANÇAMENTOS'!$I$6:$I$2005=$B36)*'LANÇAMENTOS'!$B$6:$B$2005)),""),""))
P37: =IF($B37="","",SUMIFS('LANÇAMENTOS'!$Q$6:$Q$2005,'LANÇAMENTOS'!$I$6:$I$2005,$B37,'LANÇAMENTOS'!$E$6:$E$2005,"Saída")) | Q37: =IF($B37="","",SUMIFS('LANÇAMENTOS'!$V$6:$V$2005,'LANÇAMENTOS'!$I$6:$I$2005,$B37,'LANÇAMENTOS'!$E$6:$E$2005,"Saída")) | R37: =IF($B37="","",SUMIFS('LANÇAMENTOS'!$W$6:$W$2005,'LANÇAMENTOS'!$I$6:$I$2005,$B37,'LANÇAMENTOS'!$E$6:$E$2005,"Saída")) | S37: =IF($B37="","",SUMIFS('LANÇAMENTOS'!$W$6:$W$2005,'LANÇAMENTOS'!$I$6:$I$2005,$B37,'LANÇAMENTOS'!$E$6:$E$2005,"Saída",'LANÇAMENTOS'!$C$6:$C$2005,"<"&TODAY())) | T37: =IF($B37="","",IFERROR(IF(SUMPRODUCT(MAX(('LANÇAMENTOS'!$I$6:$I$2005=$B37)*'LANÇAMENTOS'!$B$6:$B$2005))>0,SUMPRODUCT(MAX(('LANÇAMENTOS'!$I$6:$I$2005=$B37)*'LANÇAMENTOS'!$B$6:$B$2005)),""),""))
P38: =IF($B38="","",SUMIFS('LANÇAMENTOS'!$Q$6:$Q$2005,'LANÇAMENTOS'!$I$6:$I$2005,$B38,'LANÇAMENTOS'!$E$6:$E$2005,"Saída")) | Q38: =IF($B38="","",SUMIFS('LANÇAMENTOS'!$V$6:$V$2005,'LANÇAMENTOS'!$I$6:$I$2005,$B38,'LANÇAMENTOS'!$E$6:$E$2005,"Saída")) | R38: =IF($B38="","",SUMIFS('LANÇAMENTOS'!$W$6:$W$2005,'LANÇAMENTOS'!$I$6:$I$2005,$B38,'LANÇAMENTOS'!$E$6:$E$2005,"Saída")) | S38: =IF($B38="","",SUMIFS('LANÇAMENTOS'!$W$6:$W$2005,'LANÇAMENTOS'!$I$6:$I$2005,$B38,'LANÇAMENTOS'!$E$6:$E$2005,"Saída",'LANÇAMENTOS'!$C$6:$C$2005,"<"&TODAY())) | T38: =IF($B38="","",IFERROR(IF(SUMPRODUCT(MAX(('LANÇAMENTOS'!$I$6:$I$2005=$B38)*'LANÇAMENTOS'!$B$6:$B$2005))>0,SUMPRODUCT(MAX(('LANÇAMENTOS'!$I$6:$I$2005=$B38)*'LANÇAMENTOS'!$B$6:$B$2005)),""),""))
P39: =IF($B39="","",SUMIFS('LANÇAMENTOS'!$Q$6:$Q$2005,'LANÇAMENTOS'!$I$6:$I$2005,$B39,'LANÇAMENTOS'!$E$6:$E$2005,"Saída")) | Q39: =IF($B39="","",SUMIFS('LANÇAMENTOS'!$V$6:$V$2005,'LANÇAMENTOS'!$I$6:$I$2005,$B39,'LANÇAMENTOS'!$E$6:$E$2005,"Saída")) | R39: =IF($B39="","",SUMIFS('LANÇAMENTOS'!$W$6:$W$2005,'LANÇAMENTOS'!$I$6:$I$2005,$B39,'LANÇAMENTOS'!$E$6:$E$2005,"Saída")) | S39: =IF($B39="","",SUMIFS('LANÇAMENTOS'!$W$6:$W$2005,'LANÇAMENTOS'!$I$6:$I$2005,$B39,'LANÇAMENTOS'!$E$6:$E$2005,"Saída",'LANÇAMENTOS'!$C$6:$C$2005,"<"&TODAY())) | T39: =IF($B39="","",IFERROR(IF(SUMPRODUCT(MAX(('LANÇAMENTOS'!$I$6:$I$2005=$B39)*'LANÇAMENTOS'!$B$6:$B$2005))>0,SUMPRODUCT(MAX(('LANÇAMENTOS'!$I$6:$I$2005=$B39)*'LANÇAMENTOS'!$B$6:$B$2005)),""),""))
P40: =IF($B40="","",SUMIFS('LANÇAMENTOS'!$Q$6:$Q$2005,'LANÇAMENTOS'!$I$6:$I$2005,$B40,'LANÇAMENTOS'!$E$6:$E$2005,"Saída")) | Q40: =IF($B40="","",SUMIFS('LANÇAMENTOS'!$V$6:$V$2005,'LANÇAMENTOS'!$I$6:$I$2005,$B40,'LANÇAMENTOS'!$E$6:$E$2005,"Saída")) | R40: =IF($B40="","",SUMIFS('LANÇAMENTOS'!$W$6:$W$2005,'LANÇAMENTOS'!$I$6:$I$2005,$B40,'LANÇAMENTOS'!$E$6:$E$2005,"Saída")) | S40: =IF($B40="","",SUMIFS('LANÇAMENTOS'!$W$6:$W$2005,'LANÇAMENTOS'!$I$6:$I$2005,$B40,'LANÇAMENTOS'!$E$6:$E$2005,"Saída",'LANÇAMENTOS'!$C$6:$C$2005,"<"&TODAY())) | T40: =IF($B40="","",IFERROR(IF(SUMPRODUCT(MAX(('LANÇAMENTOS'!$I$6:$I$2005=$B40)*'LANÇAMENTOS'!$B$6:$B$2005))>0,SUMPRODUCT(MAX(('LANÇAMENTOS'!$I$6:$I$2005=$B40)*'LANÇAMENTOS'!$B$6:$B$2005)),""),""))
P41: =IF($B41="","",SUMIFS('LANÇAMENTOS'!$Q$6:$Q$2005,'LANÇAMENTOS'!$I$6:$I$2005,$B41,'LANÇAMENTOS'!$E$6:$E$2005,"Saída")) | Q41: =IF($B41="","",SUMIFS('LANÇAMENTOS'!$V$6:$V$2005,'LANÇAMENTOS'!$I$6:$I$2005,$B41,'LANÇAMENTOS'!$E$6:$E$2005,"Saída")) | R41: =IF($B41="","",SUMIFS('LANÇAMENTOS'!$W$6:$W$2005,'LANÇAMENTOS'!$I$6:$I$2005,$B41,'LANÇAMENTOS'!$E$6:$E$2005,"Saída")) | S41: =IF($B41="","",SUMIFS('LANÇAMENTOS'!$W$6:$W$2005,'LANÇAMENTOS'!$I$6:$I$2005,$B41,'LANÇAMENTOS'!$E$6:$E$2005,"Saída",'LANÇAMENTOS'!$C$6:$C$2005,"<"&TODAY())) | T41: =IF($B41="","",IFERROR(IF(SUMPRODUCT(MAX(('LANÇAMENTOS'!$I$6:$I$2005=$B41)*'LANÇAMENTOS'!$B$6:$B$2005))>0,SUMPRODUCT(MAX(('LANÇAMENTOS'!$I$6:$I$2005=$B41)*'LANÇAMENTOS'!$B$6:$B$2005)),""),""))
P42: =IF($B42="","",SUMIFS('LANÇAMENTOS'!$Q$6:$Q$2005,'LANÇAMENTOS'!$I$6:$I$2005,$B42,'LANÇAMENTOS'!$E$6:$E$2005,"Saída")) | Q42: =IF($B42="","",SUMIFS('LANÇAMENTOS'!$V$6:$V$2005,'LANÇAMENTOS'!$I$6:$I$2005,$B42,'LANÇAMENTOS'!$E$6:$E$2005,"Saída")) | R42: =IF($B42="","",SUMIFS('LANÇAMENTOS'!$W$6:$W$2005,'LANÇAMENTOS'!$I$6:$I$2005,$B42,'LANÇAMENTOS'!$E$6:$E$2005,"Saída")) | S42: =IF($B42="","",SUMIFS('LANÇAMENTOS'!$W$6:$W$2005,'LANÇAMENTOS'!$I$6:$I$2005,$B42,'LANÇAMENTOS'!$E$6:$E$2005,"Saída",'LANÇAMENTOS'!$C$6:$C$2005,"<"&TODAY())) | T42: =IF($B42="","",IFERROR(IF(SUMPRODUCT(MAX(('LANÇAMENTOS'!$I$6:$I$2005=$B42)*'LANÇAMENTOS'!$B$6:$B$2005))>0,SUMPRODUCT(MAX(('LANÇAMENTOS'!$I$6:$I$2005=$B42)*'LANÇAMENTOS'!$B$6:$B$2005)),""),""))
P43: =IF($B43="","",SUMIFS('LANÇAMENTOS'!$Q$6:$Q$2005,'LANÇAMENTOS'!$I$6:$I$2005,$B43,'LANÇAMENTOS'!$E$6:$E$2005,"Saída")) | Q43: =IF($B43="","",SUMIFS('LANÇAMENTOS'!$V$6:$V$2005,'LANÇAMENTOS'!$I$6:$I$2005,$B43,'LANÇAMENTOS'!$E$6:$E$2005,"Saída")) | R43: =IF($B43="","",SUMIFS('LANÇAMENTOS'!$W$6:$W$2005,'LANÇAMENTOS'!$I$6:$I$2005,$B43,'LANÇAMENTOS'!$E$6:$E$2005,"Saída")) | S43: =IF($B43="","",SUMIFS('LANÇAMENTOS'!$W$6:$W$2005,'LANÇAMENTOS'!$I$6:$I$2005,$B43,'LANÇAMENTOS'!$E$6:$E$2005,"Saída",'LANÇAMENTOS'!$C$6:$C$2005,"<"&TODAY())) | T43: =IF($B43="","",IFERROR(IF(SUMPRODUCT(MAX(('LANÇAMENTOS'!$I$6:$I$2005=$B43)*'LANÇAMENTOS'!$B$6:$B$2005))>0,SUMPRODUCT(MAX(('LANÇAMENTOS'!$I$6:$I$2005=$B43)*'LANÇAMENTOS'!$B$6:$B$2005)),""),""))
P44: =IF($B44="","",SUMIFS('LANÇAMENTOS'!$Q$6:$Q$2005,'LANÇAMENTOS'!$I$6:$I$2005,$B44,'LANÇAMENTOS'!$E$6:$E$2005,"Saída")) | Q44: =IF($B44="","",SUMIFS('LANÇAMENTOS'!$V$6:$V$2005,'LANÇAMENTOS'!$I$6:$I$2005,$B44,'LANÇAMENTOS'!$E$6:$E$2005,"Saída")) | R44: =IF($B44="","",SUMIFS('LANÇAMENTOS'!$W$6:$W$2005,'LANÇAMENTOS'!$I$6:$I$2005,$B44,'LANÇAMENTOS'!$E$6:$E$2005,"Saída")) | S44: =IF($B44="","",SUMIFS('LANÇAMENTOS'!$W$6:$W$2005,'LANÇAMENTOS'!$I$6:$I$2005,$B44,'LANÇAMENTOS'!$E$6:$E$2005,"Saída",'LANÇAMENTOS'!$C$6:$C$2005,"<"&TODAY())) | T44: =IF($B44="","",IFERROR(IF(SUMPRODUCT(MAX(('LANÇAMENTOS'!$I$6:$I$2005=$B44)*'LANÇAMENTOS'!$B$6:$B$2005))>0,SUMPRODUCT(MAX(('LANÇAMENTOS'!$I$6:$I$2005=$B44)*'LANÇAMENTOS'!$B$6:$B$2005)),""),""))
P45: =IF($B45="","",SUMIFS('LANÇAMENTOS'!$Q$6:$Q$2005,'LANÇAMENTOS'!$I$6:$I$2005,$B45,'LANÇAMENTOS'!$E$6:$E$2005,"Saída")) | Q45: =IF($B45="","",SUMIFS('LANÇAMENTOS'!$V$6:$V$2005,'LANÇAMENTOS'!$I$6:$I$2005,$B45,'LANÇAMENTOS'!$E$6:$E$2005,"Saída")) | R45: =IF($B45="","",SUMIFS('LANÇAMENTOS'!$W$6:$W$2005,'LANÇAMENTOS'!$I$6:$I$2005,$B45,'LANÇAMENTOS'!$E$6:$E$2005,"Saída")) | S45: =IF($B45="","",SUMIFS('LANÇAMENTOS'!$W$6:$W$2005,'LANÇAMENTOS'!$I$6:$I$2005,$B45,'LANÇAMENTOS'!$E$6:$E$2005,"Saída",'LANÇAMENTOS'!$C$6:$C$2005,"<"&TODAY())) | T45: =IF($B45="","",IFERROR(IF(SUMPRODUCT(MAX(('LANÇAMENTOS'!$I$6:$I$2005=$B45)*'LANÇAMENTOS'!$B$6:$B$2005))>0,SUMPRODUCT(MAX(('LANÇAMENTOS'!$I$6:$I$2005=$B45)*'LANÇAMENTOS'!$B$6:$B$2005)),""),""))
P46: =IF($B46="","",SUMIFS('LANÇAMENTOS'!$Q$6:$Q$2005,'LANÇAMENTOS'!$I$6:$I$2005,$B46,'LANÇAMENTOS'!$E$6:$E$2005,"Saída")) | Q46: =IF($B46="","",SUMIFS('LANÇAMENTOS'!$V$6:$V$2005,'LANÇAMENTOS'!$I$6:$I$2005,$B46,'LANÇAMENTOS'!$E$6:$E$2005,"Saída")) | R46: =IF($B46="","",SUMIFS('LANÇAMENTOS'!$W$6:$W$2005,'LANÇAMENTOS'!$I$6:$I$2005,$B46,'LANÇAMENTOS'!$E$6:$E$2005,"Saída")) | S46: =IF($B46="","",SUMIFS('LANÇAMENTOS'!$W$6:$W$2005,'LANÇAMENTOS'!$I$6:$I$2005,$B46,'LANÇAMENTOS'!$E$6:$E$2005,"Saída",'LANÇAMENTOS'!$C$6:$C$2005,"<"&TODAY())) | T46: =IF($B46="","",IFERROR(IF(SUMPRODUCT(MAX(('LANÇAMENTOS'!$I$6:$I$2005=$B46)*'LANÇAMENTOS'!$B$6:$B$2005))>0,SUMPRODUCT(MAX(('LANÇAMENTOS'!$I$6:$I$2005=$B46)*'LANÇAMENTOS'!$B$6:$B$2005)),""),""))
P47: =IF($B47="","",SUMIFS('LANÇAMENTOS'!$Q$6:$Q$2005,'LANÇAMENTOS'!$I$6:$I$2005,$B47,'LANÇAMENTOS'!$E$6:$E$2005,"Saída")) | Q47: =IF($B47="","",SUMIFS('LANÇAMENTOS'!$V$6:$V$2005,'LANÇAMENTOS'!$I$6:$I$2005,$B47,'LANÇAMENTOS'!$E$6:$E$2005,"Saída")) | R47: =IF($B47="","",SUMIFS('LANÇAMENTOS'!$W$6:$W$2005,'LANÇAMENTOS'!$I$6:$I$2005,$B47,'LANÇAMENTOS'!$E$6:$E$2005,"Saída")) | S47: =IF($B47="","",SUMIFS('LANÇAMENTOS'!$W$6:$W$2005,'LANÇAMENTOS'!$I$6:$I$2005,$B47,'LANÇAMENTOS'!$E$6:$E$2005,"Saída",'LANÇAMENTOS'!$C$6:$C$2005,"<"&TODAY())) | T47: =IF($B47="","",IFERROR(IF(SUMPRODUCT(MAX(('LANÇAMENTOS'!$I$6:$I$2005=$B47)*'LANÇAMENTOS'!$B$6:$B$2005))>0,SUMPRODUCT(MAX(('LANÇAMENTOS'!$I$6:$I$2005=$B47)*'LANÇAMENTOS'!$B$6:$B$2005)),""),""))
... P65: =IF($B65="","",SUMIFS('LANÇAMENTOS'!$Q$6:$Q$2005,'LANÇAMENTOS'!$I$6:$I$2005,$B65,'LANÇAMENTOS'!$E$6:$E$2005,"Saída")) | Q65: =IF($B65="","",SUMIFS('LANÇAMENTOS'!$V$6:$V$2005,'LANÇAMENTOS'!$I$6:$I$2005,$B65,'LANÇAMENTOS'!$E$6:$E$2005,"Saída")) | R65: =IF($B65="","",SUMIFS('LANÇAMENTOS'!$W$6:$W$2005,'LANÇAMENTOS'!$I$6:$I$2005,$B65,'LANÇAMENTOS'!$E$6:$E$2005,"Saída")) | S65: =IF($B65="","",SUMIFS('LANÇAMENTOS'!$W$6:$W$2005,'LANÇAMENTOS'!$I$6:$I$2005,$B65,'LANÇAMENTOS'!$E$6:$E$2005,"Saída",'LANÇAMENTOS'!$C$6:$C$2005,"<"&TODAY())) | T65: =IF($B65="","",IFERROR(IF(SUMPRODUCT(MAX(('LANÇAMENTOS'!$I$6:$I$2005=$B65)*'LANÇAMENTOS'!$B$6:$B$2005))>0,SUMPRODUCT(MAX(('LANÇAMENTOS'!$I$6:$I$2005=$B65)*'LANÇAMENTOS'!$B$6:$B$2005)),""),""))

Sheet PLANO DE CONTAS
A1: PLANO DE CONTAS GERENCIAL
A2: Estrutura hierárquica que classifica todos os lançamentos e alimenta o DRE, o fluxo de caixa e o orçamento. Para criar novas contas, use as linhas em branco e escolha os valores das listas.
B3: Plano de contas de exemplo já cadastrado (receitas, custos, despesas administrativas, pessoal, comercial, financeiras, tributos, investimentos, financiamentos e patrimônio).
A5: Código | B5: Grupo | C5: Categoria (subgrupo) | D5: Subcategoria (conta gerencial) | E5: Tipo de conta | F5: Natureza | G5: Tipo de fluxo | H5: Linha do DRE | I5: Ativo? | J5: Observações
A6: 1.1.01 | B6: RECEITAS | C6: Vendas | D6: Vendas de Produtos | E6: Receita | F6: Entrada | G6: Operacional | H6: Faturamento Bruto | I6: Sim
A7: 1.1.02 | B7: RECEITAS | C7: Vendas | D7: Vendas de Serviços | E7: Receita | F7: Entrada | G7: Operacional | H7: Faturamento Bruto | I7: Sim
A8: 1.2.01 | B8: RECEITAS | C8: Outras Receitas | D8: Outras Receitas Operacionais | E8: Receita | F8: Entrada | G8: Operacional | H8: Outras Receitas Operacionais | I8: Sim
A9: 1.3.01 | B9: RECEITAS | C9: Receitas Financeiras | D9: Rendimentos de Aplicações Financeiras | E9: Receita | F9: Entrada | G9: Operacional | H9: Receitas Financeiras | I9: Sim
A10: 1.3.02 | B10: RECEITAS | C10: Receitas Financeiras | D10: Juros Recebidos de Clientes | E10: Receita | F10: Entrada | G10: Operacional | H10: Receitas Financeiras | I10: Sim
A11: 1.3.03 | B11: RECEITAS | C11: Receitas Financeiras | D11: Descontos Obtidos de Fornecedores | E11: Receita | F11: Entrada | G11: Operacional | H11: Receitas Financeiras | I11: Sim
A12: 1.4.01 | B12: RECEITAS | C12: Devoluções e Cancelamentos | D12: Devoluções e Cancelamentos de Vendas | E12: Devolução | F12: Saída | G12: Operacional | H12: Devoluções | I12: Sim
A13: 2.1.01 | B13: CUSTOS | C13: Custos Variáveis | D13: Matéria-prima | E13: Custo | F13: Saída | G13: Operacional | H13: Custos Variáveis | I13: Sim
A14: 2.1.02 | B14: CUSTOS | C14: Custos Variáveis | D14: Mercadorias para Revenda | E14: Custo | F14: Saída | G14: Operacional | H14: Custos Variáveis | I14: Sim
A15: 2.1.03 | B15: CUSTOS | C15: Custos Variáveis | D15: Embalagens | E15: Custo | F15: Saída | G15: Operacional | H15: Custos Variáveis | I15: Sim
A16: 2.1.04 | B16: CUSTOS | C16: Custos Variáveis | D16: Fretes e Entregas sobre Vendas | E16: Custo | F16: Saída | G16: Operacional | H16: Custos Variáveis | I16: Sim
A17: 2.1.05 | B17: CUSTOS | C17: Custos Variáveis | D17: Comissões sobre Vendas | E17: Custo | F17: Saída | G17: Operacional | H17: Custos Variáveis | I17: Sim
... A65: 6.1.02 | B65: PATRIMÔNIO LÍQUIDO | C65: Patrimônio Líquido | D65: Aporte de Capital dos Sócios | E65: Aporte de Capital | F65: Entrada | G65: Financiamento | H65: Financiamentos e Sócios (Principal) | I65: Sim

Sheet CENTRO DE CUSTOS
A1: CENTROS DE CUSTO
A2: Separe o resultado da empresa por área. Classifique cada lançamento com um centro de custo na aba LANÇAMENTOS para ver o desempenho de cada área.
B3: ⚠ DADOS DE EXEMPLO — 8 centros de custo fictícios (administrativo, comercial, produção, logística, marketing, financeiro, diretoria e não alocado).
A5: Código | B5: Centro de custo | C5: Responsável | D5: Descrição / finalidade | E5: Ativo? | F5: Receita (ano) | G5: Custos (ano) | H5: Despesas (ano) | I5: Resultado | J5: Margem
A6: CC01 | B6: Administrativo | C6: Marina Alves | D6: Aluguel, utilidades, escritório e pessoal administrativo | E6: Sim | F6: =IF($B6="","",SUMIFS('LANÇAMENTOS'!$AE$6:$AE$2005,'LANÇAMENTOS'!$H$6:$H$2005,$B6,'LANÇAMENTOS'!$E$6:$E$2005,"Entrada")) | G6: =IF($B6="","",SUMIFS('LANÇAMENTOS'!$AE$6:$AE$2005,'LANÇAMENTOS'!$H$6:$H$2005,$B6,'LANÇAMENTOS'!$AF$6:$AF$2005,"Custos Variáveis")) | H6: =IF($B6="","",SUMIFS('LANÇAMENTOS'!$AE$6:$AE$2005,'LANÇAMENTOS'!$H$6:$H$2005,$B6,'LANÇAMENTOS'!$E$6:$E$2005,"Saída")-SUMIFS('LANÇAMENTOS'!$AE$6:$AE$2005,'LANÇAMENTOS'!$H$6:$H$2005,$B6,'LANÇAMENTOS'!$AF$6:$AF$2005,"Custos Variáveis")-SUMIFS('LANÇAMENTOS'!$AE$6:$AE$2005,'LANÇAMENTOS'!$H$6:$H$2005,$B6,'LANÇAMENTOS'!$AF$6:$AF$2005,"Investimentos (CAPEX)")-SUMIFS('LANÇAMENTOS'!$AE$6:$AE$2005,'LANÇAMENTOS'!$H$6:$H$2005,$B6,'LANÇAMENTOS'!$AF$6:$AF$2005,"Financiamentos e Sócios (Principal)")-SUMIFS('LANÇAMENTOS'!$AE$6:$AE$2005,'LANÇAMENTOS'!$H$6:$H$2005,$B6,'LANÇAMENTOS'!$AF$6:$AF$2005,"Distribuição de Lucros")) | I6: =IF($B6="","",$F6-$G6-$H6) | J6: =IF(OR($B6="",$F6=0),"",$I6/$F6)
A7: CC02 | B7: Comercial | C7: Carlos Menezes | D7: Equipe de vendas, comissões e prospecção | E7: Sim | F7: =IF($B7="","",SUMIFS('LANÇAMENTOS'!$AE$6:$AE$2005,'LANÇAMENTOS'!$H$6:$H$2005,$B7,'LANÇAMENTOS'!$E$6:$E$2005,"Entrada")) | G7: =IF($B7="","",SUMIFS('LANÇAMENTOS'!$AE$6:$AE$2005,'LANÇAMENTOS'!$H$6:$H$2005,$B7,'LANÇAMENTOS'!$AF$6:$AF$2005,"Custos Variáveis")) | H7: =IF($B7="","",SUMIFS('LANÇAMENTOS'!$AE$6:$AE$2005,'LANÇAMENTOS'!$H$6:$H$2005,$B7,'LANÇAMENTOS'!$E$6:$E$2005,"Saída")-SUMIFS('LANÇAMENTOS'!$AE$6:$AE$2005,'LANÇAMENTOS'!$H$6:$H$2005,$B7,'LANÇAMENTOS'!$AF$6:$AF$2005,"Custos Variáveis")-SUMIFS('LANÇAMENTOS'!$AE$6:$AE$2005,'LANÇAMENTOS'!$H$6:$H$2005,$B7,'LANÇAMENTOS'!$AF$6:$AF$2005,"Investimentos (CAPEX)")-SUMIFS('LANÇAMENTOS'!$AE$6:$AE$2005,'LANÇAMENTOS'!$H$6:$H$2005,$B7,'LANÇAMENTOS'!$AF$6:$AF$2005,"Financiamentos e Sócios (Principal)")-SUMIFS('LANÇAMENTOS'!$AE$6:$AE$2005,'LANÇAMENTOS'!$H$6:$H$2005,$B7,'LANÇAMENTOS'!$AF$6:$AF$2005,"Distribuição de Lucros")) | I7: =IF($B7="","",$F7-$G7-$H7) | J7: =IF(OR($B7="",$F7=0),"",$I7/$F7)
A8: CC03 | B8: Produção | C8: Roberto Nunes | D8: Beneficiamento e preparação de pedidos | E8: Sim | F8: =IF($B8="","",SUMIFS('LANÇAMENTOS'!$AE$6:$AE$2005,'LANÇAMENTOS'!$H$6:$H$2005,$B8,'LANÇAMENTOS'!$E$6:$E$2005,"Entrada")) | G8: =IF($B8="","",SUMIFS('LANÇAMENTOS'!$AE$6:$AE$2005,'LANÇAMENTOS'!$H$6:$H$2005,$B8,'LANÇAMENTOS'!$AF$6:$AF$2005,"Custos Variáveis")) | H8: =IF($B8="","",SUMIFS('LANÇAMENTOS'!$AE$6:$AE$2005,'LANÇAMENTOS'!$H$6:$H$2005,$B8,'LANÇAMENTOS'!$E$6:$E$2005,"Saída")-SUMIFS('LANÇAMENTOS'!$AE$6:$AE$2005,'LANÇAMENTOS'!$H$6:$H$2005,$B8,'LANÇAMENTOS'!$AF$6:$AF$2005,"Custos Variáveis")-SUMIFS('LANÇAMENTOS'!$AE$6:$AE$2005,'LANÇAMENTOS'!$H$6:$H$2005,$B8,'LANÇAMENTOS'!$AF$6:$AF$2005,"Investimentos (CAPEX)")-SUMIFS('LANÇAMENTOS'!$AE$6:$AE$2005,'LANÇAMENTOS'!$H$6:$H$2005,$B8,'LANÇAMENTOS'!$AF$6:$AF$2005,"Financiamentos e Sócios (Principal)")-SUMIFS('LANÇAMENTOS'!$AE$6:$AE$2005,'LANÇAMENTOS'!$H$6:$H$2005,$B8,'LANÇAMENTOS'!$AF$6:$AF$2005,"Distribuição de Lucros")) | I8: =IF($B8="","",$F8-$G8-$H8) | J8: =IF(OR($B8="",$F8=0),"",$I8/$F8)
A9: CC04 | B9: Logística | C9: Paulo Ricardo | D9: Estoque, expedição, fretes e entregas | E9: Sim | F9: =IF($B9="","",SUMIFS('LANÇAMENTOS'!$AE$6:$AE$2005,'LANÇAMENTOS'!$H$6:$H$2005,$B9,'LANÇAMENTOS'!$E$6:$E$2005,"Entrada")) | G9: =IF($B9="","",SUMIFS('LANÇAMENTOS'!$AE$6:$AE$2005,'LANÇAMENTOS'!$H$6:$H$2005,$B9,'LANÇAMENTOS'!$AF$6:$AF$2005,"Custos Variáveis")) | H9: =IF($B9="","",SUMIFS('LANÇAMENTOS'!$AE$6:$AE$2005,'LANÇAMENTOS'!$H$6:$H$2005,$B9,'LANÇAMENTOS'!$E$6:$E$2005,"Saída")-SUMIFS('LANÇAMENTOS'!$AE$6:$AE$2005,'LANÇAMENTOS'!$H$6:$H$2005,$B9,'LANÇAMENTOS'!$AF$6:$AF$2005,"Custos Variáveis")-SUMIFS('LANÇAMENTOS'!$AE$6:$AE$2005,'LANÇAMENTOS'!$H$6:$H$2005,$B9,'LANÇAMENTOS'!$AF$6:$AF$2005,"Investimentos (CAPEX)")-SUMIFS('LANÇAMENTOS'!$AE$6:$AE$2005,'LANÇAMENTOS'!$H$6:$H$2005,$B9,'LANÇAMENTOS'!$AF$6:$AF$2005,"Financiamentos e Sócios (Principal)")-SUMIFS('LANÇAMENTOS'!$AE$6:$AE$2005,'LANÇAMENTOS'!$H$6:$H$2005,$B9,'LANÇAMENTOS'!$AF$6:$AF$2005,"Distribuição de Lucros")) | I9: =IF($B9="","",$F9-$G9-$H9) | J9: =IF(OR($B9="",$F9=0),"",$I9/$F9)
A10: CC05 | B10: Marketing | C10: Ana Paula Souza | D10: Marketing digital, publicidade e eventos | E10: Sim | F10: =IF($B10="","",SUMIFS('LANÇAMENTOS'!$AE$6:$AE$2005,'LANÇAMENTOS'!$H$6:$H$2005,$B10,'LANÇAMENTOS'!$E$6:$E$2005,"Entrada")) | G10: =IF($B10="","",SUMIFS('LANÇAMENTOS'!$AE$6:$AE$2005,'LANÇAMENTOS'!$H$6:$H$2005,$B10,'LANÇAMENTOS'!$AF$6:$AF$2005,"Custos Variáveis")) | H10: =IF($B10="","",SUMIFS('LANÇAMENTOS'!$AE$6:$AE$2005,'LANÇAMENTOS'!$H$6:$H$2005,$B10,'LANÇAMENTOS'!$E$6:$E$2005,"Saída")-SUMIFS('LANÇAMENTOS'!$AE$6:$AE$2005,'LANÇAMENTOS'!$H$6:$H$2005,$B10,'LANÇAMENTOS'!$AF$6:$AF$2005,"Custos Variáveis")-SUMIFS('LANÇAMENTOS'!$AE$6:$AE$2005,'LANÇAMENTOS'!$H$6:$H$2005,$B10,'LANÇAMENTOS'!$AF$6:$AF$2005,"Investimentos (CAPEX)")-SUMIFS('LANÇAMENTOS'!$AE$6:$AE$2005,'LANÇAMENTOS'!$H$6:$H$2005,$B10,'LANÇAMENTOS'!$AF$6:$AF$2005,"Financiamentos e Sócios (Principal)")-SUMIFS('LANÇAMENTOS'!$AE$6:$AE$2005,'LANÇAMENTOS'!$H$6:$H$2005,$B10,'LANÇAMENTOS'!$AF$6:$AF$2005,"Distribuição de Lucros")) | I10: =IF($B10="","",$F10-$G10-$H10) | J10: =IF(OR($B10="",$F10=0),"",$I10/$F10)
A11: CC06 | B11: Financeiro | C11: Marina Alves | D11: Tesouraria, cobrança, contabilidade e tributos | E11: Sim | F11: =IF($B11="","",SUMIFS('LANÇAMENTOS'!$AE$6:$AE$2005,'LANÇAMENTOS'!$H$6:$H$2005,$B11,'LANÇAMENTOS'!$E$6:$E$2005,"Entrada")) | G11: =IF($B11="","",SUMIFS('LANÇAMENTOS'!$AE$6:$AE$2005,'LANÇAMENTOS'!$H$6:$H$2005,$B11,'LANÇAMENTOS'!$AF$6:$AF$2005,"Custos Variáveis")) | H11: =IF($B11="","",SUMIFS('LANÇAMENTOS'!$AE$6:$AE$2005,'LANÇAMENTOS'!$H$6:$H$2005,$B11,'LANÇAMENTOS'!$E$6:$E$2005,"Saída")-SUMIFS('LANÇAMENTOS'!$AE$6:$AE$2005,'LANÇAMENTOS'!$H$6:$H$2005,$B11,'LANÇAMENTOS'!$AF$6:$AF$2005,"Custos Variáveis")-SUMIFS('LANÇAMENTOS'!$AE$6:$AE$2005,'LANÇAMENTOS'!$H$6:$H$2005,$B11,'LANÇAMENTOS'!$AF$6:$AF$2005,"Investimentos (CAPEX)")-SUMIFS('LANÇAMENTOS'!$AE$6:$AE$2005,'LANÇAMENTOS'!$H$6:$H$2005,$B11,'LANÇAMENTOS'!$AF$6:$AF$2005,"Financiamentos e Sócios (Principal)")-SUMIFS('LANÇAMENTOS'!$AE$6:$AE$2005,'LANÇAMENTOS'!$H$6:$H$2005,$B11,'LANÇAMENTOS'!$AF$6:$AF$2005,"Distribuição de Lucros")) | I11: =IF($B11="","",$F11-$G11-$H11) | J11: =IF(OR($B11="",$F11=0),"",$I11/$F11)
A12: CC07 | B12: Diretoria | C12: Jefferson Andrade | D12: Pró-labore, estratégia e investimentos | E12: Sim | F12: =IF($B12="","",SUMIFS('LANÇAMENTOS'!$AE$6:$AE$2005,'LANÇAMENTOS'!$H$6:$H$2005,$B12,'LANÇAMENTOS'!$E$6:$E$2005,"Entrada")) | G12: =IF($B12="","",SUMIFS('LANÇAMENTOS'!$AE$6:$AE$2005,'LANÇAMENTOS'!$H$6:$H$2005,$B12,'LANÇAMENTOS'!$AF$6:$AF$2005,"Custos Variáveis")) | H12: =IF($B12="","",SUMIFS('LANÇAMENTOS'!$AE$6:$AE$2005,'LANÇAMENTOS'!$H$6:$H$2005,$B12,'LANÇAMENTOS'!$E$6:$E$2005,"Saída")-SUMIFS('LANÇAMENTOS'!$AE$6:$AE$2005,'LANÇAMENTOS'!$H$6:$H$2005,$B12,'LANÇAMENTOS'!$AF$6:$AF$2005,"Custos Variáveis")-SUMIFS('LANÇAMENTOS'!$AE$6:$AE$2005,'LANÇAMENTOS'!$H$6:$H$2005,$B12,'LANÇAMENTOS'!$AF$6:$AF$2005,"Investimentos (CAPEX)")-SUMIFS('LANÇAMENTOS'!$AE$6:$AE$2005,'LANÇAMENTOS'!$H$6:$H$2005,$B12,'LANÇAMENTOS'!$AF$6:$AF$2005,"Financiamentos e Sócios (Principal)")-SUMIFS('LANÇAMENTOS'!$AE$6:$AE$2005,'LANÇAMENTOS'!$H$6:$H$2005,$B12,'LANÇAMENTOS'!$AF$6:$AF$2005,"Distribuição de Lucros")) | I12: =IF($B12="","",$F12-$G12-$H12) | J12: =IF(OR($B12="",$F12=0),"",$I12/$F12)
A13: CC08 | B13: Não alocado | C13: — | D13: Lançamentos ainda sem centro de custo definido | E13: Sim | F13: =IF($B13="","",SUMIFS('LANÇAMENTOS'!$AE$6:$AE$2005,'LANÇAMENTOS'!$H$6:$H$2005,$B13,'LANÇAMENTOS'!$E$6:$E$2005,"Entrada")) | G13: =IF($B13="","",SUMIFS('LANÇAMENTOS'!$AE$6:$AE$2005,'LANÇAMENTOS'!$H$6:$H$2005,$B13,'LANÇAMENTOS'!$AF$6:$AF$2005,"Custos Variáveis")) | H13: =IF($B13="","",SUMIFS('LANÇAMENTOS'!$AE$6:$AE$2005,'LANÇAMENTOS'!$H$6:$H$2005,$B13,'LANÇAMENTOS'!$E$6:$E$2005,"Saída")-SUMIFS('LANÇAMENTOS'!$AE$6:$AE$2005,'LANÇAMENTOS'!$H$6:$H$2005,$B13,'LANÇAMENTOS'!$AF$6:$AF$2005,"Custos Variáveis")-SUMIFS('LANÇAMENTOS'!$AE$6:$AE$2005,'LANÇAMENTOS'!$H$6:$H$2005,$B13,'LANÇAMENTOS'!$AF$6:$AF$2005,"Investimentos (CAPEX)")-SUMIFS('LANÇAMENTOS'!$AE$6:$AE$2005,'LANÇAMENTOS'!$H$6:$H$2005,$B13,'LANÇAMENTOS'!$AF$6:$AF$2005,"Financiamentos e Sócios (Principal)")-SUMIFS('LANÇAMENTOS'!$AE$6:$AE$2005,'LANÇAMENTOS'!$H$6:$H$2005,$B13,'LANÇAMENTOS'!$AF$6:$AF$2005,"Distribuição de Lucros")) | I13: =IF($B13="","",$F13-$G13-$H13) | J13: =IF(OR($B13="",$F13=0),"",$I13/$F13)
F14: =IF($B14="","",SUMIFS('LANÇAMENTOS'!$AE$6:$AE$2005,'LANÇAMENTOS'!$H$6:$H$2005,$B14,'LANÇAMENTOS'!$E$6:$E$2005,"Entrada")) | G14: =IF($B14="","",SUMIFS('LANÇAMENTOS'!$AE$6:$AE$2005,'LANÇAMENTOS'!$H$6:$H$2005,$B14,'LANÇAMENTOS'!$AF$6:$AF$2005,"Custos Variáveis")) | H14: =IF($B14="","",SUMIFS('LANÇAMENTOS'!$AE$6:$AE$2005,'LANÇAMENTOS'!$H$6:$H$2005,$B14,'LANÇAMENTOS'!$E$6:$E$2005,"Saída")-SUMIFS('LANÇAMENTOS'!$AE$6:$AE$2005,'LANÇAMENTOS'!$H$6:$H$2005,$B14,'LANÇAMENTOS'!$AF$6:$AF$2005,"Custos Variáveis")-SUMIFS('LANÇAMENTOS'!$AE$6:$AE$2005,'LANÇAMENTOS'!$H$6:$H$2005,$B14,'LANÇAMENTOS'!$AF$6:$AF$2005,"Investimentos (CAPEX)")-SUMIFS('LANÇAMENTOS'!$AE$6:$AE$2005,'LANÇAMENTOS'!$H$6:$H$2005,$B14,'LANÇAMENTOS'!$AF$6:$AF$2005,"Financiamentos e Sócios (Principal)")-SUMIFS('LANÇAMENTOS'!$AE$6:$AE$2005,'LANÇAMENTOS'!$H$6:$H$2005,$B14,'LANÇAMENTOS'!$AF$6:$AF$2005,"Distribuição de Lucros")) | I14: =IF($B14="","",$F14-$G14-$H14) | J14: =IF(OR($B14="",$F14=0),"",$I14/$F14)
F15: =IF($B15="","",SUMIFS('LANÇAMENTOS'!$AE$6:$AE$2005,'LANÇAMENTOS'!$H$6:$H$2005,$B15,'LANÇAMENTOS'!$E$6:$E$2005,"Entrada")) | G15: =IF($B15="","",SUMIFS('LANÇAMENTOS'!$AE$6:$AE$2005,'LANÇAMENTOS'!$H$6:$H$2005,$B15,'LANÇAMENTOS'!$AF$6:$AF$2005,"Custos Variáveis")) | H15: =IF($B15="","",SUMIFS('LANÇAMENTOS'!$AE$6:$AE$2005,'LANÇAMENTOS'!$H$6:$H$2005,$B15,'LANÇAMENTOS'!$E$6:$E$2005,"Saída")-SUMIFS('LANÇAMENTOS'!$AE$6:$AE$2005,'LANÇAMENTOS'!$H$6:$H$2005,$B15,'LANÇAMENTOS'!$AF$6:$AF$2005,"Custos Variáveis")-SUMIFS('LANÇAMENTOS'!$AE$6:$AE$2005,'LANÇAMENTOS'!$H$6:$H$2005,$B15,'LANÇAMENTOS'!$AF$6:$AF$2005,"Investimentos (CAPEX)")-SUMIFS('LANÇAMENTOS'!$AE$6:$AE$2005,'LANÇAMENTOS'!$H$6:$H$2005,$B15,'LANÇAMENTOS'!$AF$6:$AF$2005,"Financiamentos e Sócios (Principal)")-SUMIFS('LANÇAMENTOS'!$AE$6:$AE$2005,'LANÇAMENTOS'!$H$6:$H$2005,$B15,'LANÇAMENTOS'!$AF$6:$AF$2005,"Distribuição de Lucros")) | I15: =IF($B15="","",$F15-$G15-$H15) | J15: =IF(OR($B15="",$F15=0),"",$I15/$F15)
F16: =IF($B16="","",SUMIFS('LANÇAMENTOS'!$AE$6:$AE$2005,'LANÇAMENTOS'!$H$6:$H$2005,$B16,'LANÇAMENTOS'!$E$6:$E$2005,"Entrada")) | G16: =IF($B16="","",SUMIFS('LANÇAMENTOS'!$AE$6:$AE$2005,'LANÇAMENTOS'!$H$6:$H$2005,$B16,'LANÇAMENTOS'!$AF$6:$AF$2005,"Custos Variáveis")) | H16: =IF($B16="","",SUMIFS('LANÇAMENTOS'!$AE$6:$AE$2005,'LANÇAMENTOS'!$H$6:$H$2005,$B16,'LANÇAMENTOS'!$E$6:$E$2005,"Saída")-SUMIFS('LANÇAMENTOS'!$AE$6:$AE$2005,'LANÇAMENTOS'!$H$6:$H$2005,$B16,'LANÇAMENTOS'!$AF$6:$AF$2005,"Custos Variáveis")-SUMIFS('LANÇAMENTOS'!$AE$6:$AE$2005,'LANÇAMENTOS'!$H$6:$H$2005,$B16,'LANÇAMENTOS'!$AF$6:$AF$2005,"Investimentos (CAPEX)")-SUMIFS('LANÇAMENTOS'!$AE$6:$AE$2005,'LANÇAMENTOS'!$H$6:$H$2005,$B16,'LANÇAMENTOS'!$AF$6:$AF$2005,"Financiamentos e Sócios (Principal)")-SUMIFS('LANÇAMENTOS'!$AE$6:$AE$2005,'LANÇAMENTOS'!$H$6:$H$2005,$B16,'LANÇAMENTOS'!$AF$6:$AF$2005,"Distribuição de Lucros")) | I16: =IF($B16="","",$F16-$G16-$H16) | J16: =IF(OR($B16="",$F16=0),"",$I16/$F16)
F17: =IF($B17="","",SUMIFS('LANÇAMENTOS'!$AE$6:$AE$2005,'LANÇAMENTOS'!$H$6:$H$2005,$B17,'LANÇAMENTOS'!$E$6:$E$2005,"Entrada")) | G17: =IF($B17="","",SUMIFS('LANÇAMENTOS'!$AE$6:$AE$2005,'LANÇAMENTOS'!$H$6:$H$2005,$B17,'LANÇAMENTOS'!$AF$6:$AF$2005,"Custos Variáveis")) | H17: =IF($B17="","",SUMIFS('LANÇAMENTOS'!$AE$6:$AE$2005,'LANÇAMENTOS'!$H$6:$H$2005,$B17,'LANÇAMENTOS'!$E$6:$E$2005,"Saída")-SUMIFS('LANÇAMENTOS'!$AE$6:$AE$2005,'LANÇAMENTOS'!$H$6:$H$2005,$B17,'LANÇAMENTOS'!$AF$6:$AF$2005,"Custos Variáveis")-SUMIFS('LANÇAMENTOS'!$AE$6:$AE$2005,'LANÇAMENTOS'!$H$6:$H$2005,$B17,'LANÇAMENTOS'!$AF$6:$AF$2005,"Investimentos (CAPEX)")-SUMIFS('LANÇAMENTOS'!$AE$6:$AE$2005,'LANÇAMENTOS'!$H$6:$H$2005,$B17,'LANÇAMENTOS'!$AF$6:$AF$2005,"Financiamentos e Sócios (Principal)")-SUMIFS('LANÇAMENTOS'!$AE$6:$AE$2005,'LANÇAMENTOS'!$H$6:$H$2005,$B17,'LANÇAMENTOS'!$AF$6:$AF$2005,"Distribuição de Lucros")) | I17: =IF($B17="","",$F17-$G17-$H17) | J17: =IF(OR($B17="",$F17=0),"",$I17/$F17)
F18: =IF($B18="","",SUMIFS('LANÇAMENTOS'!$AE$6:$AE$2005,'LANÇAMENTOS'!$H$6:$H$2005,$B18,'LANÇAMENTOS'!$E$6:$E$2005,"Entrada")) | G18: =IF($B18="","",SUMIFS('LANÇAMENTOS'!$AE$6:$AE$2005,'LANÇAMENTOS'!$H$6:$H$2005,$B18,'LANÇAMENTOS'!$AF$6:$AF$2005,"Custos Variáveis")) | H18: =IF($B18="","",SUMIFS('LANÇAMENTOS'!$AE$6:$AE$2005,'LANÇAMENTOS'!$H$6:$H$2005,$B18,'LANÇAMENTOS'!$E$6:$E$2005,"Saída")-SUMIFS('LANÇAMENTOS'!$AE$6:$AE$2005,'LANÇAMENTOS'!$H$6:$H$2005,$B18,'LANÇAMENTOS'!$AF$6:$AF$2005,"Custos Variáveis")-SUMIFS('LANÇAMENTOS'!$AE$6:$AE$2005,'LANÇAMENTOS'!$H$6:$H$2005,$B18,'LANÇAMENTOS'!$AF$6:$AF$2005,"Investimentos (CAPEX)")-SUMIFS('LANÇAMENTOS'!$AE$6:$AE$2005,'LANÇAMENTOS'!$H$6:$H$2005,$B18,'LANÇAMENTOS'!$AF$6:$AF$2005,"Financiamentos e Sócios (Principal)")-SUMIFS('LANÇAMENTOS'!$AE$6:$AE$2005,'LANÇAMENTOS'!$H$6:$H$2005,$B18,'LANÇAMENTOS'!$AF$6:$AF$2005,"Distribuição de Lucros")) | I18: =IF($B18="","",$F18-$G18-$H18) | J18: =IF(OR($B18="",$F18=0),"",$I18/$F18)
F19: =IF($B19="","",SUMIFS('LANÇAMENTOS'!$AE$6:$AE$2005,'LANÇAMENTOS'!$H$6:$H$2005,$B19,'LANÇAMENTOS'!$E$6:$E$2005,"Entrada")) | G19: =IF($B19="","",SUMIFS('LANÇAMENTOS'!$AE$6:$AE$2005,'LANÇAMENTOS'!$H$6:$H$2005,$B19,'LANÇAMENTOS'!$AF$6:$AF$2005,"Custos Variáveis")) | H19: =IF($B19="","",SUMIFS('LANÇAMENTOS'!$AE$6:$AE$2005,'LANÇAMENTOS'!$H$6:$H$2005,$B19,'LANÇAMENTOS'!$E$6:$E$2005,"Saída")-SUMIFS('LANÇAMENTOS'!$AE$6:$AE$2005,'LANÇAMENTOS'!$H$6:$H$2005,$B19,'LANÇAMENTOS'!$AF$6:$AF$2005,"Custos Variáveis")-SUMIFS('LANÇAMENTOS'!$AE$6:$AE$2005,'LANÇAMENTOS'!$H$6:$H$2005,$B19,'LANÇAMENTOS'!$AF$6:$AF$2005,"Investimentos (CAPEX)")-SUMIFS('LANÇAMENTOS'!$AE$6:$AE$2005,'LANÇAMENTOS'!$H$6:$H$2005,$B19,'LANÇAMENTOS'!$AF$6:$AF$2005,"Financiamentos e Sócios (Principal)")-SUMIFS('LANÇAMENTOS'!$AE$6:$AE$2005,'LANÇAMENTOS'!$H$6:$H$2005,$B19,'LANÇAMENTOS'!$AF$6:$AF$2005,"Distribuição de Lucros")) | I19: =IF($B19="","",$F19-$G19-$H19) | J19: =IF(OR($B19="",$F19=0),"",$I19/$F19)
F20: =IF($B20="","",SUMIFS('LANÇAMENTOS'!$AE$6:$AE$2005,'LANÇAMENTOS'!$H$6:$H$2005,$B20,'LANÇAMENTOS'!$E$6:$E$2005,"Entrada")) | G20: =IF($B20="","",SUMIFS('LANÇAMENTOS'!$AE$6:$AE$2005,'LANÇAMENTOS'!$H$6:$H$2005,$B20,'LANÇAMENTOS'!$AF$6:$AF$2005,"Custos Variáveis")) | H20: =IF($B20="","",SUMIFS('LANÇAMENTOS'!$AE$6:$AE$2005,'LANÇAMENTOS'!$H$6:$H$2005,$B20,'LANÇAMENTOS'!$E$6:$E$2005,"Saída")-SUMIFS('LANÇAMENTOS'!$AE$6:$AE$2005,'LANÇAMENTOS'!$H$6:$H$2005,$B20,'LANÇAMENTOS'!$AF$6:$AF$2005,"Custos Variáveis")-SUMIFS('LANÇAMENTOS'!$AE$6:$AE$2005,'LANÇAMENTOS'!$H$6:$H$2005,$B20,'LANÇAMENTOS'!$AF$6:$AF$2005,"Investimentos (CAPEX)")-SUMIFS('LANÇAMENTOS'!$AE$6:$AE$2005,'LANÇAMENTOS'!$H$6:$H$2005,$B20,'LANÇAMENTOS'!$AF$6:$AF$2005,"Financiamentos e Sócios (Principal)")-SUMIFS('LANÇAMENTOS'!$AE$6:$AE$2005,'LANÇAMENTOS'!$H$6:$H$2005,$B20,'LANÇAMENTOS'!$AF$6:$AF$2005,"Distribuição de Lucros")) | I20: =IF($B20="","",$F20-$G20-$H20) | J20: =IF(OR($B20="",$F20=0),"",$I20/$F20)
F21: =IF($B21="","",SUMIFS('LANÇAMENTOS'!$AE$6:$AE$2005,'LANÇAMENTOS'!$H$6:$H$2005,$B21,'LANÇAMENTOS'!$E$6:$E$2005,"Entrada")) | G21: =IF($B21="","",SUMIFS('LANÇAMENTOS'!$AE$6:$AE$2005,'LANÇAMENTOS'!$H$6:$H$2005,$B21,'LANÇAMENTOS'!$AF$6:$AF$2005,"Custos Variáveis")) | H21: =IF($B21="","",SUMIFS('LANÇAMENTOS'!$AE$6:$AE$2005,'LANÇAMENTOS'!$H$6:$H$2005,$B21,'LANÇAMENTOS'!$E$6:$E$2005,"Saída")-SUMIFS('LANÇAMENTOS'!$AE$6:$AE$2005,'LANÇAMENTOS'!$H$6:$H$2005,$B21,'LANÇAMENTOS'!$AF$6:$AF$2005,"Custos Variáveis")-SUMIFS('LANÇAMENTOS'!$AE$6:$AE$2005,'LANÇAMENTOS'!$H$6:$H$2005,$B21,'LANÇAMENTOS'!$AF$6:$AF$2005,"Investimentos (CAPEX)")-SUMIFS('LANÇAMENTOS'!$AE$6:$AE$2005,'LANÇAMENTOS'!$H$6:$H$2005,$B21,'LANÇAMENTOS'!$AF$6:$AF$2005,"Financiamentos e Sócios (Principal)")-SUMIFS('LANÇAMENTOS'!$AE$6:$AE$2005,'LANÇAMENTOS'!$H$6:$H$2005,$B21,'LANÇAMENTOS'!$AF$6:$AF$2005,"Distribuição de Lucros")) | I21: =IF($B21="","",$F21-$G21-$H21) | J21: =IF(OR($B21="",$F21=0),"",$I21/$F21)
F22: =IF($B22="","",SUMIFS('LANÇAMENTOS'!$AE$6:$AE$2005,'LANÇAMENTOS'!$H$6:$H$2005,$B22,'LANÇAMENTOS'!$E$6:$E$2005,"Entrada")) | G22: =IF($B22="","",SUMIFS('LANÇAMENTOS'!$AE$6:$AE$2005,'LANÇAMENTOS'!$H$6:$H$2005,$B22,'LANÇAMENTOS'!$AF$6:$AF$2005,"Custos Variáveis")) | H22: =IF($B22="","",SUMIFS('LANÇAMENTOS'!$AE$6:$AE$2005,'LANÇAMENTOS'!$H$6:$H$2005,$B22,'LANÇAMENTOS'!$E$6:$E$2005,"Saída")-SUMIFS('LANÇAMENTOS'!$AE$6:$AE$2005,'LANÇAMENTOS'!$H$6:$H$2005,$B22,'LANÇAMENTOS'!$AF$6:$AF$2005,"Custos Variáveis")-SUMIFS('LANÇAMENTOS'!$AE$6:$AE$2005,'LANÇAMENTOS'!$H$6:$H$2005,$B22,'LANÇAMENTOS'!$AF$6:$AF$2005,"Investimentos (CAPEX)")-SUMIFS('LANÇAMENTOS'!$AE$6:$AE$2005,'LANÇAMENTOS'!$H$6:$H$2005,$B22,'LANÇAMENTOS'!$AF$6:$AF$2005,"Financiamentos e Sócios (Principal)")-SUMIFS('LANÇAMENTOS'!$AE$6:$AE$2005,'LANÇAMENTOS'!$H$6:$H$2005,$B22,'LANÇAMENTOS'!$AF$6:$AF$2005,"Distribuição de Lucros")) | I22: =IF($B22="","",$F22-$G22-$H22) | J22: =IF(OR($B22="",$F22=0),"",$I22/$F22)
F23: =IF($B23="","",SUMIFS('LANÇAMENTOS'!$AE$6:$AE$2005,'LANÇAMENTOS'!$H$6:$H$2005,$B23,'LANÇAMENTOS'!$E$6:$E$2005,"Entrada")) | G23: =IF($B23="","",SUMIFS('LANÇAMENTOS'!$AE$6:$AE$2005,'LANÇAMENTOS'!$H$6:$H$2005,$B23,'LANÇAMENTOS'!$AF$6:$AF$2005,"Custos Variáveis")) | H23: =IF($B23="","",SUMIFS('LANÇAMENTOS'!$AE$6:$AE$2005,'LANÇAMENTOS'!$H$6:$H$2005,$B23,'LANÇAMENTOS'!$E$6:$E$2005,"Saída")-SUMIFS('LANÇAMENTOS'!$AE$6:$AE$2005,'LANÇAMENTOS'!$H$6:$H$2005,$B23,'LANÇAMENTOS'!$AF$6:$AF$2005,"Custos Variáveis")-SUMIFS('LANÇAMENTOS'!$AE$6:$AE$2005,'LANÇAMENTOS'!$H$6:$H$2005,$B23,'LANÇAMENTOS'!$AF$6:$AF$2005,"Investimentos (CAPEX)")-SUMIFS('LANÇAMENTOS'!$AE$6:$AE$2005,'LANÇAMENTOS'!$H$6:$H$2005,$B23,'LANÇAMENTOS'!$AF$6:$AF$2005,"Financiamentos e Sócios (Principal)")-SUMIFS('LANÇAMENTOS'!$AE$6:$AE$2005,'LANÇAMENTOS'!$H$6:$H$2005,$B23,'LANÇAMENTOS'!$AF$6:$AF$2005,"Distribuição de Lucros")) | I23: =IF($B23="","",$F23-$G23-$H23) | J23: =IF(OR($B23="",$F23=0),"",$I23/$F23)
F24: =IF($B24="","",SUMIFS('LANÇAMENTOS'!$AE$6:$AE$2005,'LANÇAMENTOS'!$H$6:$H$2005,$B24,'LANÇAMENTOS'!$E$6:$E$2005,"Entrada")) | G24: =IF($B24="","",SUMIFS('LANÇAMENTOS'!$AE$6:$AE$2005,'LANÇAMENTOS'!$H$6:$H$2005,$B24,'LANÇAMENTOS'!$AF$6:$AF$2005,"Custos Variáveis")) | H24: =IF($B24="","",SUMIFS('LANÇAMENTOS'!$AE$6:$AE$2005,'LANÇAMENTOS'!$H$6:$H$2005,$B24,'LANÇAMENTOS'!$E$6:$E$2005,"Saída")-SUMIFS('LANÇAMENTOS'!$AE$6:$AE$2005,'LANÇAMENTOS'!$H$6:$H$2005,$B24,'LANÇAMENTOS'!$AF$6:$AF$2005,"Custos Variáveis")-SUMIFS('LANÇAMENTOS'!$AE$6:$AE$2005,'LANÇAMENTOS'!$H$6:$H$2005,$B24,'LANÇAMENTOS'!$AF$6:$AF$2005,"Investimentos (CAPEX)")-SUMIFS('LANÇAMENTOS'!$AE$6:$AE$2005,'LANÇAMENTOS'!$H$6:$H$2005,$B24,'LANÇAMENTOS'!$AF$6:$AF$2005,"Financiamentos e Sócios (Principal)")-SUMIFS('LANÇAMENTOS'!$AE$6:$AE$2005,'LANÇAMENTOS'!$H$6:$H$2005,$B24,'LANÇAMENTOS'!$AF$6:$AF$2005,"Distribuição de Lucros")) | I24: =IF($B24="","",$F24-$G24-$H24) | J24: =IF(OR($B24="",$F24=0),"",$I24/$F24)
F25: =IF($B25="","",SUMIFS('LANÇAMENTOS'!$AE$6:$AE$2005,'LANÇAMENTOS'!$H$6:$H$2005,$B25,'LANÇAMENTOS'!$E$6:$E$2005,"Entrada")) | G25: =IF($B25="","",SUMIFS('LANÇAMENTOS'!$AE$6:$AE$2005,'LANÇAMENTOS'!$H$6:$H$2005,$B25,'LANÇAMENTOS'!$AF$6:$AF$2005,"Custos Variáveis")) | H25: =IF($B25="","",SUMIFS('LANÇAMENTOS'!$AE$6:$AE$2005,'LANÇAMENTOS'!$H$6:$H$2005,$B25,'LANÇAMENTOS'!$E$6:$E$2005,"Saída")-SUMIFS('LANÇAMENTOS'!$AE$6:$AE$2005,'LANÇAMENTOS'!$H$6:$H$2005,$B25,'LANÇAMENTOS'!$AF$6:$AF$2005,"Custos Variáveis")-SUMIFS('LANÇAMENTOS'!$AE$6:$AE$2005,'LANÇAMENTOS'!$H$6:$H$2005,$B25,'LANÇAMENTOS'!$AF$6:$AF$2005,"Investimentos (CAPEX)")-SUMIFS('LANÇAMENTOS'!$AE$6:$AE$2005,'LANÇAMENTOS'!$H$6:$H$2005,$B25,'LANÇAMENTOS'!$AF$6:$AF$2005,"Financiamentos e Sócios (Principal)")-SUMIFS('LANÇAMENTOS'!$AE$6:$AE$2005,'LANÇAMENTOS'!$H$6:$H$2005,$B25,'LANÇAMENTOS'!$AF$6:$AF$2005,"Distribuição de Lucros")) | I25: =IF($B25="","",$F25-$G25-$H25) | J25: =IF(OR($B25="",$F25=0),"",$I25/$F25)
B26: TOTAL | F26: =SUM(F6:F25) | G26: =SUM(G6:G25) | H26: =SUM(H6:H25) | I26: =SUM(I6:I25) | J26: =IF($F26=0,"",$I26/$F26)

Sheet CONTAS BANCÁRIAS
A1: CONTAS BANCÁRIAS
A2: Cadastre as contas correntes e de investimento. O saldo inicial é o saldo existente no momento em que você começou a usar a planilha; o saldo atual é calculado pelos lançamentos.
B3: ⚠ DADOS DE EXEMPLO — três contas correntes fictícias (Banco do Brasil, Itaú e Nubank). Os cartões de crédito ficam na aba CARTÕES.
A5: Código | B5: Conta (nome de referência) | C5: Banco / instituição | D5: Agência | E5: Conta nº | F5: Tipo de conta | G5: Saldo inicial | H5: Entradas no ano | I5: Saídas no ano | J5: Saldo atual | K5: Limite de crédito | L5: Saldo + limite | M5: Gerente / contato | N5: Status | O5: Observações
A6: BN01 | B6: Banco do Brasil — C/C 12345-6 | C6: Banco do Brasil | D6: 1234-5 | E6: 12345-6 | F6: Conta Corrente | G6: 45000 | H6: =IF($B6="","",SUMIFS('LANÇAMENTOS'!$V$6:$V$2005,'LANÇAMENTOS'!$L$6:$L$2005,$B6,'LANÇAMENTOS'!$E$6:$E$2005,"Entrada",'LANÇAMENTOS'!$D$6:$D$2005,"<="&TODAY())) | I6: =IF($B6="","",SUMIFS('LANÇAMENTOS'!$V$6:$V$2005,'LANÇAMENTOS'!$L$6:$L$2005,$B6,'LANÇAMENTOS'!$E$6:$E$2005,"Saída",'LANÇAMENTOS'!$D$6:$D$2005,"<="&TODAY())) | J6: =IF($B6="","",$G6+$H6-$I6) | K6: 20000 | L6: =IF($B6="","",$J6+$K6) | M6: (11) 3499-1000 | N6: Ativa | O6: Conta principal — recebimentos e folha
A7: BN02 | B7: Itaú Unibanco — C/C 45678-9 | C7: Itaú Unibanco | D7: 0987 | E7: 45678-9 | F7: Conta Corrente | G7: 32000 | H7: =IF($B7="","",SUMIFS('LANÇAMENTOS'!$V$6:$V$2005,'LANÇAMENTOS'!$L$6:$L$2005,$B7,'LANÇAMENTOS'!$E$6:$E$2005,"Entrada",'LANÇAMENTOS'!$D$6:$D$2005,"<="&TODAY())) | I7: =IF($B7="","",SUMIFS('LANÇAMENTOS'!$V$6:$V$2005,'LANÇAMENTOS'!$L$6:$L$2005,$B7,'LANÇAMENTOS'!$E$6:$E$2005,"Saída",'LANÇAMENTOS'!$D$6:$D$2005,"<="&TODAY())) | J7: =IF($B7="","",$G7+$H7-$I7) | K7: 15000 | L7: =IF($B7="","",$J7+$K7) | M7: (11) 3003-4828 | N7: Ativa | O7: Pagamentos, tributos e fornecedores
A8: BN03 | B8: Nubank PJ — C/C 9876543-2 | C8: Nubank | D8: 0001 | E8: 9876543-2 | F8: Conta Corrente | G8: 8500 | H8: =IF($B8="","",SUMIFS('LANÇAMENTOS'!$V$6:$V$2005,'LANÇAMENTOS'!$L$6:$L$2005,$B8,'LANÇAMENTOS'!$E$6:$E$2005,"Entrada",'LANÇAMENTOS'!$D$6:$D$2005,"<="&TODAY())) | I8: =IF($B8="","",SUMIFS('LANÇAMENTOS'!$V$6:$V$2005,'LANÇAMENTOS'!$L$6:$L$2005,$B8,'LANÇAMENTOS'!$E$6:$E$2005,"Saída",'LANÇAMENTOS'!$D$6:$D$2005,"<="&TODAY())) | J8: =IF($B8="","",$G8+$H8-$I8) | K8: 0 | L8: =IF($B8="","",$J8+$K8) | M8: 0800 591 2117 | N8: Ativa | O8: Conta digital — despesas pequenas e PIX
H9: =IF($B9="","",SUMIFS('LANÇAMENTOS'!$V$6:$V$2005,'LANÇAMENTOS'!$L$6:$L$2005,$B9,'LANÇAMENTOS'!$E$6:$E$2005,"Entrada",'LANÇAMENTOS'!$D$6:$D$2005,"<="&TODAY())) | I9: =IF($B9="","",SUMIFS('LANÇAMENTOS'!$V$6:$V$2005,'LANÇAMENTOS'!$L$6:$L$2005,$B9,'LANÇAMENTOS'!$E$6:$E$2005,"Saída",'LANÇAMENTOS'!$D$6:$D$2005,"<="&TODAY())) | J9: =IF($B9="","",$G9+$H9-$I9) | L9: =IF($B9="","",$J9+$K9)
H10: =IF($B10="","",SUMIFS('LANÇAMENTOS'!$V$6:$V$2005,'LANÇAMENTOS'!$L$6:$L$2005,$B10,'LANÇAMENTOS'!$E$6:$E$2005,"Entrada",'LANÇAMENTOS'!$D$6:$D$2005,"<="&TODAY())) | I10: =IF($B10="","",SUMIFS('LANÇAMENTOS'!$V$6:$V$2005,'LANÇAMENTOS'!$L$6:$L$2005,$B10,'LANÇAMENTOS'!$E$6:$E$2005,"Saída",'LANÇAMENTOS'!$D$6:$D$2005,"<="&TODAY())) | J10: =IF($B10="","",$G10+$H10-$I10) | L10: =IF($B10="","",$J10+$K10)
H11: =IF($B11="","",SUMIFS('LANÇAMENTOS'!$V$6:$V$2005,'LANÇAMENTOS'!$L$6:$L$2005,$B11,'LANÇAMENTOS'!$E$6:$E$2005,"Entrada",'LANÇAMENTOS'!$D$6:$D$2005,"<="&TODAY())) | I11: =IF($B11="","",SUMIFS('LANÇAMENTOS'!$V$6:$V$2005,'LANÇAMENTOS'!$L$6:$L$2005,$B11,'LANÇAMENTOS'!$E$6:$E$2005,"Saída",'LANÇAMENTOS'!$D$6:$D$2005,"<="&TODAY())) | J11: =IF($B11="","",$G11+$H11-$I11) | L11: =IF($B11="","",$J11+$K11)
H12: =IF($B12="","",SUMIFS('LANÇAMENTOS'!$V$6:$V$2005,'LANÇAMENTOS'!$L$6:$L$2005,$B12,'LANÇAMENTOS'!$E$6:$E$2005,"Entrada",'LANÇAMENTOS'!$D$6:$D$2005,"<="&TODAY())) | I12: =IF($B12="","",SUMIFS('LANÇAMENTOS'!$V$6:$V$2005,'LANÇAMENTOS'!$L$6:$L$2005,$B12,'LANÇAMENTOS'!$E$6:$E$2005,"Saída",'LANÇAMENTOS'!$D$6:$D$2005,"<="&TODAY())) | J12: =IF($B12="","",$G12+$H12-$I12) | L12: =IF($B12="","",$J12+$K12)
H13: =IF($B13="","",SUMIFS('LANÇAMENTOS'!$V$6:$V$2005,'LANÇAMENTOS'!$L$6:$L$2005,$B13,'LANÇAMENTOS'!$E$6:$E$2005,"Entrada",'LANÇAMENTOS'!$D$6:$D$2005,"<="&TODAY())) | I13: =IF($B13="","",SUMIFS('LANÇAMENTOS'!$V$6:$V$2005,'LANÇAMENTOS'!$L$6:$L$2005,$B13,'LANÇAMENTOS'!$E$6:$E$2005,"Saída",'LANÇAMENTOS'!$D$6:$D$2005,"<="&TODAY())) | J13: =IF($B13="","",$G13+$H13-$I13) | L13: =IF($B13="","",$J13+$K13)
B14: TOTAL DISPONÍVEL (caixa e bancos) | G14: =SUM(G6:G13) | H14: =SUM(H6:H13) | I14: =SUM(I6:I13) | J14: =SUM(J6:J13) | K14: =SUM(K6:K13) | L14: =SUM(L6:L13)
B16: O saldo atual é calculado assim: saldo inicial + entradas realizadas − saídas realizadas (data de pagamento/recebimento preenchida na aba LANÇAMENTOS).

Sheet CARTÕES
A1: CARTÕES DE CRÉDITO
A2: Controle de limites, faturas e comprometimento. As compras devem ser lançadas na aba LANÇAMENTOS com a forma de pagamento 'Cartão de crédito' e o cartão escolhido na coluna Cartão.
B3: ⚠ DADOS DE EXEMPLO — três cartões de crédito fictícios.
A5: Código | B5: Cartão (nome de referência) | C5: Bandeira | D5: Banco emissor | E5: Final | F5: Limite total | G5: Dia de fechamento | H5: Dia de vencimento | I5: Conta de pagamento | J5: Compras no mês (competência) | K5: Fatura paga no mês | L5: Fatura em aberto | M5: Limite disponível | N5: % do limite usado | O5: Status | P5: Observações
A6: CT01 | B6: Cartão Visa Itaú Business | C6: Visa | D6: Itaú Unibanco | E6: 4417 | F6: 25000 | G6: 25 | H6: 5 | I6: Itaú Unibanco — C/C 45678-9 | J6: =IF($B6="","",SUMIFS('LANÇAMENTOS'!$Q$6:$Q$2005,'LANÇAMENTOS'!$N$6:$N$2005,$B6,'LANÇAMENTOS'!$Z$6:$Z$2005,'CONFIGURAÇÕES'!$B$19,'LANÇAMENTOS'!$AA$6:$AA$2005,'CONFIGURAÇÕES'!$B$18)) | K6: =IF($B6="","",SUMIFS('LANÇAMENTOS'!$V$6:$V$2005,'LANÇAMENTOS'!$N$6:$N$2005,$B6,'LANÇAMENTOS'!$Z$6:$Z$2005,'CONFIGURAÇÕES'!$B$19,'LANÇAMENTOS'!$AA$6:$AA$2005,'CONFIGURAÇÕES'!$B$18)) | L6: =IF($B6="","",SUMIFS('LANÇAMENTOS'!$W$6:$W$2005,'LANÇAMENTOS'!$N$6:$N$2005,$B6)) | M6: =IF($B6="","",$F6-$L6) | N6: =IF(OR($B6="",$F6=0),"",$L6/$F6) | O6: Ativo | P6: Compras de fornecedores e viagens comerciais
A7: CT02 | B7: Cartão Mastercard Nubank PJ | C7: Mastercard | D7: Nubank | E7: 8823 | F7: 10000 | G7: 20 | H7: 28 | I7: Nubank PJ — C/C 9876543-2 | J7: =IF($B7="","",SUMIFS('LANÇAMENTOS'!$Q$6:$Q$2005,'LANÇAMENTOS'!$N$6:$N$2005,$B7,'LANÇAMENTOS'!$Z$6:$Z$2005,'CONFIGURAÇÕES'!$B$19,'LANÇAMENTOS'!$AA$6:$AA$2005,'CONFIGURAÇÕES'!$B$18)) | K7: =IF($B7="","",SUMIFS('LANÇAMENTOS'!$V$6:$V$2005,'LANÇAMENTOS'!$N$6:$N$2005,$B7,'LANÇAMENTOS'!$Z$6:$Z$2005,'CONFIGURAÇÕES'!$B$19,'LANÇAMENTOS'!$AA$6:$AA$2005,'CONFIGURAÇÕES'!$B$18)) | L7: =IF($B7="","",SUMIFS('LANÇAMENTOS'!$W$6:$W$2005,'LANÇAMENTOS'!$N$6:$N$2005,$B7)) | M7: =IF($B7="","",$F7-$L7) | N7: =IF(OR($B7="",$F7=0),"",$L7/$F7) | O7: Ativo | P7: Assinaturas de software, marketing e serviços digitais
A8: CT03 | B8: Cartão Elo Banco do Brasil PJ | C8: Elo | D8: Banco do Brasil | E8: 7751 | F8: 15000 | G8: 15 | H8: 25 | I8: Banco do Brasil — C/C 12345-6 | J8: =IF($B8="","",SUMIFS('LANÇAMENTOS'!$Q$6:$Q$2005,'LANÇAMENTOS'!$N$6:$N$2005,$B8,'LANÇAMENTOS'!$Z$6:$Z$2005,'CONFIGURAÇÕES'!$B$19,'LANÇAMENTOS'!$AA$6:$AA$2005,'CONFIGURAÇÕES'!$B$18)) | K8: =IF($B8="","",SUMIFS('LANÇAMENTOS'!$V$6:$V$2005,'LANÇAMENTOS'!$N$6:$N$2005,$B8,'LANÇAMENTOS'!$Z$6:$Z$2005,'CONFIGURAÇÕES'!$B$19,'LANÇAMENTOS'!$AA$6:$AA$2005,'CONFIGURAÇÕES'!$B$18)) | L8: =IF($B8="","",SUMIFS('LANÇAMENTOS'!$W$6:$W$2005,'LANÇAMENTOS'!$N$6:$N$2005,$B8)) | M8: =IF($B8="","",$F8-$L8) | N8: =IF(OR($B8="",$F8=0),"",$L8/$F8) | O8: Ativo | P8: Combustível e manutenção da frota
J9: =IF($B9="","",SUMIFS('LANÇAMENTOS'!$Q$6:$Q$2005,'LANÇAMENTOS'!$N$6:$N$2005,$B9,'LANÇAMENTOS'!$Z$6:$Z$2005,'CONFIGURAÇÕES'!$B$19,'LANÇAMENTOS'!$AA$6:$AA$2005,'CONFIGURAÇÕES'!$B$18)) | K9: =IF($B9="","",SUMIFS('LANÇAMENTOS'!$V$6:$V$2005,'LANÇAMENTOS'!$N$6:$N$2005,$B9,'LANÇAMENTOS'!$Z$6:$Z$2005,'CONFIGURAÇÕES'!$B$19,'LANÇAMENTOS'!$AA$6:$AA$2005,'CONFIGURAÇÕES'!$B$18)) | L9: =IF($B9="","",SUMIFS('LANÇAMENTOS'!$W$6:$W$2005,'LANÇAMENTOS'!$N$6:$N$2005,$B9)) | M9: =IF($B9="","",$F9-$L9) | N9: =IF(OR($B9="",$F9=0),"",$L9/$F9)
J10: =IF($B10="","",SUMIFS('LANÇAMENTOS'!$Q$6:$Q$2005,'LANÇAMENTOS'!$N$6:$N$2005,$B10,'LANÇAMENTOS'!$Z$6:$Z$2005,'CONFIGURAÇÕES'!$B$19,'LANÇAMENTOS'!$AA$6:$AA$2005,'CONFIGURAÇÕES'!$B$18)) | K10: =IF($B10="","",SUMIFS('LANÇAMENTOS'!$V$6:$V$2005,'LANÇAMENTOS'!$N$6:$N$2005,$B10,'LANÇAMENTOS'!$Z$6:$Z$2005,'CONFIGURAÇÕES'!$B$19,'LANÇAMENTOS'!$AA$6:$AA$2005,'CONFIGURAÇÕES'!$B$18)) | L10: =IF($B10="","",SUMIFS('LANÇAMENTOS'!$W$6:$W$2005,'LANÇAMENTOS'!$N$6:$N$2005,$B10)) | M10: =IF($B10="","",$F10-$L10) | N10: =IF(OR($B10="",$F10=0),"",$L10/$F10)
J11: =IF($B11="","",SUMIFS('LANÇAMENTOS'!$Q$6:$Q$2005,'LANÇAMENTOS'!$N$6:$N$2005,$B11,'LANÇAMENTOS'!$Z$6:$Z$2005,'CONFIGURAÇÕES'!$B$19,'LANÇAMENTOS'!$AA$6:$AA$2005,'CONFIGURAÇÕES'!$B$18)) | K11: =IF($B11="","",SUMIFS('LANÇAMENTOS'!$V$6:$V$2005,'LANÇAMENTOS'!$N$6:$N$2005,$B11,'LANÇAMENTOS'!$Z$6:$Z$2005,'CONFIGURAÇÕES'!$B$19,'LANÇAMENTOS'!$AA$6:$AA$2005,'CONFIGURAÇÕES'!$B$18)) | L11: =IF($B11="","",SUMIFS('LANÇAMENTOS'!$W$6:$W$2005,'LANÇAMENTOS'!$N$6:$N$2005,$B11)) | M11: =IF($B11="","",$F11-$L11) | N11: =IF(OR($B11="",$F11=0),"",$L11/$F11)
J12: =IF($B12="","",SUMIFS('LANÇAMENTOS'!$Q$6:$Q$2005,'LANÇAMENTOS'!$N$6:$N$2005,$B12,'LANÇAMENTOS'!$Z$6:$Z$2005,'CONFIGURAÇÕES'!$B$19,'LANÇAMENTOS'!$AA$6:$AA$2005,'CONFIGURAÇÕES'!$B$18)) | K12: =IF($B12="","",SUMIFS('LANÇAMENTOS'!$V$6:$V$2005,'LANÇAMENTOS'!$N$6:$N$2005,$B12,'LANÇAMENTOS'!$Z$6:$Z$2005,'CONFIGURAÇÕES'!$B$19,'LANÇAMENTOS'!$AA$6:$AA$2005,'CONFIGURAÇÕES'!$B$18)) | L12: =IF($B12="","",SUMIFS('LANÇAMENTOS'!$W$6:$W$2005,'LANÇAMENTOS'!$N$6:$N$2005,$B12)) | M12: =IF($B12="","",$F12-$L12) | N12: =IF(OR($B12="",$F12=0),"",$L12/$F12)
J13: =IF($B13="","",SUMIFS('LANÇAMENTOS'!$Q$6:$Q$2005,'LANÇAMENTOS'!$N$6:$N$2005,$B13,'LANÇAMENTOS'!$Z$6:$Z$2005,'CONFIGURAÇÕES'!$B$19,'LANÇAMENTOS'!$AA$6:$AA$2005,'CONFIGURAÇÕES'!$B$18)) | K13: =IF($B13="","",SUMIFS('LANÇAMENTOS'!$V$6:$V$2005,'LANÇAMENTOS'!$N$6:$N$2005,$B13,'LANÇAMENTOS'!$Z$6:$Z$2005,'CONFIGURAÇÕES'!$B$19,'LANÇAMENTOS'!$AA$6:$AA$2005,'CONFIGURAÇÕES'!$B$18)) | L13: =IF($B13="","",SUMIFS('LANÇAMENTOS'!$W$6:$W$2005,'LANÇAMENTOS'!$N$6:$N$2005,$B13)) | M13: =IF($B13="","",$F13-$L13) | N13: =IF(OR($B13="",$F13=0),"",$L13/$F13)
J14: =IF($B14="","",SUMIFS('LANÇAMENTOS'!$Q$6:$Q$2005,'LANÇAMENTOS'!$N$6:$N$2005,$B14,'LANÇAMENTOS'!$Z$6:$Z$2005,'CONFIGURAÇÕES'!$B$19,'LANÇAMENTOS'!$AA$6:$AA$2005,'CONFIGURAÇÕES'!$B$18)) | K14: =IF($B14="","",SUMIFS('LANÇAMENTOS'!$V$6:$V$2005,'LANÇAMENTOS'!$N$6:$N$2005,$B14,'LANÇAMENTOS'!$Z$6:$Z$2005,'CONFIGURAÇÕES'!$B$19,'LANÇAMENTOS'!$AA$6:$AA$2005,'CONFIGURAÇÕES'!$B$18)) | L14: =IF($B14="","",SUMIFS('LANÇAMENTOS'!$W$6:$W$2005,'LANÇAMENTOS'!$N$6:$N$2005,$B14)) | M14: =IF($B14="","",$F14-$L14) | N14: =IF(OR($B14="",$F14=0),"",$L14/$F14)
J15: =IF($B15="","",SUMIFS('LANÇAMENTOS'!$Q$6:$Q$2005,'LANÇAMENTOS'!$N$6:$N$2005,$B15,'LANÇAMENTOS'!$Z$6:$Z$2005,'CONFIGURAÇÕES'!$B$19,'LANÇAMENTOS'!$AA$6:$AA$2005,'CONFIGURAÇÕES'!$B$18)) | K15: =IF($B15="","",SUMIFS('LANÇAMENTOS'!$V$6:$V$2005,'LANÇAMENTOS'!$N$6:$N$2005,$B15,'LANÇAMENTOS'!$Z$6:$Z$2005,'CONFIGURAÇÕES'!$B$19,'LANÇAMENTOS'!$AA$6:$AA$2005,'CONFIGURAÇÕES'!$B$18)) | L15: =IF($B15="","",SUMIFS('LANÇAMENTOS'!$W$6:$W$2005,'LANÇAMENTOS'!$N$6:$N$2005,$B15)) | M15: =IF($B15="","",$F15-$L15) | N15: =IF(OR($B15="",$F15=0),"",$L15/$F15)
B16: TOTAL | F16: =SUM(F6:F15) | J16: =SUM(J6:J15) | K16: =SUM(K6:K15) | L16: =SUM(L6:L15) | M16: =SUM(M6:M15) | N16: =IF($F16=0,"",$L16/$F16)
A19: FATURAS POR MÊS — compras em cada cartão (ano de análise)
A20: Cartão | B20: Mês 1 | C20: Mês 2 | D20: Mês 3 | E20: Mês 4 | F20: Mês 5 | G20: Mês 6 | H20: Mês 7 | I20: Mês 8 | J20: Mês 9 | K20: Mês 10 | L20: Mês 11 | M20: Mês 12 | N20: Total
A21: =$B$6 | B21: =IF($A21="","",SUMIFS('LANÇAMENTOS'!$Q$6:$Q$2005,'LANÇAMENTOS'!$N$6:$N$2005,$A21,'LANÇAMENTOS'!$Z$6:$Z$2005,1,'LANÇAMENTOS'!$AA$6:$AA$2005,'CONFIGURAÇÕES'!$B$18)) | C21: =IF($A21="","",SUMIFS('LANÇAMENTOS'!$Q$6:$Q$2005,'LANÇAMENTOS'!$N$6:$N$2005,$A21,'LANÇAMENTOS'!$Z$6:$Z$2005,2,'LANÇAMENTOS'!$AA$6:$AA$2005,'CONFIGURAÇÕES'!$B$18)) | D21: =IF($A21="","",SUMIFS('LANÇAMENTOS'!$Q$6:$Q$2005,'LANÇAMENTOS'!$N$6:$N$2005,$A21,'LANÇAMENTOS'!$Z$6:$Z$2005,3,'LANÇAMENTOS'!$AA$6:$AA$2005,'CONFIGURAÇÕES'!$B$18)) | E21: =IF($A21="","",SUMIFS('LANÇAMENTOS'!$Q$6:$Q$2005,'LANÇAMENTOS'!$N$6:$N$2005,$A21,'LANÇAMENTOS'!$Z$6:$Z$2005,4,'LANÇAMENTOS'!$AA$6:$AA$2005,'CONFIGURAÇÕES'!$B$18)) | F21: =IF($A21="","",SUMIFS('LANÇAMENTOS'!$Q$6:$Q$2005,'LANÇAMENTOS'!$N$6:$N$2005,$A21,'LANÇAMENTOS'!$Z$6:$Z$2005,5,'LANÇAMENTOS'!$AA$6:$AA$2005,'CONFIGURAÇÕES'!$B$18)) | G21: =IF($A21="","",SUMIFS('LANÇAMENTOS'!$Q$6:$Q$2005,'LANÇAMENTOS'!$N$6:$N$2005,$A21,'LANÇAMENTOS'!$Z$6:$Z$2005,6,'LANÇAMENTOS'!$AA$6:$AA$2005,'CONFIGURAÇÕES'!$B$18)) | H21: =IF($A21="","",SUMIFS('LANÇAMENTOS'!$Q$6:$Q$2005,'LANÇAMENTOS'!$N$6:$N$2005,$A21,'LANÇAMENTOS'!$Z$6:$Z$2005,7,'LANÇAMENTOS'!$AA$6:$AA$2005,'CONFIGURAÇÕES'!$B$18)) | I21: =IF($A21="","",SUMIFS('LANÇAMENTOS'!$Q$6:$Q$2005,'LANÇAMENTOS'!$N$6:$N$2005,$A21,'LANÇAMENTOS'!$Z$6:$Z$2005,8,'LANÇAMENTOS'!$AA$6:$AA$2005,'CONFIGURAÇÕES'!$B$18)) | J21: =IF($A21="","",SUMIFS('LANÇAMENTOS'!$Q$6:$Q$2005,'LANÇAMENTOS'!$N$6:$N$2005,$A21,'LANÇAMENTOS'!$Z$6:$Z$2005,9,'LANÇAMENTOS'!$AA$6:$AA$2005,'CONFIGURAÇÕES'!$B$18)) | K21: =IF($A21="","",SUMIFS('LANÇAMENTOS'!$Q$6:$Q$2005,'LANÇAMENTOS'!$N$6:$N$2005,$A21,'LANÇAMENTOS'!$Z$6:$Z$2005,10,'LANÇAMENTOS'!$AA$6:$AA$2005,'CONFIGURAÇÕES'!$B$18)) | L21: =IF($A21="","",SUMIFS('LANÇAMENTOS'!$Q$6:$Q$2005,'LANÇAMENTOS'!$N$6:$N$2005,$A21,'LANÇAMENTOS'!$Z$6:$Z$2005,11,'LANÇAMENTOS'!$AA$6:$AA$2005,'CONFIGURAÇÕES'!$B$18)) | M21: =IF($A21="","",SUMIFS('LANÇAMENTOS'!$Q$6:$Q$2005,'LANÇAMENTOS'!$N$6:$N$2005,$A21,'LANÇAMENTOS'!$Z$6:$Z$2005,12,'LANÇAMENTOS'!$AA$6:$AA$2005,'CONFIGURAÇÕES'!$B$18)) | N21: =IF($A21="","",SUM(B21:M21))
A22: =$B$7 | B22: =IF($A22="","",SUMIFS('LANÇAMENTOS'!$Q$6:$Q$2005,'LANÇAMENTOS'!$N$6:$N$2005,$A22,'LANÇAMENTOS'!$Z$6:$Z$2005,1,'LANÇAMENTOS'!$AA$6:$AA$2005,'CONFIGURAÇÕES'!$B$18)) | C22: =IF($A22="","",SUMIFS('LANÇAMENTOS'!$Q$6:$Q$2005,'LANÇAMENTOS'!$N$6:$N$2005,$A22,'LANÇAMENTOS'!$Z$6:$Z$2005,2,'LANÇAMENTOS'!$AA$6:$AA$2005,'CONFIGURAÇÕES'!$B$18)) | D22: =IF($A22="","",SUMIFS('LANÇAMENTOS'!$Q$6:$Q$2005,'LANÇAMENTOS'!$N$6:$N$2005,$A22,'LANÇAMENTOS'!$Z$6:$Z$2005,3,'LANÇAMENTOS'!$AA$6:$AA$2005,'CONFIGURAÇÕES'!$B$18)) | E22: =IF($A22="","",SUMIFS('LANÇAMENTOS'!$Q$6:$Q$2005,'LANÇAMENTOS'!$N$6:$N$2005,$A22,'LANÇAMENTOS'!$Z$6:$Z$2005,4,'LANÇAMENTOS'!$AA$6:$AA$2005,'CONFIGURAÇÕES'!$B$18)) | F22: =IF($A22="","",SUMIFS('LANÇAMENTOS'!$Q$6:$Q$2005,'LANÇAMENTOS'!$N$6:$N$2005,$A22,'LANÇAMENTOS'!$Z$6:$Z$2005,5,'LANÇAMENTOS'!$AA$6:$AA$2005,'CONFIGURAÇÕES'!$B$18)) | G22: =IF($A22="","",SUMIFS('LANÇAMENTOS'!$Q$6:$Q$2005,'LANÇAMENTOS'!$N$6:$N$2005,$A22,'LANÇAMENTOS'!$Z$6:$Z$2005,6,'LANÇAMENTOS'!$AA$6:$AA$2005,'CONFIGURAÇÕES'!$B$18)) | H22: =IF($A22="","",SUMIFS('LANÇAMENTOS'!$Q$6:$Q$2005,'LANÇAMENTOS'!$N$6:$N$2005,$A22,'LANÇAMENTOS'!$Z$6:$Z$2005,7,'LANÇAMENTOS'!$AA$6:$AA$2005,'CONFIGURAÇÕES'!$B$18)) | I22: =IF($A22="","",SUMIFS('LANÇAMENTOS'!$Q$6:$Q$2005,'LANÇAMENTOS'!$N$6:$N$2005,$A22,'LANÇAMENTOS'!$Z$6:$Z$2005,8,'LANÇAMENTOS'!$AA$6:$AA$2005,'CONFIGURAÇÕES'!$B$18)) | J22: =IF($A22="","",SUMIFS('LANÇAMENTOS'!$Q$6:$Q$2005,'LANÇAMENTOS'!$N$6:$N$2005,$A22,'LANÇAMENTOS'!$Z$6:$Z$2005,9,'LANÇAMENTOS'!$AA$6:$AA$2005,'CONFIGURAÇÕES'!$B$18)) | K22: =IF($A22="","",SUMIFS('LANÇAMENTOS'!$Q$6:$Q$2005,'LANÇAMENTOS'!$N$6:$N$2005,$A22,'LANÇAMENTOS'!$Z$6:$Z$2005,10,'LANÇAMENTOS'!$AA$6:$AA$2005,'CONFIGURAÇÕES'!$B$18)) | L22: =IF($A22="","",SUMIFS('LANÇAMENTOS'!$Q$6:$Q$2005,'LANÇAMENTOS'!$N$6:$N$2005,$A22,'LANÇAMENTOS'!$Z$6:$Z$2005,11,'LANÇAMENTOS'!$AA$6:$AA$2005,'CONFIGURAÇÕES'!$B$18)) | M22: =IF($A22="","",SUMIFS('LANÇAMENTOS'!$Q$6:$Q$2005,'LANÇAMENTOS'!$N$6:$N$2005,$A22,'LANÇAMENTOS'!$Z$6:$Z$2005,12,'LANÇAMENTOS'!$AA$6:$AA$2005,'CONFIGURAÇÕES'!$B$18)) | N22: =IF($A22="","",SUM(B22:M22))
A23: =$B$8 | B23: =IF($A23="","",SUMIFS('LANÇAMENTOS'!$Q$6:$Q$2005,'LANÇAMENTOS'!$N$6:$N$2005,$A23,'LANÇAMENTOS'!$Z$6:$Z$2005,1,'LANÇAMENTOS'!$AA$6:$AA$2005,'CONFIGURAÇÕES'!$B$18)) | C23: =IF($A23="","",SUMIFS('LANÇAMENTOS'!$Q$6:$Q$2005,'LANÇAMENTOS'!$N$6:$N$2005,$A23,'LANÇAMENTOS'!$Z$6:$Z$2005,2,'LANÇAMENTOS'!$AA$6:$AA$2005,'CONFIGURAÇÕES'!$B$18)) | D23: =IF($A23="","",SUMIFS('LANÇAMENTOS'!$Q$6:$Q$2005,'LANÇAMENTOS'!$N$6:$N$2005,$A23,'LANÇAMENTOS'!$Z$6:$Z$2005,3,'LANÇAMENTOS'!$AA$6:$AA$2005,'CONFIGURAÇÕES'!$B$18)) | E23: =IF($A23="","",SUMIFS('LANÇAMENTOS'!$Q$6:$Q$2005,'LANÇAMENTOS'!$N$6:$N$2005,$A23,'LANÇAMENTOS'!$Z$6:$Z$2005,4,'LANÇAMENTOS'!$AA$6:$AA$2005,'CONFIGURAÇÕES'!$B$18)) | F23: =IF($A23="","",SUMIFS('LANÇAMENTOS'!$Q$6:$Q$2005,'LANÇAMENTOS'!$N$6:$N$2005,$A23,'LANÇAMENTOS'!$Z$6:$Z$2005,5,'LANÇAMENTOS'!$AA$6:$AA$2005,'CONFIGURAÇÕES'!$B$18)) | G23: =IF($A23="","",SUMIFS('LANÇAMENTOS'!$Q$6:$Q$2005,'LANÇAMENTOS'!$N$6:$N$2005,$A23,'LANÇAMENTOS'!$Z$6:$Z$2005,6,'LANÇAMENTOS'!$AA$6:$AA$2005,'CONFIGURAÇÕES'!$B$18)) | H23: =IF($A23="","",SUMIFS('LANÇAMENTOS'!$Q$6:$Q$2005,'LANÇAMENTOS'!$N$6:$N$2005,$A23,'LANÇAMENTOS'!$Z$6:$Z$2005,7,'LANÇAMENTOS'!$AA$6:$AA$2005,'CONFIGURAÇÕES'!$B$18)) | I23: =IF($A23="","",SUMIFS('LANÇAMENTOS'!$Q$6:$Q$2005,'LANÇAMENTOS'!$N$6:$N$2005,$A23,'LANÇAMENTOS'!$Z$6:$Z$2005,8,'LANÇAMENTOS'!$AA$6:$AA$2005,'CONFIGURAÇÕES'!$B$18)) | J23: =IF($A23="","",SUMIFS('LANÇAMENTOS'!$Q$6:$Q$2005,'LANÇAMENTOS'!$N$6:$N$2005,$A23,'LANÇAMENTOS'!$Z$6:$Z$2005,9,'LANÇAMENTOS'!$AA$6:$AA$2005,'CONFIGURAÇÕES'!$B$18)) | K23: =IF($A23="","",SUMIFS('LANÇAMENTOS'!$Q$6:$Q$2005,'LANÇAMENTOS'!$N$6:$N$2005,$A23,'LANÇAMENTOS'!$Z$6:$Z$2005,10,'LANÇAMENTOS'!$AA$6:$AA$2005,'CONFIGURAÇÕES'!$B$18)) | L23: =IF($A23="","",SUMIFS('LANÇAMENTOS'!$Q$6:$Q$2005,'LANÇAMENTOS'!$N$6:$N$2005,$A23,'LANÇAMENTOS'!$Z$6:$Z$2005,11,'LANÇAMENTOS'!$AA$6:$AA$2005,'CONFIGURAÇÕES'!$B$18)) | M23: =IF($A23="","",SUMIFS('LANÇAMENTOS'!$Q$6:$Q$2005,'LANÇAMENTOS'!$N$6:$N$2005,$A23,'LANÇAMENTOS'!$Z$6:$Z$2005,12,'LANÇAMENTOS'!$AA$6:$AA$2005,'CONFIGURAÇÕES'!$B$18)) | N23: =IF($A23="","",SUM(B23:M23))

Sheet LANÇAMENTOS
A1: LANÇAMENTOS — BASE CENTRAL DE ENTRADAS E SAÍDAS
A2: Cada linha é um lançamento. Colunas amarelas = você digita • Colunas cinzas = cálculo automático (não editar). Contas a pagar e a receber saem desta base.
A3: COMO USAR: 1) informe as datas e escolha tipo, categoria, subcategoria, centro de custo e cliente/fornecedor nas listas; 2) preencha o valor previsto; 3) ao pagar/receber, informe a data e o valor realizado e mude o status para Pago/Recebido. O sistema classifica vencimentos, atrasos, DRE e fluxo de caixa.
A4: ⚠ DADOS DE EXEMPLO: as linhas já preenchidas são fictícias (demonstração). Para começar do zero, selecione as linhas de dados nas colunas A a X e pressione Delete — as fórmulas das colunas Y a AO permanecem e continuam funcionando.
A5: ID | B5: Data de competência | C5: Data de vencimento | D5: Data de pagamento/recebimento | E5: Tipo | F5: Categoria | G5: Subcategoria | H5: Centro de custo | I5: Cliente / Fornecedor | J5: Descrição | K5: Documento | L5: Banco / Conta | M5: Forma de pagamento | N5: Cartão | O5: Nº parcela | P5: Total parcelas | Q5: Valor previsto | R5: Valor realizado | S5: Juros | T5: Multa | U5: Desconto | V5: Valor final (caixa) | W5: Saldo em aberto | X5: Status | Y5: Situação automática | Z5: Mês | AA5: Ano | AB5: Semana | AC5: Dia da semana | AD5: Competência | AE5: Valor DRE | AF5: Linha do DRE | AG5: Tipo de fluxo | AH5: Grupo | AI5: Dias p/ vencimento | AJ5: Dias em atraso | AK5: Dias até pagamento | AL5: Valor × dias | AM5: Chave AP (ordem) | AN5: Chave AR (ordem) | AO5: Validação automática
A6: L0001 | B6: 46026 | C6: 46056 | D6: 46056 | E6: Saída | F6: Custos Variáveis | G6: Mercadorias para Revenda | H6: Logística | I6: DISTRIBUIDORA CENTRAL DE ALIMENTOS S/A | J6: Compra de mercadorias para revenda — NF 5010 | K6: NF 5010 | L6: Itaú Unibanco — C/C 45678-9 | M6: Boleto | O6: 1 | P6: 1 | Q6: 59572.8 | R6: 59572.8 | V6: =IF(COUNTA($B6:$R6)=0,"",ROUND(N($R6)+N($S6)+N($T6)-N($U6),2)) | W6: =IF(COUNTA($B6:$R6)=0,"",IF(OR($X6="Pago",$X6="Recebido",$X6="Cancelado"),0,ROUND(N($Q6)+N($S6)+N($T6)-N($U6)-N($R6),2))) | X6: Pago | Y6: =IF(COUNTA($B6:$R6)=0,"",IF($X6="Cancelado","Cancelado",IF(OR($X6="Pago",$X6="Recebido"),$X6,IF(OR($X6="Parcial",N($R6)>0),"Parcial",IF($C6="","Sem vencimento",IF($C6<TODAY(),"Vencido",IF($C6=TODAY(),"Vence hoje",IF($C6<=TODAY()+7,"Vence em 7 dias",IF($C6<=TODAY()+30,"Vence em 30 dias","Futuro"))))))))) | Z6: =IF($B6="","",MONTH($B6)) | AA6: =IF($B6="","",YEAR($B6)) | AB6: =IF($B6="","",ISOWEEKNUM($B6)) | AC6: =IF($B6="","",CHOOSE(WEEKDAY($B6,2),"Segunda","Terça","Quarta","Quinta","Sexta","Sábado","Domingo")) | AD6: =IF($B6="","",TEXT($B6,"MM/AAAA")) | AE6: =IF(COUNTA($B6:$R6)=0,"",IF($X6="Cancelado",0,ROUND(N($Q6)+N($S6)+N($T6)-N($U6),2))) | AF6: =IF($G6="","",IFERROR(INDEX(LINHAS_DRE_PLANO,MATCH($G6,SUBCATEGORIAS_PLANO,0)),"Não classificado")) | AG6: =IF($G6="","",IFERROR(INDEX(TIPOS_FLUXO_PLANO,MATCH($G6,SUBCATEGORIAS_PLANO,0)),"Não classificado")) | AH6: =IF($G6="","",IFERROR(INDEX(GRUPOS_PLANO,MATCH($G6,SUBCATEGORIAS_PLANO,0)),"Não classificado")) | AI6: =IF(OR($C6="",$X6="Pago",$X6="Recebido",$X6="Cancelado"),"",$C6-TODAY()) | AJ6: =IF(OR($C6="",$X6="Pago",$X6="Recebido",$X6="Cancelado"),0,MAX(0,TODAY()-$C6)) | AK6: =IF($D6="","",$D6-$B6) | AL6: =IF(OR($D6="",$B6=""),"",ROUND(N($R6)*($D6-$B6),2)) | AM6: =IF(AND($E6="Saída",$W6>0,$C6<>""),$C6+ROW()/1000000,"") | AN6: =IF(AND($E6="Entrada",$W6>0,$C6<>""),$C6+ROW()/1000000,"") | AO6: =IF(COUNTA($B6:$R6)=0,"",IF(AND($I6<>"",COUNTIF(CLIENTES_NOMES,$I6)+COUNTIF(CLIENTES_FANTASIA,$I6)+COUNTIF(FORNECEDORES_NOMES,$I6)+COUNTIF(FORNECEDORES_FANTASIA,$I6)=0),"⚠ Cliente/Fornecedor não cadastrado",IF(AND($G6<>"",COUNTIF(SUBCATEGORIAS_PLANO,$G6)=0),"⚠ Subcategoria fora do plano de contas",IF(OR($Q6="",N($Q6)=0),"⚠ Valor previsto não informado",IF(AND(OR($X6="Pago",$X6="Recebido"),$D6=""),"⚠ Status pago/recebido sem data",IF(AND($D6<>"",N($R6)=0),"⚠ Data de pagamento sem valor realizado",IF(AND(N($P6)>1,N($O6)>N($P6)),"⚠ Nº da parcela maior que o total",IF(AND($C6<>"",$B6<>"",$C6<$B6),"⚠ Vencimento anterior à competência","OK"))))))))
A7: L0002 | B7: 46027 | C7: 46032 | D7: 46033 | E7: Saída | F7: Despesas Administrativas | G7: Aluguel | H7: Administrativo | I7: IMÓVEIS E LOCAÇÕES PINHEIROS LTDA | J7: Aluguel do galpão — competência 01/2026 | K7: DOC 8265 | L7: Banco do Brasil — C/C 12345-6 | M7: Boleto | O7: 1 | P7: 1 | Q7: 7500 | R7: 7500 | V7: =IF(COUNTA($B7:$R7)=0,"",ROUND(N($R7)+N($S7)+N($T7)-N($U7),2)) | W7: =IF(COUNTA($B7:$R7)=0,"",IF(OR($X7="Pago",$X7="Recebido",$X7="Cancelado"),0,ROUND(N($Q7)+N($S7)+N($T7)-N($U7)-N($R7),2))) | X7: Pago | Y7: =IF(COUNTA($B7:$R7)=0,"",IF($X7="Cancelado","Cancelado",IF(OR($X7="Pago",$X7="Recebido"),$X7,IF(OR($X7="Parcial",N($R7)>0),"Parcial",IF($C7="","Sem vencimento",IF($C7<TODAY(),"Vencido",IF($C7=TODAY(),"Vence hoje",IF($C7<=TODAY()+7,"Vence em 7 dias",IF($C7<=TODAY()+30,"Vence em 30 dias","Futuro"))))))))) | Z7: =IF($B7="","",MONTH($B7)) | AA7: =IF($B7="","",YEAR($B7)) | AB7: =IF($B7="","",ISOWEEKNUM($B7)) | AC7: =IF($B7="","",CHOOSE(WEEKDAY($B7,2),"Segunda","Terça","Quarta","Quinta","Sexta","Sábado","Domingo")) | AD7: =IF($B7="","",TEXT($B7,"MM/AAAA")) | AE7: =IF(COUNTA($B7:$R7)=0,"",IF($X7="Cancelado",0,ROUND(N($Q7)+N($S7)+N($T7)-N($U7),2))) | AF7: =IF($G7="","",IFERROR(INDEX(LINHAS_DRE_PLANO,MATCH($G7,SUBCATEGORIAS_PLANO,0)),"Não classificado")) | AG7: =IF($G7="","",IFERROR(INDEX(TIPOS_FLUXO_PLANO,MATCH($G7,SUBCATEGORIAS_PLANO,0)),"Não classificado")) | AH7: =IF($G7="","",IFERROR(INDEX(GRUPOS_PLANO,MATCH($G7,SUBCATEGORIAS_PLANO,0)),"Não classificado")) | AI7: =IF(OR($C7="",$X7="Pago",$X7="Recebido",$X7="Cancelado"),"",$C7-TODAY()) | AJ7: =IF(OR($C7="",$X7="Pago",$X7="Recebido",$X7="Cancelado"),0,MAX(0,TODAY()-$C7)) | AK7: =IF($D7="","",$D7-$B7) | AL7: =IF(OR($D7="",$B7=""),"",ROUND(N($R7)*($D7-$B7),2)) | AM7: =IF(AND($E7="Saída",$W7>0,$C7<>""),$C7+ROW()/1000000,"") | AN7: =IF(AND($E7="Entrada",$W7>0,$C7<>""),$C7+ROW()/1000000,"") | AO7: =IF(COUNTA($B7:$R7)=0,"",IF(AND($I7<>"",COUNTIF(CLIENTES_NOMES,$I7)+COUNTIF(CLIENTES_FANTASIA,$I7)+COUNTIF(FORNECEDORES_NOMES,$I7)+COUNTIF(FORNECEDORES_FANTASIA,$I7)=0),"⚠ Cliente/Fornecedor não cadastrado",IF(AND($G7<>"",COUNTIF(SUBCATEGORIAS_PLANO,$G7)=0),"⚠ Subcategoria fora do plano de contas",IF(OR($Q7="",N($Q7)=0),"⚠ Valor previsto não informado",IF(AND(OR($X7="Pago",$X7="Recebido"),$D7=""),"⚠ Status pago/recebido sem data",IF(AND($D7<>"",N($R7)=0),"⚠ Data de pagamento sem valor realizado",IF(AND(N($P7)>1,N($O7)>N($P7)),"⚠ Nº da parcela maior que o total",IF(AND($C7<>"",$B7<>"",$C7<$B7),"⚠ Vencimento anterior à competência","OK"))))))))
A8: L0003 | B8: 46027 | C8: 46032 | D8: 46032 | E8: Saída | F8: Despesas com Pessoal | G8: Salários | H8: Administrativo | I8: COLABORADORES — FOLHA DE PAGAMENTO | J8: Folha de pagamento — 01/2026 | K8: DOC 8271 | L8: Banco do Brasil — C/C 12345-6 | M8: Transferência | O8: 1 | P8: 1 | Q8: 16000 | R8: 16000 | V8: =IF(COUNTA($B8:$R8)=0,"",ROUND(N($R8)+N($S8)+N($T8)-N($U8),2)) | W8: =IF(COUNTA($B8:$R8)=0,"",IF(OR($X8="Pago",$X8="Recebido",$X8="Cancelado"),0,ROUND(N($Q8)+N($S8)+N($T8)-N($U8)-N($R8),2))) | X8: Pago | Y8: =IF(COUNTA($B8:$R8)=0,"",IF($X8="Cancelado","Cancelado",IF(OR($X8="Pago",$X8="Recebido"),$X8,IF(OR($X8="Parcial",N($R8)>0),"Parcial",IF($C8="","Sem vencimento",IF($C8<TODAY(),"Vencido",IF($C8=TODAY(),"Vence hoje",IF($C8<=TODAY()+7,"Vence em 7 dias",IF($C8<=TODAY()+30,"Vence em 30 dias","Futuro"))))))))) | Z8: =IF($B8="","",MONTH($B8)) | AA8: =IF($B8="","",YEAR($B8)) | AB8: =IF($B8="","",ISOWEEKNUM($B8)) | AC8: =IF($B8="","",CHOOSE(WEEKDAY($B8,2),"Segunda","Terça","Quarta","Quinta","Sexta","Sábado","Domingo")) | AD8: =IF($B8="","",TEXT($B8,"MM/AAAA")) | AE8: =IF(COUNTA($B8:$R8)=0,"",IF($X8="Cancelado",0,ROUND(N($Q8)+N($S8)+N($T8)-N($U8),2))) | AF8: =IF($G8="","",IFERROR(INDEX(LINHAS_DRE_PLANO,MATCH($G8,SUBCATEGORIAS_PLANO,0)),"Não classificado")) | AG8: =IF($G8="","",IFERROR(INDEX(TIPOS_FLUXO_PLANO,MATCH($G8,SUBCATEGORIAS_PLANO,0)),"Não classificado")) | AH8: =IF($G8="","",IFERROR(INDEX(GRUPOS_PLANO,MATCH($G8,SUBCATEGORIAS_PLANO,0)),"Não classificado")) | AI8: =IF(OR($C8="",$X8="Pago",$X8="Recebido",$X8="Cancelado"),"",$C8-TODAY()) | AJ8: =IF(OR($C8="",$X8="Pago",$X8="Recebido",$X8="Cancelado"),0,MAX(0,TODAY()-$C8)) | AK8: =IF($D8="","",$D8-$B8) | AL8: =IF(OR($D8="",$B8=""),"",ROUND(N($R8)*($D8-$B8),2)) | AM8: =IF(AND($E8="Saída",$W8>0,$C8<>""),$C8+ROW()/1000000,"") | AN8: =IF(AND($E8="Entrada",$W8>0,$C8<>""),$C8+ROW()/1000000,"") | AO8: =IF(COUNTA($B8:$R8)=0,"",IF(AND($I8<>"",COUNTIF(CLIENTES_NOMES,$I8)+COUNTIF(CLIENTES_FANTASIA,$I8)+COUNTIF(FORNECEDORES_NOMES,$I8)+COUNTIF(FORNECEDORES_FANTASIA,$I8)=0),"⚠ Cliente/Fornecedor não cadastrado",IF(AND($G8<>"",COUNTIF(SUBCATEGORIAS_PLANO,$G8)=0),"⚠ Subcategoria fora do plano de contas",IF(OR($Q8="",N($Q8)=0),"⚠ Valor previsto não informado",IF(AND(OR($X8="Pago",$X8="Recebido"),$D8=""),"⚠ Status pago/recebido sem data",IF(AND($D8<>"",N($R8)=0),"⚠ Data de pagamento sem valor realizado",IF(AND(N($P8)>1,N($O8)>N($P8)),"⚠ Nº da parcela maior que o total",IF(AND($C8<>"",$B8<>"",$C8<$B8),"⚠ Vencimento anterior à competência","OK"))))))))
A9: L0004 | B9: 46027 | C9: 46032 | D9: 46035 | E9: Saída | F9: Despesas com Pessoal | G9: Benefícios (VT/VA/Plano de Saúde) | H9: Administrativo | I9: BENEFÍCIOS BRASIL ADMINISTRADORA LTDA | J9: Vale-transporte, alimentação e saúde | K9: DOC 8273 | L9: Banco do Brasil — C/C 12345-6 | M9: Transferência | O9: 1 | P9: 1 | Q9: 1900 | R9: 1900 | V9: =IF(COUNTA($B9:$R9)=0,"",ROUND(N($R9)+N($S9)+N($T9)-N($U9),2)) | W9: =IF(COUNTA($B9:$R9)=0,"",IF(OR($X9="Pago",$X9="Recebido",$X9="Cancelado"),0,ROUND(N($Q9)+N($S9)+N($T9)-N($U9)-N($R9),2))) | X9: Pago | Y9: =IF(COUNTA($B9:$R9)=0,"",IF($X9="Cancelado","Cancelado",IF(OR($X9="Pago",$X9="Recebido"),$X9,IF(OR($X9="Parcial",N($R9)>0),"Parcial",IF($C9="","Sem vencimento",IF($C9<TODAY(),"Vencido",IF($C9=TODAY(),"Vence hoje",IF($C9<=TODAY()+7,"Vence em 7 dias",IF($C9<=TODAY()+30,"Vence em 30 dias","Futuro"))))))))) | Z9: =IF($B9="","",MONTH($B9)) | AA9: =IF($B9="","",YEAR($B9)) | AB9: =IF($B9="","",ISOWEEKNUM($B9)) | AC9: =IF($B9="","",CHOOSE(WEEKDAY($B9,2),"Segunda","Terça","Quarta","Quinta","Sexta","Sábado","Domingo")) | AD9: =IF($B9="","",TEXT($B9,"MM/AAAA")) | AE9: =IF(COUNTA($B9:$R9)=0,"",IF($X9="Cancelado",0,ROUND(N($Q9)+N($S9)+N($T9)-N($U9),2))) | AF9: =IF($G9="","",IFERROR(INDEX(LINHAS_DRE_PLANO,MATCH($G9,SUBCATEGORIAS_PLANO,0)),"Não classificado")) | AG9: =IF($G9="","",IFERROR(INDEX(TIPOS_FLUXO_PLANO,MATCH($G9,SUBCATEGORIAS_PLANO,0)),"Não classificado")) | AH9: =IF($G9="","",IFERROR(INDEX(GRUPOS_PLANO,MATCH($G9,SUBCATEGORIAS_PLANO,0)),"Não classificado")) | AI9: =IF(OR($C9="",$X9="Pago",$X9="Recebido",$X9="Cancelado"),"",$C9-TODAY()) | AJ9: =IF(OR($C9="",$X9="Pago",$X9="Recebido",$X9="Cancelado"),0,MAX(0,TODAY()-$C9)) | AK9: =IF($D9="","",$D9-$B9) | AL9: =IF(OR($D9="",$B9=""),"",ROUND(N($R9)*($D9-$B9),2)) | AM9: =IF(AND($E9="Saída",$W9>0,$C9<>""),$C9+ROW()/1000000,"") | AN9: =IF(AND($E9="Entrada",$W9>0,$C9<>""),$C9+ROW()/1000000,"") | AO9: =IF(COUNTA($B9:$R9)=0,"",IF(AND($I9<>"",COUNTIF(CLIENTES_NOMES,$I9)+COUNTIF(CLIENTES_FANTASIA,$I9)+COUNTIF(FORNECEDORES_NOMES,$I9)+COUNTIF(FORNECEDORES_FANTASIA,$I9)=0),"⚠ Cliente/Fornecedor não cadastrado",IF(AND($G9<>"",COUNTIF(SUBCATEGORIAS_PLANO,$G9)=0),"⚠ Subcategoria fora do plano de contas",IF(OR($Q9="",N($Q9)=0),"⚠ Valor previsto não informado",IF(AND(OR($X9="Pago",$X9="Recebido"),$D9=""),"⚠ Status pago/recebido sem data",IF(AND($D9<>"",N($R9)=0),"⚠ Data de pagamento sem valor realizado",IF(AND(N($P9)>1,N($O9)>N($P9)),"⚠ Nº da parcela maior que o total",IF(AND($C9<>"",$B9<>"",$C9<$B9),"⚠ Vencimento anterior à competência","OK"))))))))
A10: L0005 | B10: 46027 | C10: 46032 | D10: 46035 | E10: Saída | F10: Despesas com Pessoal | G10: Pró-labore | H10: Diretoria | I10: SÓCIOS — PRÓ-LABORE E DISTRIBUIÇÕES | J10: Pró-labore dos sócios — 01/2026 | K10: DOC 8274 | L10: Banco do Brasil — C/C 12345-6 | M10: Transferência | O10: 1 | P10: 1 | Q10: 9500 | R10: 9500 | V10: =IF(COUNTA($B10:$R10)=0,"",ROUND(N($R10)+N($S10)+N($T10)-N($U10),2)) | W10: =IF(COUNTA($B10:$R10)=0,"",IF(OR($X10="Pago",$X10="Recebido",$X10="Cancelado"),0,ROUND(N($Q10)+N($S10)+N($T10)-N($U10)-N($R10),2))) | X10: Pago | Y10: =IF(COUNTA($B10:$R10)=0,"",IF($X10="Cancelado","Cancelado",IF(OR($X10="Pago",$X10="Recebido"),$X10,IF(OR($X10="Parcial",N($R10)>0),"Parcial",IF($C10="","Sem vencimento",IF($C10<TODAY(),"Vencido",IF($C10=TODAY(),"Vence hoje",IF($C10<=TODAY()+7,"Vence em 7 dias",IF($C10<=TODAY()+30,"Vence em 30 dias","Futuro"))))))))) | Z10: =IF($B10="","",MONTH($B10)) | AA10: =IF($B10="","",YEAR($B10)) | AB10: =IF($B10="","",ISOWEEKNUM($B10)) | AC10: =IF($B10="","",CHOOSE(WEEKDAY($B10,2),"Segunda","Terça","Quarta","Quinta","Sexta","Sábado","Domingo")) | AD10: =IF($B10="","",TEXT($B10,"MM/AAAA")) | AE10: =IF(COUNTA($B10:$R10)=0,"",IF($X10="Cancelado",0,ROUND(N($Q10)+N($S10)+N($T10)-N($U10),2))) | AF10: =IF($G10="","",IFERROR(INDEX(LINHAS_DRE_PLANO,MATCH($G10,SUBCATEGORIAS_PLANO,0)),"Não classificado")) | AG10: =IF($G10="","",IFERROR(INDEX(TIPOS_FLUXO_PLANO,MATCH($G10,SUBCATEGORIAS_PLANO,0)),"Não classificado")) | AH10: =IF($G10="","",IFERROR(INDEX(GRUPOS_PLANO,MATCH($G10,SUBCATEGORIAS_PLANO,0)),"Não classificado")) | AI10: =IF(OR($C10="",$X10="Pago",$X10="Recebido",$X10="Cancelado"),"",$C10-TODAY()) | AJ10: =IF(OR($C10="",$X10="Pago",$X10="Recebido",$X10="Cancelado"),0,MAX(0,TODAY()-$C10)) | AK10: =IF($D10="","",$D10-$B10) | AL10: =IF(OR($D10="",$B10=""),"",ROUND(N($R10)*($D10-$B10),2)) | AM10: =IF(AND($E10="Saída",$W10>0,$C10<>""),$C10+ROW()/1000000,"") | AN10: =IF(AND($E10="Entrada",$W10>0,$C10<>""),$C10+ROW()/1000000,"") | AO10: =IF(COUNTA($B10:$R10)=0,"",IF(AND($I10<>"",COUNTIF(CLIENTES_NOMES,$I10)+COUNTIF(CLIENTES_FANTASIA,$I10)+COUNTIF(FORNECEDORES_NOMES,$I10)+COUNTIF(FORNECEDORES_FANTASIA,$I10)=0),"⚠ Cliente/Fornecedor não cadastrado",IF(AND($G10<>"",COUNTIF(SUBCATEGORIAS_PLANO,$G10)=0),"⚠ Subcategoria fora do plano de contas",IF(OR($Q10="",N($Q10)=0),"⚠ Valor previsto não informado",IF(AND(OR($X10="Pago",$X10="Recebido"),$D10=""),"⚠ Status pago/recebido sem data",IF(AND($D10<>"",N($R10)=0),"⚠ Data de pagamento sem valor realizado",IF(AND(N($P10)>1,N($O10)>N($P10)),"⚠ Nº da parcela maior que o total",IF(AND($C10<>"",$B10<>"",$C10<$B10),"⚠ Vencimento anterior à competência","OK"))))))))
A11: L0006 | B11: 46029 | C11: 46036 | D11: 46036 | E11: Saída | F11: Despesas com Pessoal | G11: Encargos Sociais (FGTS/INSS) | H11: Administrativo | I11: RECEITA FEDERAL DO BRASIL | J11: FGTS e INSS — competência 01/2026 | K11: DOC 8272 | L11: Itaú Unibanco — C/C 45678-9 | M11: Transferência | O11: 1 | P11: 1 | Q11: 5600 | R11: 5600 | V11: =IF(COUNTA($B11:$R11)=0,"",ROUND(N($R11)+N($S11)+N($T11)-N($U11),2)) | W11: =IF(COUNTA($B11:$R11)=0,"",IF(OR($X11="Pago",$X11="Recebido",$X11="Cancelado"),0,ROUND(N($Q11)+N($S11)+N($T11)-N($U11)-N($R11),2))) | X11: Pago | Y11: =IF(COUNTA($B11:$R11)=0,"",IF($X11="Cancelado","Cancelado",IF(OR($X11="Pago",$X11="Recebido"),$X11,IF(OR($X11="Parcial",N($R11)>0),"Parcial",IF($C11="","Sem vencimento",IF($C11<TODAY(),"Vencido",IF($C11=TODAY(),"Vence hoje",IF($C11<=TODAY()+7,"Vence em 7 dias",IF($C11<=TODAY()+30,"Vence em 30 dias","Futuro"))))))))) | Z11: =IF($B11="","",MONTH($B11)) | AA11: =IF($B11="","",YEAR($B11)) | AB11: =IF($B11="","",ISOWEEKNUM($B11)) | AC11: =IF($B11="","",CHOOSE(WEEKDAY($B11,2),"Segunda","Terça","Quarta","Quinta","Sexta","Sábado","Domingo")) | AD11: =IF($B11="","",TEXT($B11,"MM/AAAA")) | AE11: =IF(COUNTA($B11:$R11)=0,"",IF($X11="Cancelado",0,ROUND(N($Q11)+N($S11)+N($T11)-N($U11),2))) | AF11: =IF($G11="","",IFERROR(INDEX(LINHAS_DRE_PLANO,MATCH($G11,SUBCATEGORIAS_PLANO,0)),"Não classificado")) | AG11: =IF($G11="","",IFERROR(INDEX(TIPOS_FLUXO_PLANO,MATCH($G11,SUBCATEGORIAS_PLANO,0)),"Não classificado")) | AH11: =IF($G11="","",IFERROR(INDEX(GRUPOS_PLANO,MATCH($G11,SUBCATEGORIAS_PLANO,0)),"Não classificado")) | AI11: =IF(OR($C11="",$X11="Pago",$X11="Recebido",$X11="Cancelado"),"",$C11-TODAY()) | AJ11: =IF(OR($C11="",$X11="Pago",$X11="Recebido",$X11="Cancelado"),0,MAX(0,TODAY()-$C11)) | AK11: =IF($D11="","",$D11-$B11) | AL11: =IF(OR($D11="",$B11=""),"",ROUND(N($R11)*($D11-$B11),2)) | AM11: =IF(AND($E11="Saída",$W11>0,$C11<>""),$C11+ROW()/1000000,"") | AN11: =IF(AND($E11="Entrada",$W11>0,$C11<>""),$C11+ROW()/1000000,"") | AO11: =IF(COUNTA($B11:$R11)=0,"",IF(AND($I11<>"",COUNTIF(CLIENTES_NOMES,$I11)+COUNTIF(CLIENTES_FANTASIA,$I11)+COUNTIF(FORNECEDORES_NOMES,$I11)+COUNTIF(FORNECEDORES_FANTASIA,$I11)=0),"⚠ Cliente/Fornecedor não cadastrado",IF(AND($G11<>"",COUNTIF(SUBCATEGORIAS_PLANO,$G11)=0),"⚠ Subcategoria fora do plano de contas",IF(OR($Q11="",N($Q11)=0),"⚠ Valor previsto não informado",IF(AND(OR($X11="Pago",$X11="Recebido"),$D11=""),"⚠ Status pago/recebido sem data",IF(AND($D11<>"",N($R11)=0),"⚠ Data de pagamento sem valor realizado",IF(AND(N($P11)>1,N($O11)>N($P11)),"⚠ Nº da parcela maior que o total",IF(AND($C11<>"",$B11<>"",$C11<$B11),"⚠ Vencimento anterior à competência","OK"))))))))
A12: L0007 | B12: 46030 | C12: 46050 | D12: 46052 | E12: Saída | F12: Despesas Administrativas | G12: Sistemas e Softwares | H12: Administrativo | I12: TECNOLOGIA E SISTEMAS ABC LTDA | J12: Assinatura ERP, NF-e e BI | K12: DOC 8270 | L12: Nubank PJ — C/C 9876543-2 | M12: Cartão de crédito | N12: Cartão Mastercard Nubank PJ | O12: 1 | P12: 1 | Q12: 850 | R12: 850 | V12: =IF(COUNTA($B12:$R12)=0,"",ROUND(N($R12)+N($S12)+N($T12)-N($U12),2)) | W12: =IF(COUNTA($B12:$R12)=0,"",IF(OR($X12="Pago",$X12="Recebido",$X12="Cancelado"),0,ROUND(N($Q12)+N($S12)+N($T12)-N($U12)-N($R12),2))) | X12: Pago | Y12: =IF(COUNTA($B12:$R12)=0,"",IF($X12="Cancelado","Cancelado",IF(OR($X12="Pago",$X12="Recebido"),$X12,IF(OR($X12="Parcial",N($R12)>0),"Parcial",IF($C12="","Sem vencimento",IF($C12<TODAY(),"Vencido",IF($C12=TODAY(),"Vence hoje",IF($C12<=TODAY()+7,"Vence em 7 dias",IF($C12<=TODAY()+30,"Vence em 30 dias","Futuro"))))))))) | Z12: =IF($B12="","",MONTH($B12)) | AA12: =IF($B12="","",YEAR($B12)) | AB12: =IF($B12="","",ISOWEEKNUM($B12)) | AC12: =IF($B12="","",CHOOSE(WEEKDAY($B12,2),"Segunda","Terça","Quarta","Quinta","Sexta","Sábado","Domingo")) | AD12: =IF($B12="","",TEXT($B12,"MM/AAAA")) | AE12: =IF(COUNTA($B12:$R12)=0,"",IF($X12="Cancelado",0,ROUND(N($Q12)+N($S12)+N($T12)-N($U12),2))) | AF12: =IF($G12="","",IFERROR(INDEX(LINHAS_DRE_PLANO,MATCH($G12,SUBCATEGORIAS_PLANO,0)),"Não classificado")) | AG12: =IF($G12="","",IFERROR(INDEX(TIPOS_FLUXO_PLANO,MATCH($G12,SUBCATEGORIAS_PLANO,0)),"Não classificado")) | AH12: =IF($G12="","",IFERROR(INDEX(GRUPOS_PLANO,MATCH($G12,SUBCATEGORIAS_PLANO,0)),"Não classificado")) | AI12: =IF(OR($C12="",$X12="Pago",$X12="Recebido",$X12="Cancelado"),"",$C12-TODAY()) | AJ12: =IF(OR($C12="",$X12="Pago",$X12="Recebido",$X12="Cancelado"),0,MAX(0,TODAY()-$C12)) | AK12: =IF($D12="","",$D12-$B12) | AL12: =IF(OR($D12="",$B12=""),"",ROUND(N($R12)*($D12-$B12),2)) | AM12: =IF(AND($E12="Saída",$W12>0,$C12<>""),$C12+ROW()/1000000,"") | AN12: =IF(AND($E12="Entrada",$W12>0,$C12<>""),$C12+ROW()/1000000,"") | AO12: =IF(COUNTA($B12:$R12)=0,"",IF(AND($I12<>"",COUNTIF(CLIENTES_NOMES,$I12)+COUNTIF(CLIENTES_FANTASIA,$I12)+COUNTIF(FORNECEDORES_NOMES,$I12)+COUNTIF(FORNECEDORES_FANTASIA,$I12)=0),"⚠ Cliente/Fornecedor não cadastrado",IF(AND($G12<>"",COUNTIF(SUBCATEGORIAS_PLANO,$G12)=0),"⚠ Subcategoria fora do plano de contas",IF(OR($Q12="",N($Q12)=0),"⚠ Valor previsto não informado",IF(AND(OR($X12="Pago",$X12="Recebido"),$D12=""),"⚠ Status pago/recebido sem data",IF(AND($D12<>"",N($R12)=0),"⚠ Data de pagamento sem valor realizado",IF(AND(N($P12)>1,N($O12)>N($P12)),"⚠ Nº da parcela maior que o total",IF(AND($C12<>"",$B12<>"",$C12<$B12),"⚠ Vencimento anterior à competência","OK"))))))))
A13: L0008 | B13: 46031 | C13: 46046 | D13: 46049 | E13: Saída | F13: Custos Variáveis | G13: Matéria-prima | H13: Produção | I13: DISTRIBUIDORA CENTRAL DE ALIMENTOS S/A | J13: Insumos e matéria-prima para beneficiamento | K13: NF 5901 | L13: Itaú Unibanco — C/C 45678-9 | M13: Boleto | O13: 1 | P13: 1 | Q13: 9419.6 | R13: 9419.6 | V13: =IF(COUNTA($B13:$R13)=0,"",ROUND(N($R13)+N($S13)+N($T13)-N($U13),2)) | W13: =IF(COUNTA($B13:$R13)=0,"",IF(OR($X13="Pago",$X13="Recebido",$X13="Cancelado"),0,ROUND(N($Q13)+N($S13)+N($T13)-N($U13)-N($R13),2))) | X13: Pago | Y13: =IF(COUNTA($B13:$R13)=0,"",IF($X13="Cancelado","Cancelado",IF(OR($X13="Pago",$X13="Recebido"),$X13,IF(OR($X13="Parcial",N($R13)>0),"Parcial",IF($C13="","Sem vencimento",IF($C13<TODAY(),"Vencido",IF($C13=TODAY(),"Vence hoje",IF($C13<=TODAY()+7,"Vence em 7 dias",IF($C13<=TODAY()+30,"Vence em 30 dias","Futuro"))))))))) | Z13: =IF($B13="","",MONTH($B13)) | AA13: =IF($B13="","",YEAR($B13)) | AB13: =IF($B13="","",ISOWEEKNUM($B13)) | AC13: =IF($B13="","",CHOOSE(WEEKDAY($B13,2),"Segunda","Terça","Quarta","Quinta","Sexta","Sábado","Domingo")) | AD13: =IF($B13="","",TEXT($B13,"MM/AAAA")) | AE13: =IF(COUNTA($B13:$R13)=0,"",IF($X13="Cancelado",0,ROUND(N($Q13)+N($S13)+N($T13)-N($U13),2))) | AF13: =IF($G13="","",IFERROR(INDEX(LINHAS_DRE_PLANO,MATCH($G13,SUBCATEGORIAS_PLANO,0)),"Não classificado")) | AG13: =IF($G13="","",IFERROR(INDEX(TIPOS_FLUXO_PLANO,MATCH($G13,SUBCATEGORIAS_PLANO,0)),"Não classificado")) | AH13: =IF($G13="","",IFERROR(INDEX(GRUPOS_PLANO,MATCH($G13,SUBCATEGORIAS_PLANO,0)),"Não classificado")) | AI13: =IF(OR($C13="",$X13="Pago",$X13="Recebido",$X13="Cancelado"),"",$C13-TODAY()) | AJ13: =IF(OR($C13="",$X13="Pago",$X13="Recebido",$X13="Cancelado"),0,MAX(0,TODAY()-$C13)) | AK13: =IF($D13="","",$D13-$B13) | AL13: =IF(OR($D13="",$B13=""),"",ROUND(N($R13)*($D13-$B13),2)) | AM13: =IF(AND($E13="Saída",$W13>0,$C13<>""),$C13+ROW()/1000000,"") | AN13: =IF(AND($E13="Entrada",$W13>0,$C13<>""),$C13+ROW()/1000000,"") | AO13: =IF(COUNTA($B13:$R13)=0,"",IF(AND($I13<>"",COUNTIF(CLIENTES_NOMES,$I13)+COUNTIF(CLIENTES_FANTASIA,$I13)+COUNTIF(FORNECEDORES_NOMES,$I13)+COUNTIF(FORNECEDORES_FANTASIA,$I13)=0),"⚠ Cliente/Fornecedor não cadastrado",IF(AND($G13<>"",COUNTIF(SUBCATEGORIAS_PLANO,$G13)=0),"⚠ Subcategoria fora do plano de contas",IF(OR($Q13="",N($Q13)=0),"⚠ Valor previsto não informado",IF(AND(OR($X13="Pago",$X13="Recebido"),$D13=""),"⚠ Status pago/recebido sem data",IF(AND($D13<>"",N($R13)=0),"⚠ Data de pagamento sem valor realizado",IF(AND(N($P13)>1,N($O13)>N($P13)),"⚠ Nº da parcela maior que o total",IF(AND($C13<>"",$B13<>"",$C13<$B13),"⚠ Vencimento anterior à competência","OK"))))))))
A14: L0009 | B14: 46032 | C14: 46050 | D14: 46051 | E14: Saída | F14: Despesas Administrativas | G14: Internet e Telefonia | H14: Administrativo | I14: TELEFÔNICA BRASIL S.A. (VIVO EMPRESAS) | J14: Internet, telefonia e link dedicado | K14: DOC 8268 | L14: Nubank PJ — C/C 9876543-2 | M14: Cartão de crédito | N14: Cartão Mastercard Nubank PJ | O14: 1 | P14: 1 | Q14: 780 | R14: 780 | V14: =IF(COUNTA($B14:$R14)=0,"",ROUND(N($R14)+N($S14)+N($T14)-N($U14),2)) | W14: =IF(COUNTA($B14:$R14)=0,"",IF(OR($X14="Pago",$X14="Recebido",$X14="Cancelado"),0,ROUND(N($Q14)+N($S14)+N($T14)-N($U14)-N($R14),2))) | X14: Pago | Y14: =IF(COUNTA($B14:$R14)=0,"",IF($X14="Cancelado","Cancelado",IF(OR($X14="Pago",$X14="Recebido"),$X14,IF(OR($X14="Parcial",N($R14)>0),"Parcial",IF($C14="","Sem vencimento",IF($C14<TODAY(),"Vencido",IF($C14=TODAY(),"Vence hoje",IF($C14<=TODAY()+7,"Vence em 7 dias",IF($C14<=TODAY()+30,"Vence em 30 dias","Futuro"))))))))) | Z14: =IF($B14="","",MONTH($B14)) | AA14: =IF($B14="","",YEAR($B14)) | AB14: =IF($B14="","",ISOWEEKNUM($B14)) | AC14: =IF($B14="","",CHOOSE(WEEKDAY($B14,2),"Segunda","Terça","Quarta","Quinta","Sexta","Sábado","Domingo")) | AD14: =IF($B14="","",TEXT($B14,"MM/AAAA")) | AE14: =IF(COUNTA($B14:$R14)=0,"",IF($X14="Cancelado",0,ROUND(N($Q14)+N($S14)+N($T14)-N($U14),2))) | AF14: =IF($G14="","",IFERROR(INDEX(LINHAS_DRE_PLANO,MATCH($G14,SUBCATEGORIAS_PLANO,0)),"Não classificado")) | AG14: =IF($G14="","",IFERROR(INDEX(TIPOS_FLUXO_PLANO,MATCH($G14,SUBCATEGORIAS_PLANO,0)),"Não classificado")) | AH14: =IF($G14="","",IFERROR(INDEX(GRUPOS_PLANO,MATCH($G14,SUBCATEGORIAS_PLANO,0)),"Não classificado")) | AI14: =IF(OR($C14="",$X14="Pago",$X14="Recebido",$X14="Cancelado"),"",$C14-TODAY()) | AJ14: =IF(OR($C14="",$X14="Pago",$X14="Recebido",$X14="Cancelado"),0,MAX(0,TODAY()-$C14)) | AK14: =IF($D14="","",$D14-$B14) | AL14: =IF(OR($D14="",$B14=""),"",ROUND(N($R14)*($D14-$B14),2)) | AM14: =IF(AND($E14="Saída",$W14>0,$C14<>""),$C14+ROW()/1000000,"") | AN14: =IF(AND($E14="Entrada",$W14>0,$C14<>""),$C14+ROW()/1000000,"") | AO14: =IF(COUNTA($B14:$R14)=0,"",IF(AND($I14<>"",COUNTIF(CLIENTES_NOMES,$I14)+COUNTIF(CLIENTES_FANTASIA,$I14)+COUNTIF(FORNECEDORES_NOMES,$I14)+COUNTIF(FORNECEDORES_FANTASIA,$I14)=0),"⚠ Cliente/Fornecedor não cadastrado",IF(AND($G14<>"",COUNTIF(SUBCATEGORIAS_PLANO,$G14)=0),"⚠ Subcategoria fora do plano de contas",IF(OR($Q14="",N($Q14)=0),"⚠ Valor previsto não informado",IF(AND(OR($X14="Pago",$X14="Recebido"),$D14=""),"⚠ Status pago/recebido sem data",IF(AND($D14<>"",N($R14)=0),"⚠ Data de pagamento sem valor realizado",IF(AND(N($P14)>1,N($O14)>N($P14)),"⚠ Nº da parcela maior que o total",IF(AND($C14<>"",$B14<>"",$C14<$B14),"⚠ Vencimento anterior à competência","OK"))))))))
A15: L0010 | B15: 46032 | C15: 46032 | D15: 46035 | E15: Saída | F15: Despesas Administrativas | G15: Contabilidade | H15: Financeiro | I15: CONTABILIDADE AURORA ASSESSORIA CONTÁBIL LTDA | J15: Honorários contábeis — competência 01/2026 | K15: DOC 8269 | L15: Itaú Unibanco — C/C 45678-9 | M15: PIX | O15: 1 | P15: 1 | Q15: 1250 | R15: 1250 | V15: =IF(COUNTA($B15:$R15)=0,"",ROUND(N($R15)+N($S15)+N($T15)-N($U15),2)) | W15: =IF(COUNTA($B15:$R15)=0,"",IF(OR($X15="Pago",$X15="Recebido",$X15="Cancelado"),0,ROUND(N($Q15)+N($S15)+N($T15)-N($U15)-N($R15),2))) | X15: Pago | Y15: =IF(COUNTA($B15:$R15)=0,"",IF($X15="Cancelado","Cancelado",IF(OR($X15="Pago",$X15="Recebido"),$X15,IF(OR($X15="Parcial",N($R15)>0),"Parcial",IF($C15="","Sem vencimento",IF($C15<TODAY(),"Vencido",IF($C15=TODAY(),"Vence hoje",IF($C15<=TODAY()+7,"Vence em 7 dias",IF($C15<=TODAY()+30,"Vence em 30 dias","Futuro"))))))))) | Z15: =IF($B15="","",MONTH($B15)) | AA15: =IF($B15="","",YEAR($B15)) | AB15: =IF($B15="","",ISOWEEKNUM($B15)) | AC15: =IF($B15="","",CHOOSE(WEEKDAY($B15,2),"Segunda","Terça","Quarta","Quinta","Sexta","Sábado","Domingo")) | AD15: =IF($B15="","",TEXT($B15,"MM/AAAA")) | AE15: =IF(COUNTA($B15:$R15)=0,"",IF($X15="Cancelado",0,ROUND(N($Q15)+N($S15)+N($T15)-N($U15),2))) | AF15: =IF($G15="","",IFERROR(INDEX(LINHAS_DRE_PLANO,MATCH($G15,SUBCATEGORIAS_PLANO,0)),"Não classificado")) | AG15: =IF($G15="","",IFERROR(INDEX(TIPOS_FLUXO_PLANO,MATCH($G15,SUBCATEGORIAS_PLANO,0)),"Não classificado")) | AH15: =IF($G15="","",IFERROR(INDEX(GRUPOS_PLANO,MATCH($G15,SUBCATEGORIAS_PLANO,0)),"Não classificado")) | AI15: =IF(OR($C15="",$X15="Pago",$X15="Recebido",$X15="Cancelado"),"",$C15-TODAY()) | AJ15: =IF(OR($C15="",$X15="Pago",$X15="Recebido",$X15="Cancelado"),0,MAX(0,TODAY()-$C15)) | AK15: =IF($D15="","",$D15-$B15) | AL15: =IF(OR($D15="",$B15=""),"",ROUND(N($R15)*($D15-$B15),2)) | AM15: =IF(AND($E15="Saída",$W15>0,$C15<>""),$C15+ROW()/1000000,"") | AN15: =IF(AND($E15="Entrada",$W15>0,$C15<>""),$C15+ROW()/1000000,"") | AO15: =IF(COUNTA($B15:$R15)=0,"",IF(AND($I15<>"",COUNTIF(CLIENTES_NOMES,$I15)+COUNTIF(CLIENTES_FANTASIA,$I15)+COUNTIF(FORNECEDORES_NOMES,$I15)+COUNTIF(FORNECEDORES_FANTASIA,$I15)=0),"⚠ Cliente/Fornecedor não cadastrado",IF(AND($G15<>"",COUNTIF(SUBCATEGORIAS_PLANO,$G15)=0),"⚠ Subcategoria fora do plano de contas",IF(OR($Q15="",N($Q15)=0),"⚠ Valor previsto não informado",IF(AND(OR($X15="Pago",$X15="Recebido"),$D15=""),"⚠ Status pago/recebido sem data",IF(AND($D15<>"",N($R15)=0),"⚠ Data de pagamento sem valor realizado",IF(AND(N($P15)>1,N($O15)>N($P15)),"⚠ Nº da parcela maior que o total",IF(AND($C15<>"",$B15<>"",$C15<$B15),"⚠ Vencimento anterior à competência","OK"))))))))
A16: L0011 | B16: 46032 | C16: 46050 | D16: 46052 | E16: Saída | F16: Despesas Comerciais | G16: Marketing Digital | H16: Marketing | I16: AGÊNCIA PULSO DIGITAL LTDA | J16: Gestão de tráfego pago e produção de conteúdo | K16: DOC 8275 | L16: Nubank PJ — C/C 9876543-2 | M16: Cartão de crédito | N16: Cartão Mastercard Nubank PJ | O16: 1 | P16: 1 | Q16: 4166.43 | R16: 4166.43 | V16: =IF(COUNTA($B16:$R16)=0,"",ROUND(N($R16)+N($S16)+N($T16)-N($U16),2)) | W16: =IF(COUNTA($B16:$R16)=0,"",IF(OR($X16="Pago",$X16="Recebido",$X16="Cancelado"),0,ROUND(N($Q16)+N($S16)+N($T16)-N($U16)-N($R16),2))) | X16: Pago | Y16: =IF(COUNTA($B16:$R16)=0,"",IF($X16="Cancelado","Cancelado",IF(OR($X16="Pago",$X16="Recebido"),$X16,IF(OR($X16="Parcial",N($R16)>0),"Parcial",IF($C16="","Sem vencimento",IF($C16<TODAY(),"Vencido",IF($C16=TODAY(),"Vence hoje",IF($C16<=TODAY()+7,"Vence em 7 dias",IF($C16<=TODAY()+30,"Vence em 30 dias","Futuro"))))))))) | Z16: =IF($B16="","",MONTH($B16)) | AA16: =IF($B16="","",YEAR($B16)) | AB16: =IF($B16="","",ISOWEEKNUM($B16)) | AC16: =IF($B16="","",CHOOSE(WEEKDAY($B16,2),"Segunda","Terça","Quarta","Quinta","Sexta","Sábado","Domingo")) | AD16: =IF($B16="","",TEXT($B16,"MM/AAAA")) | AE16: =IF(COUNTA($B16:$R16)=0,"",IF($X16="Cancelado",0,ROUND(N($Q16)+N($S16)+N($T16)-N($U16),2))) | AF16: =IF($G16="","",IFERROR(INDEX(LINHAS_DRE_PLANO,MATCH($G16,SUBCATEGORIAS_PLANO,0)),"Não classificado")) | AG16: =IF($G16="","",IFERROR(INDEX(TIPOS_FLUXO_PLANO,MATCH($G16,SUBCATEGORIAS_PLANO,0)),"Não classificado")) | AH16: =IF($G16="","",IFERROR(INDEX(GRUPOS_PLANO,MATCH($G16,SUBCATEGORIAS_PLANO,0)),"Não classificado")) | AI16: =IF(OR($C16="",$X16="Pago",$X16="Recebido",$X16="Cancelado"),"",$C16-TODAY()) | AJ16: =IF(OR($C16="",$X16="Pago",$X16="Recebido",$X16="Cancelado"),0,MAX(0,TODAY()-$C16)) | AK16: =IF($D16="","",$D16-$B16) | AL16: =IF(OR($D16="",$B16=""),"",ROUND(N($R16)*($D16-$B16),2)) | AM16: =IF(AND($E16="Saída",$W16>0,$C16<>""),$C16+ROW()/1000000,"") | AN16: =IF(AND($E16="Entrada",$W16>0,$C16<>""),$C16+ROW()/1000000,"") | AO16: =IF(COUNTA($B16:$R16)=0,"",IF(AND($I16<>"",COUNTIF(CLIENTES_NOMES,$I16)+COUNTIF(CLIENTES_FANTASIA,$I16)+COUNTIF(FORNECEDORES_NOMES,$I16)+COUNTIF(FORNECEDORES_FANTASIA,$I16)=0),"⚠ Cliente/Fornecedor não cadastrado",IF(AND($G16<>"",COUNTIF(SUBCATEGORIAS_PLANO,$G16)=0),"⚠ Subcategoria fora do plano de contas",IF(OR($Q16="",N($Q16)=0),"⚠ Valor previsto não informado",IF(AND(OR($X16="Pago",$X16="Recebido"),$D16=""),"⚠ Status pago/recebido sem data",IF(AND($D16<>"",N($R16)=0),"⚠ Data de pagamento sem valor realizado",IF(AND(N($P16)>1,N($O16)>N($P16)),"⚠ Nº da parcela maior que o total",IF(AND($C16<>"",$B16<>"",$C16<$B16),"⚠ Vencimento anterior à competência","OK"))))))))
A17: L0012 | B17: 46032 | C17: 46032 | D17: 46032 | E17: Entrada | F17: Empréstimos e Financiamentos | G17: Empréstimos e Financiamentos Recebidos | H17: Financeiro | I17: Banco do Brasil | J17: Liberação do Capital de Giro — contrato CG-2026-0417 | K17: CG-2026-0417 | L17: Banco do Brasil — C/C 12345-6 | M17: Transferência | O17: 1 | P17: 1 | Q17: 60000 | R17: 60000 | V17: =IF(COUNTA($B17:$R17)=0,"",ROUND(N($R17)+N($S17)+N($T17)-N($U17),2)) | W17: =IF(COUNTA($B17:$R17)=0,"",IF(OR($X17="Pago",$X17="Recebido",$X17="Cancelado"),0,ROUND(N($Q17)+N($S17)+N($T17)-N($U17)-N($R17),2))) | X17: Recebido | Y17: =IF(COUNTA($B17:$R17)=0,"",IF($X17="Cancelado","Cancelado",IF(OR($X17="Pago",$X17="Recebido"),$X17,IF(OR($X17="Parcial",N($R17)>0),"Parcial",IF($C17="","Sem vencimento",IF($C17<TODAY(),"Vencido",IF($C17=TODAY(),"Vence hoje",IF($C17<=TODAY()+7,"Vence em 7 dias",IF($C17<=TODAY()+30,"Vence em 30 dias","Futuro"))))))))) | Z17: =IF($B17="","",MONTH($B17)) | AA17: =IF($B17="","",YEAR($B17)) | AB17: =IF($B17="","",ISOWEEKNUM($B17)) | AC17: =IF($B17="","",CHOOSE(WEEKDAY($B17,2),"Segunda","Terça","Quarta","Quinta","Sexta","Sábado","Domingo")) | AD17: =IF($B17="","",TEXT($B17,"MM/AAAA")) | AE17: =IF(COUNTA($B17:$R17)=0,"",IF($X17="Cancelado",0,ROUND(N($Q17)+N($S17)+N($T17)-N($U17),2))) | AF17: =IF($G17="","",IFERROR(INDEX(LINHAS_DRE_PLANO,MATCH($G17,SUBCATEGORIAS_PLANO,0)),"Não classificado")) | AG17: =IF($G17="","",IFERROR(INDEX(TIPOS_FLUXO_PLANO,MATCH($G17,SUBCATEGORIAS_PLANO,0)),"Não classificado")) | AH17: =IF($G17="","",IFERROR(INDEX(GRUPOS_PLANO,MATCH($G17,SUBCATEGORIAS_PLANO,0)),"Não classificado")) | AI17: =IF(OR($C17="",$X17="Pago",$X17="Recebido",$X17="Cancelado"),"",$C17-TODAY()) | AJ17: =IF(OR($C17="",$X17="Pago",$X17="Recebido",$X17="Cancelado"),0,MAX(0,TODAY()-$C17)) | AK17: =IF($D17="","",$D17-$B17) | AL17: =IF(OR($D17="",$B17=""),"",ROUND(N($R17)*($D17-$B17),2)) | AM17: =IF(AND($E17="Saída",$W17>0,$C17<>""),$C17+ROW()/1000000,"") | AN17: =IF(AND($E17="Entrada",$W17>0,$C17<>""),$C17+ROW()/1000000,"") | AO17: =IF(COUNTA($B17:$R17)=0,"",IF(AND($I17<>"",COUNTIF(CLIENTES_NOMES,$I17)+COUNTIF(CLIENTES_FANTASIA,$I17)+COUNTIF(FORNECEDORES_NOMES,$I17)+COUNTIF(FORNECEDORES_FANTASIA,$I17)=0),"⚠ Cliente/Fornecedor não cadastrado",IF(AND($G17<>"",COUNTIF(SUBCATEGORIAS_PLANO,$G17)=0),"⚠ Subcategoria fora do plano de contas",IF(OR($Q17="",N($Q17)=0),"⚠ Valor previsto não informado",IF(AND(OR($X17="Pago",$X17="Recebido"),$D17=""),"⚠ Status pago/recebido sem data",IF(AND($D17<>"",N($R17)=0),"⚠ Data de pagamento sem valor realizado",IF(AND(N($P17)>1,N($O17)>N($P17)),"⚠ Nº da parcela maior que o total",IF(AND($C17<>"",$B17<>"",$C17<$B17),"⚠ Vencimento anterior à competência","OK"))))))))
A18: L0013 | B18: 46033 | C18: 46063 | D18: 46066 | E18: Entrada | F18: Vendas | G18: Vendas de Produtos | H18: Comercial | I18: MERCADO BOA COMPRA LTDA | J18: Venda de mercadorias para revenda | K18: NF-e 2000 | L18: Banco do Brasil — C/C 12345-6 | M18: Boleto | O18: 1 | P18: 1 | Q18: 36927.73 | R18: 36927.73 | V18: =IF(COUNTA($B18:$R18)=0,"",ROUND(N($R18)+N($S18)+N($T18)-N($U18),2)) | W18: =IF(COUNTA($B18:$R18)=0,"",IF(OR($X18="Pago",$X18="Recebido",$X18="Cancelado"),0,ROUND(N($Q18)+N($S18)+N($T18)-N($U18)-N($R18),2))) | X18: Pago | Y18: =IF(COUNTA($B18:$R18)=0,"",IF($X18="Cancelado","Cancelado",IF(OR($X18="Pago",$X18="Recebido"),$X18,IF(OR($X18="Parcial",N($R18)>0),"Parcial",IF($C18="","Sem vencimento",IF($C18<TODAY(),"Vencido",IF($C18=TODAY(),"Vence hoje",IF($C18<=TODAY()+7,"Vence em 7 dias",IF($C18<=TODAY()+30,"Vence em 30 dias","Futuro"))))))))) | Z18: =IF($B18="","",MONTH($B18)) | AA18: =IF($B18="","",YEAR($B18)) | AB18: =IF($B18="","",ISOWEEKNUM($B18)) | AC18: =IF($B18="","",CHOOSE(WEEKDAY($B18,2),"Segunda","Terça","Quarta","Quinta","Sexta","Sábado","Domingo")) | AD18: =IF($B18="","",TEXT($B18,"MM/AAAA")) | AE18: =IF(COUNTA($B18:$R18)=0,"",IF($X18="Cancelado",0,ROUND(N($Q18)+N($S18)+N($T18)-N($U18),2))) | AF18: =IF($G18="","",IFERROR(INDEX(LINHAS_DRE_PLANO,MATCH($G18,SUBCATEGORIAS_PLANO,0)),"Não classificado")) | AG18: =IF($G18="","",IFERROR(INDEX(TIPOS_FLUXO_PLANO,MATCH($G18,SUBCATEGORIAS_PLANO,0)),"Não classificado")) | AH18: =IF($G18="","",IFERROR(INDEX(GRUPOS_PLANO,MATCH($G18,SUBCATEGORIAS_PLANO,0)),"Não classificado")) | AI18: =IF(OR($C18="",$X18="Pago",$X18="Recebido",$X18="Cancelado"),"",$C18-TODAY()) | AJ18: =IF(OR($C18="",$X18="Pago",$X18="Recebido",$X18="Cancelado"),0,MAX(0,TODAY()-$C18)) | AK18: =IF($D18="","",$D18-$B18) | AL18: =IF(OR($D18="",$B18=""),"",ROUND(N($R18)*($D18-$B18),2)) | AM18: =IF(AND($E18="Saída",$W18>0,$C18<>""),$C18+ROW()/1000000,"") | AN18: =IF(AND($E18="Entrada",$W18>0,$C18<>""),$C18+ROW()/1000000,"") | AO18: =IF(COUNTA($B18:$R18)=0,"",IF(AND($I18<>"",COUNTIF(CLIENTES_NOMES,$I18)+COUNTIF(CLIENTES_FANTASIA,$I18)+COUNTIF(FORNECEDORES_NOMES,$I18)+COUNTIF(FORNECEDORES_FANTASIA,$I18)=0),"⚠ Cliente/Fornecedor não cadastrado",IF(AND($G18<>"",COUNTIF(SUBCATEGORIAS_PLANO,$G18)=0),"⚠ Subcategoria fora do plano de contas",IF(OR($Q18="",N($Q18)=0),"⚠ Valor previsto não informado",IF(AND(OR($X18="Pago",$X18="Recebido"),$D18=""),"⚠ Status pago/recebido sem data",IF(AND($D18<>"",N($R18)=0),"⚠ Data de pagamento sem valor realizado",IF(AND(N($P18)>1,N($O18)>N($P18)),"⚠ Nº da parcela maior que o total",IF(AND($C18<>"",$B18<>"",$C18<$B18),"⚠ Vencimento anterior à competência","OK"))))))))
A19: L0014 | B19: 46033 | C19: 46034 | D19: 46036 | E19: Entrada | F19: Vendas | G19: Vendas de Produtos | H19: Comercial | I19: PADARIA PÃO DOURADO ME | J19: Venda de mercadorias para revenda | K19: NF-e 2003 | L19: Nubank PJ — C/C 9876543-2 | M19: PIX | O19: 1 | P19: 1 | Q19: 23835.18 | R19: 23835.18 | V19: =IF(COUNTA($B19:$R19)=0,"",ROUND(N($R19)+N($S19)+N($T19)-N($U19),2)) | W19: =IF(COUNTA($B19:$R19)=0,"",IF(OR($X19="Pago",$X19="Recebido",$X19="Cancelado"),0,ROUND(N($Q19)+N($S19)+N($T19)-N($U19)-N($R19),2))) | X19: Pago | Y19: =IF(COUNTA($B19:$R19)=0,"",IF($X19="Cancelado","Cancelado",IF(OR($X19="Pago",$X19="Recebido"),$X19,IF(OR($X19="Parcial",N($R19)>0),"Parcial",IF($C19="","Sem vencimento",IF($C19<TODAY(),"Vencido",IF($C19=TODAY(),"Vence hoje",IF($C19<=TODAY()+7,"Vence em 7 dias",IF($C19<=TODAY()+30,"Vence em 30 dias","Futuro"))))))))) | Z19: =IF($B19="","",MONTH($B19)) | AA19: =IF($B19="","",YEAR($B19)) | AB19: =IF($B19="","",ISOWEEKNUM($B19)) | AC19: =IF($B19="","",CHOOSE(WEEKDAY($B19,2),"Segunda","Terça","Quarta","Quinta","Sexta","Sábado","Domingo")) | AD19: =IF($B19="","",TEXT($B19,"MM/AAAA")) | AE19: =IF(COUNTA($B19:$R19)=0,"",IF($X19="Cancelado",0,ROUND(N($Q19)+N($S19)+N($T19)-N($U19),2))) | AF19: =IF($G19="","",IFERROR(INDEX(LINHAS_DRE_PLANO,MATCH($G19,SUBCATEGORIAS_PLANO,0)),"Não classificado")) | AG19: =IF($G19="","",IFERROR(INDEX(TIPOS_FLUXO_PLANO,MATCH($G19,SUBCATEGORIAS_PLANO,0)),"Não classificado")) | AH19: =IF($G19="","",IFERROR(INDEX(GRUPOS_PLANO,MATCH($G19,SUBCATEGORIAS_PLANO,0)),"Não classificado")) | AI19: =IF(OR($C19="",$X19="Pago",$X19="Recebido",$X19="Cancelado"),"",$C19-TODAY()) | AJ19: =IF(OR($C19="",$X19="Pago",$X19="Recebido",$X19="Cancelado"),0,MAX(0,TODAY()-$C19)) | AK19: =IF($D19="","",$D19-$B19) | AL19: =IF(OR($D19="",$B19=""),"",ROUND(N($R19)*($D19-$B19),2)) | AM19: =IF(AND($E19="Saída",$W19>0,$C19<>""),$C19+ROW()/1000000,"") | AN19: =IF(AND($E19="Entrada",$W19>0,$C19<>""),$C19+ROW()/1000000,"") | AO19: =IF(COUNTA($B19:$R19)=0,"",IF(AND($I19<>"",COUNTIF(CLIENTES_NOMES,$I19)+COUNTIF(CLIENTES_FANTASIA,$I19)+COUNTIF(FORNECEDORES_NOMES,$I19)+COUNTIF(FORNECEDORES_FANTASIA,$I19)=0),"⚠ Cliente/Fornecedor não cadastrado",IF(AND($G19<>"",COUNTIF(SUBCATEGORIAS_PLANO,$G19)=0),"⚠ Subcategoria fora do plano de contas",IF(OR($Q19="",N($Q19)=0),"⚠ Valor previsto não informado",IF(AND(OR($X19="Pago",$X19="Recebido"),$D19=""),"⚠ Status pago/recebido sem data",IF(AND($D19<>"",N($R19)=0),"⚠ Data de pagamento sem valor realizado",IF(AND(N($P19)>1,N($O19)>N($P19)),"⚠ Nº da parcela maior que o total",IF(AND($C19<>"",$B19<>"",$C19<$B19),"⚠ Vencimento anterior à competência","OK"))))))))
A20: L0015 | B20: 46033 | C20: 46048 | D20: 46048 | E20: Entrada | F20: Vendas | G20: Vendas de Produtos | H20: Comercial | I20: RESTAURANTE SABOR CASEIRO LTDA | J20: Venda de mercadorias para revenda | K20: NF-e 2004 | L20: Itaú Unibanco — C/C 45678-9 | M20: Boleto | O20: 1 | P20: 1 | Q20: 17684.54 | R20: 17684.54 | V20: =IF(COUNTA($B20:$R20)=0,"",ROUND(N($R20)+N($S20)+N($T20)-N($U20),2)) | W20: =IF(COUNTA($B20:$R20)=0,"",IF(OR($X20="Pago",$X20="Recebido",$X20="Cancelado"),0,ROUND(N($Q20)+N($S20)+N($T20)-N($U20)-N($R20),2))) | X20: Pago | Y20: =IF(COUNTA($B20:$R20)=0,"",IF($X20="Cancelado","Cancelado",IF(OR($X20="Pago",$X20="Recebido"),$X20,IF(OR($X20="Parcial",N($R20)>0),"Parcial",IF($C20="","Sem vencimento",IF($C20<TODAY(),"Vencido",IF($C20=TODAY(),"Vence hoje",IF($C20<=TODAY()+7,"Vence em 7 dias",IF($C20<=TODAY()+30,"Vence em 30 dias","Futuro"))))))))) | Z20: =IF($B20="","",MONTH($B20)) | AA20: =IF($B20="","",YEAR($B20)) | AB20: =IF($B20="","",ISOWEEKNUM($B20)) | AC20: =IF($B20="","",CHOOSE(WEEKDAY($B20,2),"Segunda","Terça","Quarta","Quinta","Sexta","Sábado","Domingo")) | AD20: =IF($B20="","",TEXT($B20,"MM/AAAA")) | AE20: =IF(COUNTA($B20:$R20)=0,"",IF($X20="Cancelado",0,ROUND(N($Q20)+N($S20)+N($T20)-N($U20),2))) | AF20: =IF($G20="","",IFERROR(INDEX(LINHAS_DRE_PLANO,MATCH($G20,SUBCATEGORIAS_PLANO,0)),"Não classificado")) | AG20: =IF($G20="","",IFERROR(INDEX(TIPOS_FLUXO_PLANO,MATCH($G20,SUBCATEGORIAS_PLANO,0)),"Não classificado")) | AH20: =IF($G20="","",IFERROR(INDEX(GRUPOS_PLANO,MATCH($G20,SUBCATEGORIAS_PLANO,0)),"Não classificado")) | AI20: =IF(OR($C20="",$X20="Pago",$X20="Recebido",$X20="Cancelado"),"",$C20-TODAY()) | AJ20: =IF(OR($C20="",$X20="Pago",$X20="Recebido",$X20="Cancelado"),0,MAX(0,TODAY()-$C20)) | AK20: =IF($D20="","",$D20-$B20) | AL20: =IF(OR($D20="",$B20=""),"",ROUND(N($R20)*($D20-$B20),2)) | AM20: =IF(AND($E20="Saída",$W20>0,$C20<>""),$C20+ROW()/1000000,"") | AN20: =IF(AND($E20="Entrada",$W20>0,$C20<>""),$C20+ROW()/1000000,"") | AO20: =IF(COUNTA($B20:$R20)=0,"",IF(AND($I20<>"",COUNTIF(CLIENTES_NOMES,$I20)+COUNTIF(CLIENTES_FANTASIA,$I20)+COUNTIF(FORNECEDORES_NOMES,$I20)+COUNTIF(FORNECEDORES_FANTASIA,$I20)=0),"⚠ Cliente/Fornecedor não cadastrado",IF(AND($G20<>"",COUNTIF(SUBCATEGORIAS_PLANO,$G20)=0),"⚠ Subcategoria fora do plano de contas",IF(OR($Q20="",N($Q20)=0),"⚠ Valor previsto não informado",IF(AND(OR($X20="Pago",$X20="Recebido"),$D20=""),"⚠ Status pago/recebido sem data",IF(AND($D20<>"",N($R20)=0),"⚠ Data de pagamento sem valor realizado",IF(AND(N($P20)>1,N($O20)>N($P20)),"⚠ Nº da parcela maior que o total",IF(AND($C20<>"",$B20<>"",$C20<$B20),"⚠ Vencimento anterior à competência","OK"))))))))
A21: L0016 | B21: 46033 | C21: 46063 | D21: 46064 | E21: Entrada | F21: Vendas | G21: Vendas de Produtos | H21: Comercial | I21: HOTEL VISTA ALEGRE LTDA | J21: Venda de mercadorias para revenda | K21: NF-e 2007 | L21: Itaú Unibanco — C/C 45678-9 | M21: Boleto | O21: 1 | P21: 1 | Q21: 33978.31 | R21: 33978.31 | V21: =IF(COUNTA($B21:$R21)=0,"",ROUND(N($R21)+N($S21)+N($T21)-N($U21),2)) | W21: =IF(COUNTA($B21:$R21)=0,"",IF(OR($X21="Pago",$X21="Recebido",$X21="Cancelado"),0,ROUND(N($Q21)+N($S21)+N($T21)-N($U21)-N($R21),2))) | X21: Pago | Y21: =IF(COUNTA($B21:$R21)=0,"",IF($X21="Cancelado","Cancelado",IF(OR($X21="Pago",$X21="Recebido"),$X21,IF(OR($X21="Parcial",N($R21)>0),"Parcial",IF($C21="","Sem vencimento",IF($C21<TODAY(),"Vencido",IF($C21=TODAY(),"Vence hoje",IF($C21<=TODAY()+7,"Vence em 7 dias",IF($C21<=TODAY()+30,"Vence em 30 dias","Futuro"))))))))) | Z21: =IF($B21="","",MONTH($B21)) | AA21: =IF($B21="","",YEAR($B21)) | AB21: =IF($B21="","",ISOWEEKNUM($B21)) | AC21: =IF($B21="","",CHOOSE(WEEKDAY($B21,2),"Segunda","Terça","Quarta","Quinta","Sexta","Sábado","Domingo")) | AD21: =IF($B21="","",TEXT($B21,"MM/AAAA")) | AE21: =IF(COUNTA($B21:$R21)=0,"",IF($X21="Cancelado",0,ROUND(N($Q21)+N($S21)+N($T21)-N($U21),2))) | AF21: =IF($G21="","",IFERROR(INDEX(LINHAS_DRE_PLANO,MATCH($G21,SUBCATEGORIAS_PLANO,0)),"Não classificado")) | AG21: =IF($G21="","",IFERROR(INDEX(TIPOS_FLUXO_PLANO,MATCH($G21,SUBCATEGORIAS_PLANO,0)),"Não classificado")) | AH21: =IF($G21="","",IFERROR(INDEX(GRUPOS_PLANO,MATCH($G21,SUBCATEGORIAS_PLANO,0)),"Não classificado")) | AI21: =IF(OR($C21="",$X21="Pago",$X21="Recebido",$X21="Cancelado"),"",$C21-TODAY()) | AJ21: =IF(OR($C21="",$X21="Pago",$X21="Recebido",$X21="Cancelado"),0,MAX(0,TODAY()-$C21)) | AK21: =IF($D21="","",$D21-$B21) | AL21: =IF(OR($D21="",$B21=""),"",ROUND(N($R21)*($D21-$B21),2)) | AM21: =IF(AND($E21="Saída",$W21>0,$C21<>""),$C21+ROW()/1000000,"") | AN21: =IF(AND($E21="Entrada",$W21>0,$C21<>""),$C21+ROW()/1000000,"") | AO21: =IF(COUNTA($B21:$R21)=0,"",IF(AND($I21<>"",COUNTIF(CLIENTES_NOMES,$I21)+COUNTIF(CLIENTES_FANTASIA,$I21)+COUNTIF(FORNECEDORES_NOMES,$I21)+COUNTIF(FORNECEDORES_FANTASIA,$I21)=0),"⚠ Cliente/Fornecedor não cadastrado",IF(AND($G21<>"",COUNTIF(SUBCATEGORIAS_PLANO,$G21)=0),"⚠ Subcategoria fora do plano de contas",IF(OR($Q21="",N($Q21)=0),"⚠ Valor previsto não informado",IF(AND(OR($X21="Pago",$X21="Recebido"),$D21=""),"⚠ Status pago/recebido sem data",IF(AND($D21<>"",N($R21)=0),"⚠ Data de pagamento sem valor realizado",IF(AND(N($P21)>1,N($O21)>N($P21)),"⚠ Nº da parcela maior que o total",IF(AND($C21<>"",$B21<>"",$C21<$B21),"⚠ Vencimento anterior à competência","OK"))))))))
A22: L0017 | B22: 46033 | C22: 46055 | D22: 46057 | E22: Entrada | F22: Vendas | G22: Vendas de Produtos | H22: Comercial | I22: EMPÓRIO NATURAL COMÉRCIO LTDA | J22: Venda de mercadorias para revenda | K22: NF-e 2008 | L22: Itaú Unibanco — C/C 45678-9 | M22: Boleto | O22: 1 | P22: 1 | Q22: 23627.91 | R22: 23627.91 | V22: =IF(COUNTA($B22:$R22)=0,"",ROUND(N($R22)+N($S22)+N($T22)-N($U22),2)) | W22: =IF(COUNTA($B22:$R22)=0,"",IF(OR($X22="Pago",$X22="Recebido",$X22="Cancelado"),0,ROUND(N($Q22)+N($S22)+N($T22)-N($U22)-N($R22),2))) | X22: Pago | Y22: =IF(COUNTA($B22:$R22)=0,"",IF($X22="Cancelado","Cancelado",IF(OR($X22="Pago",$X22="Recebido"),$X22,IF(OR($X22="Parcial",N($R22)>0),"Parcial",IF($C22="","Sem vencimento",IF($C22<TODAY(),"Vencido",IF($C22=TODAY(),"Vence hoje",IF($C22<=TODAY()+7,"Vence em 7 dias",IF($C22<=TODAY()+30,"Vence em 30 dias","Futuro"))))))))) | Z22: =IF($B22="","",MONTH($B22)) | AA22: =IF($B22="","",YEAR($B22)) | AB22: =IF($B22="","",ISOWEEKNUM($B22)) | AC22: =IF($B22="","",CHOOSE(WEEKDAY($B22,2),"Segunda","Terça","Quarta","Quinta","Sexta","Sábado","Domingo")) | AD22: =IF($B22="","",TEXT($B22,"MM/AAAA")) | AE22: =IF(COUNTA($B22:$R22)=0,"",IF($X22="Cancelado",0,ROUND(N($Q22)+N($S22)+N($T22)-N($U22),2))) | AF22: =IF($G22="","",IFERROR(INDEX(LINHAS_DRE_PLANO,MATCH($G22,SUBCATEGORIAS_PLANO,0)),"Não classificado")) | AG22: =IF($G22="","",IFERROR(INDEX(TIPOS_FLUXO_PLANO,MATCH($G22,SUBCATEGORIAS_PLANO,0)),"Não classificado")) | AH22: =IF($G22="","",IFERROR(INDEX(GRUPOS_PLANO,MATCH($G22,SUBCATEGORIAS_PLANO,0)),"Não classificado")) | AI22: =IF(OR($C22="",$X22="Pago",$X22="Recebido",$X22="Cancelado"),"",$C22-TODAY()) | AJ22: =IF(OR($C22="",$X22="Pago",$X22="Recebido",$X22="Cancelado"),0,MAX(0,TODAY()-$C22)) | AK22: =IF($D22="","",$D22-$B22) | AL22: =IF(OR($D22="",$B22=""),"",ROUND(N($R22)*($D22-$B22),2)) | AM22: =IF(AND($E22="Saída",$W22>0,$C22<>""),$C22+ROW()/1000000,"") | AN22: =IF(AND($E22="Entrada",$W22>0,$C22<>""),$C22+ROW()/1000000,"") | AO22: =IF(COUNTA($B22:$R22)=0,"",IF(AND($I22<>"",COUNTIF(CLIENTES_NOMES,$I22)+COUNTIF(CLIENTES_FANTASIA,$I22)+COUNTIF(FORNECEDORES_NOMES,$I22)+COUNTIF(FORNECEDORES_FANTASIA,$I22)=0),"⚠ Cliente/Fornecedor não cadastrado",IF(AND($G22<>"",COUNTIF(SUBCATEGORIAS_PLANO,$G22)=0),"⚠ Subcategoria fora do plano de contas",IF(OR($Q22="",N($Q22)=0),"⚠ Valor previsto não informado",IF(AND(OR($X22="Pago",$X22="Recebido"),$D22=""),"⚠ Status pago/recebido sem data",IF(AND($D22<>"",N($R22)=0),"⚠ Data de pagamento sem valor realizado",IF(AND(N($P22)>1,N($O22)>N($P22)),"⚠ Nº da parcela maior que o total",IF(AND($C22<>"",$B22<>"",$C22<$B22),"⚠ Vencimento anterior à competência","OK"))))))))
A23: L0018 | B23: 46034 | C23: 46049 | D23: 46049 | E23: Saída | F23: Custos Variáveis | G23: Embalagens | H23: Logística | I23: EMBALAGENS PAULISTA LTDA | J23: Compra de embalagens e etiquetas | K23: DOC 7160 | L23: Itaú Unibanco — C/C 45678-9 | M23: Boleto | O23: 1 | P23: 1 | Q23: 2557.88 | R23: 2557.88 | V23: =IF(COUNTA($B23:$R23)=0,"",ROUND(N($R23)+N($S23)+N($T23)-N($U23),2)) | W23: =IF(COUNTA($B23:$R23)=0,"",IF(OR($X23="Pago",$X23="Recebido",$X23="Cancelado"),0,ROUND(N($Q23)+N($S23)+N($T23)-N($U23)-N($R23),2))) | X23: Pago | Y23: =IF(COUNTA($B23:$R23)=0,"",IF($X23="Cancelado","Cancelado",IF(OR($X23="Pago",$X23="Recebido"),$X23,IF(OR($X23="Parcial",N($R23)>0),"Parcial",IF($C23="","Sem vencimento",IF($C23<TODAY(),"Vencido",IF($C23=TODAY(),"Vence hoje",IF($C23<=TODAY()+7,"Vence em 7 dias",IF($C23<=TODAY()+30,"Vence em 30 dias","Futuro"))))))))) | Z23: =IF($B23="","",MONTH($B23)) | AA23: =IF($B23="","",YEAR($B23)) | AB23: =IF($B23="","",ISOWEEKNUM($B23)) | AC23: =IF($B23="","",CHOOSE(WEEKDAY($B23,2),"Segunda","Terça","Quarta","Quinta","Sexta","Sábado","Domingo")) | AD23: =IF($B23="","",TEXT($B23,"MM/AAAA")) | AE23: =IF(COUNTA($B23:$R23)=0,"",IF($X23="Cancelado",0,ROUND(N($Q23)+N($S23)+N($T23)-N($U23),2))) | AF23: =IF($G23="","",IFERROR(INDEX(LINHAS_DRE_PLANO,MATCH($G23,SUBCATEGORIAS_PLANO,0)),"Não classificado")) | AG23: =IF($G23="","",IFERROR(INDEX(TIPOS_FLUXO_PLANO,MATCH($G23,SUBCATEGORIAS_PLANO,0)),"Não classificado")) | AH23: =IF($G23="","",IFERROR(INDEX(GRUPOS_PLANO,MATCH($G23,SUBCATEGORIAS_PLANO,0)),"Não classificado")) | AI23: =IF(OR($C23="",$X23="Pago",$X23="Recebido",$X23="Cancelado"),"",$C23-TODAY()) | AJ23: =IF(OR($C23="",$X23="Pago",$X23="Recebido",$X23="Cancelado"),0,MAX(0,TODAY()-$C23)) | AK23: =IF($D23="","",$D23-$B23) | AL23: =IF(OR($D23="",$B23=""),"",ROUND(N($R23)*($D23-$B23),2)) | AM23: =IF(AND($E23="Saída",$W23>0,$C23<>""),$C23+ROW()/1000000,"") | AN23: =IF(AND($E23="Entrada",$W23>0,$C23<>""),$C23+ROW()/1000000,"") | AO23: =IF(COUNTA($B23:$R23)=0,"",IF(AND($I23<>"",COUNTIF(CLIENTES_NOMES,$I23)+COUNTIF(CLIENTES_FANTASIA,$I23)+COUNTIF(FORNECEDORES_NOMES,$I23)+COUNTIF(FORNECEDORES_FANTASIA,$I23)=0),"⚠ Cliente/Fornecedor não cadastrado",IF(AND($G23<>"",COUNTIF(SUBCATEGORIAS_PLANO,$G23)=0),"⚠ Subcategoria fora do plano de contas",IF(OR($Q23="",N($Q23)=0),"⚠ Valor previsto não informado",IF(AND(OR($X23="Pago",$X23="Recebido"),$D23=""),"⚠ Status pago/recebido sem data",IF(AND($D23<>"",N($R23)=0),"⚠ Data de pagamento sem valor realizado",IF(AND(N($P23)>1,N($O23)>N($P23)),"⚠ Nº da parcela maior que o total",IF(AND($C23<>"",$B23<>"",$C23<$B23),"⚠ Vencimento anterior à competência","OK"))))))))
A24: L0019 | B24: 46034 | C24: 46044 | D24: 46045 | E24: Saída | F24: Despesas Administrativas | G24: Energia Elétrica | H24: Administrativo | I24: ENEL DISTRIBUIÇÃO SÃO PAULO | J24: Energia elétrica — fatura 01/2026 | K24: DOC 8266 | L24: Itaú Unibanco — C/C 45678-9 | M24: Débito automático | O24: 1 | P24: 1 | Q24: 2319.32 | R24: 2319.32 | V24: =IF(COUNTA($B24:$R24)=0,"",ROUND(N($R24)+N($S24)+N($T24)-N($U24),2)) | W24: =IF(COUNTA($B24:$R24)=0,"",IF(OR($X24="Pago",$X24="Recebido",$X24="Cancelado"),0,ROUND(N($Q24)+N($S24)+N($T24)-N($U24)-N($R24),2))) | X24: Pago | Y24: =IF(COUNTA($B24:$R24)=0,"",IF($X24="Cancelado","Cancelado",IF(OR($X24="Pago",$X24="Recebido"),$X24,IF(OR($X24="Parcial",N($R24)>0),"Parcial",IF($C24="","Sem vencimento",IF($C24<TODAY(),"Vencido",IF($C24=TODAY(),"Vence hoje",IF($C24<=TODAY()+7,"Vence em 7 dias",IF($C24<=TODAY()+30,"Vence em 30 dias","Futuro"))))))))) | Z24: =IF($B24="","",MONTH($B24)) | AA24: =IF($B24="","",YEAR($B24)) | AB24: =IF($B24="","",ISOWEEKNUM($B24)) | AC24: =IF($B24="","",CHOOSE(WEEKDAY($B24,2),"Segunda","Terça","Quarta","Quinta","Sexta","Sábado","Domingo")) | AD24: =IF($B24="","",TEXT($B24,"MM/AAAA")) | AE24: =IF(COUNTA($B24:$R24)=0,"",IF($X24="Cancelado",0,ROUND(N($Q24)+N($S24)+N($T24)-N($U24),2))) | AF24: =IF($G24="","",IFERROR(INDEX(LINHAS_DRE_PLANO,MATCH($G24,SUBCATEGORIAS_PLANO,0)),"Não classificado")) | AG24: =IF($G24="","",IFERROR(INDEX(TIPOS_FLUXO_PLANO,MATCH($G24,SUBCATEGORIAS_PLANO,0)),"Não classificado")) | AH24: =IF($G24="","",IFERROR(INDEX(GRUPOS_PLANO,MATCH($G24,SUBCATEGORIAS_PLANO,0)),"Não classificado")) | AI24: =IF(OR($C24="",$X24="Pago",$X24="Recebido",$X24="Cancelado"),"",$C24-TODAY()) | AJ24: =IF(OR($C24="",$X24="Pago",$X24="Recebido",$X24="Cancelado"),0,MAX(0,TODAY()-$C24)) | AK24: =IF($D24="","",$D24-$B24) | AL24: =IF(OR($D24="",$B24=""),"",ROUND(N($R24)*($D24-$B24),2)) | AM24: =IF(AND($E24="Saída",$W24>0,$C24<>""),$C24+ROW()/1000000,"") | AN24: =IF(AND($E24="Entrada",$W24>0,$C24<>""),$C24+ROW()/1000000,"") | AO24: =IF(COUNTA($B24:$R24)=0,"",IF(AND($I24<>"",COUNTIF(CLIENTES_NOMES,$I24)+COUNTIF(CLIENTES_FANTASIA,$I24)+COUNTIF(FORNECEDORES_NOMES,$I24)+COUNTIF(FORNECEDORES_FANTASIA,$I24)=0),"⚠ Cliente/Fornecedor não cadastrado",IF(AND($G24<>"",COUNTIF(SUBCATEGORIAS_PLANO,$G24)=0),"⚠ Subcategoria fora do plano de contas",IF(OR($Q24="",N($Q24)=0),"⚠ Valor previsto não informado",IF(AND(OR($X24="Pago",$X24="Recebido"),$D24=""),"⚠ Status pago/recebido sem data",IF(AND($D24<>"",N($R24)=0),"⚠ Data de pagamento sem valor realizado",IF(AND(N($P24)>1,N($O24)>N($P24)),"⚠ Nº da parcela maior que o total",IF(AND($C24<>"",$B24<>"",$C24<$B24),"⚠ Vencimento anterior à competência","OK"))))))))
A25: L0020 | B25: 46037 | C25: 46049 | D25: 46052 | E25: Saída | F25: Despesas Administrativas | G25: Água e Saneamento | H25: Administrativo | I25: SABESP — SANEAMENTO BÁSICO DO ESTADO DE SÃO PAULO | J25: Água e saneamento — fatura 01/2026 | K25: DOC 8267 | L25: Itaú Unibanco — C/C 45678-9 | M25: Débito automático | O25: 1 | P25: 1 | Q25: 425.55 | R25: 425.55 | V25: =IF(COUNTA($B25:$R25)=0,"",ROUND(N($R25)+N($S25)+N($T25)-N($U25),2)) | W25: =IF(COUNTA($B25:$R25)=0,"",IF(OR($X25="Pago",$X25="Recebido",$X25="Cancelado"),0,ROUND(N($Q25)+N($S25)+N($T25)-N($U25)-N($R25),2))) | X25: Pago | Y25: =IF(COUNTA($B25:$R25)=0,"",IF($X25="Cancelado","Cancelado",IF(OR($X25="Pago",$X25="Recebido"),$X25,IF(OR($X25="Parcial",N($R25)>0),"Parcial",IF($C25="","Sem vencimento",IF($C25<TODAY(),"Vencido",IF($C25=TODAY(),"Vence hoje",IF($C25<=TODAY()+7,"Vence em 7 dias",IF($C25<=TODAY()+30,"Vence em 30 dias","Futuro"))))))))) | Z25: =IF($B25="","",MONTH($B25)) | AA25: =IF($B25="","",YEAR($B25)) | AB25: =IF($B25="","",ISOWEEKNUM($B25)) | AC25: =IF($B25="","",CHOOSE(WEEKDAY($B25,2),"Segunda","Terça","Quarta","Quinta","Sexta","Sábado","Domingo")) | AD25: =IF($B25="","",TEXT($B25,"MM/AAAA")) | AE25: =IF(COUNTA($B25:$R25)=0,"",IF($X25="Cancelado",0,ROUND(N($Q25)+N($S25)+N($T25)-N($U25),2))) | AF25: =IF($G25="","",IFERROR(INDEX(LINHAS_DRE_PLANO,MATCH($G25,SUBCATEGORIAS_PLANO,0)),"Não classificado")) | AG25: =IF($G25="","",IFERROR(INDEX(TIPOS_FLUXO_PLANO,MATCH($G25,SUBCATEGORIAS_PLANO,0)),"Não classificado")) | AH25: =IF($G25="","",IFERROR(INDEX(GRUPOS_PLANO,MATCH($G25,SUBCATEGORIAS_PLANO,0)),"Não classificado")) | AI25: =IF(OR($C25="",$X25="Pago",$X25="Recebido",$X25="Cancelado"),"",$C25-TODAY()) | AJ25: =IF(OR($C25="",$X25="Pago",$X25="Recebido",$X25="Cancelado"),0,MAX(0,TODAY()-$C25)) | AK25: =IF($D25="","",$D25-$B25) | AL25: =IF(OR($D25="",$B25=""),"",ROUND(N($R25)*($D25-$B25),2)) | AM25: =IF(AND($E25="Saída",$W25>0,$C25<>""),$C25+ROW()/1000000,"") | AN25: =IF(AND($E25="Entrada",$W25>0,$C25<>""),$C25+ROW()/1000000,"") | AO25: =IF(COUNTA($B25:$R25)=0,"",IF(AND($I25<>"",COUNTIF(CLIENTES_NOMES,$I25)+COUNTIF(CLIENTES_FANTASIA,$I25)+COUNTIF(FORNECEDORES_NOMES,$I25)+COUNTIF(FORNECEDORES_FANTASIA,$I25)=0),"⚠ Cliente/Fornecedor não cadastrado",IF(AND($G25<>"",COUNTIF(SUBCATEGORIAS_PLANO,$G25)=0),"⚠ Subcategoria fora do plano de contas",IF(OR($Q25="",N($Q25)=0),"⚠ Valor previsto não informado",IF(AND(OR($X25="Pago",$X25="Recebido"),$D25=""),"⚠ Status pago/recebido sem data",IF(AND($D25<>"",N($R25)=0),"⚠ Data de pagamento sem valor realizado",IF(AND(N($P25)>1,N($O25)>N($P25)),"⚠ Nº da parcela maior que o total",IF(AND($C25<>"",$B25<>"",$C25<$B25),"⚠ Vencimento anterior à competência","OK"))))))))
A26: L0021 | B26: 46038 | C26: 46068 | D26: 46068 | E26: Saída | F26: Custos Variáveis | G26: Mercadorias para Revenda | H26: Logística | I26: DISTRIBUIDORA CENTRAL DE ALIMENTOS S/A | J26: Compra de mercadorias para revenda — NF 5011 | K26: NF 5011 | L26: Itaú Unibanco — C/C 45678-9 | M26: Boleto | O26: 1 | P26: 1 | Q26: 50989.63 | R26: 50989.63 | V26: =IF(COUNTA($B26:$R26)=0,"",ROUND(N($R26)+N($S26)+N($T26)-N($U26),2)) | W26: =IF(COUNTA($B26:$R26)=0,"",IF(OR($X26="Pago",$X26="Recebido",$X26="Cancelado"),0,ROUND(N($Q26)+N($S26)+N($T26)-N($U26)-N($R26),2))) | X26: Pago | Y26: =IF(COUNTA($B26:$R26)=0,"",IF($X26="Cancelado","Cancelado",IF(OR($X26="Pago",$X26="Recebido"),$X26,IF(OR($X26="Parcial",N($R26)>0),"Parcial",IF($C26="","Sem vencimento",IF($C26<TODAY(),"Vencido",IF($C26=TODAY(),"Vence hoje",IF($C26<=TODAY()+7,"Vence em 7 dias",IF($C26<=TODAY()+30,"Vence em 30 dias","Futuro"))))))))) | Z26: =IF($B26="","",MONTH($B26)) | AA26: =IF($B26="","",YEAR($B26)) | AB26: =IF($B26="","",ISOWEEKNUM($B26)) | AC26: =IF($B26="","",CHOOSE(WEEKDAY($B26,2),"Segunda","Terça","Quarta","Quinta","Sexta","Sábado","Domingo")) | AD26: =IF($B26="","",TEXT($B26,"MM/AAAA")) | AE26: =IF(COUNTA($B26:$R26)=0,"",IF($X26="Cancelado",0,ROUND(N($Q26)+N($S26)+N($T26)-N($U26),2))) | AF26: =IF($G26="","",IFERROR(INDEX(LINHAS_DRE_PLANO,MATCH($G26,SUBCATEGORIAS_PLANO,0)),"Não classificado")) | AG26: =IF($G26="","",IFERROR(INDEX(TIPOS_FLUXO_PLANO,MATCH($G26,SUBCATEGORIAS_PLANO,0)),"Não classificado")) | AH26: =IF($G26="","",IFERROR(INDEX(GRUPOS_PLANO,MATCH($G26,SUBCATEGORIAS_PLANO,0)),"Não classificado")) | AI26: =IF(OR($C26="",$X26="Pago",$X26="Recebido",$X26="Cancelado"),"",$C26-TODAY()) | AJ26: =IF(OR($C26="",$X26="Pago",$X26="Recebido",$X26="Cancelado"),0,MAX(0,TODAY()-$C26)) | AK26: =IF($D26="","",$D26-$B26) | AL26: =IF(OR($D26="",$B26=""),"",ROUND(N($R26)*($D26-$B26),2)) | AM26: =IF(AND($E26="Saída",$W26>0,$C26<>""),$C26+ROW()/1000000,"") | AN26: =IF(AND($E26="Entrada",$W26>0,$C26<>""),$C26+ROW()/1000000,"") | AO26: =IF(COUNTA($B26:$R26)=0,"",IF(AND($I26<>"",COUNTIF(CLIENTES_NOMES,$I26)+COUNTIF(CLIENTES_FANTASIA,$I26)+COUNTIF(FORNECEDORES_NOMES,$I26)+COUNTIF(FORNECEDORES_FANTASIA,$I26)=0),"⚠ Cliente/Fornecedor não cadastrado",IF(AND($G26<>"",COUNTIF(SUBCATEGORIAS_PLANO,$G26)=0),"⚠ Subcategoria fora do plano de contas",IF(OR($Q26="",N($Q26)=0),"⚠ Valor previsto não informado",IF(AND(OR($X26="Pago",$X26="Recebido"),$D26=""),"⚠ Status pago/recebido sem data",IF(AND($D26<>"",N($R26)=0),"⚠ Data de pagamento sem valor realizado",IF(AND(N($P26)>1,N($O26)>N($P26)),"⚠ Nº da parcela maior que o total",IF(AND($C26<>"",$B26<>"",$C26<$B26),"⚠ Vencimento anterior à competência","OK"))))))))
A27: L0022 | B27: 46040 | C27: 46050 | D27: 46052 | E27: Saída | F27: Despesas Comerciais | G27: Publicidade e Anúncios | H27: Marketing | I27: GOOGLE BRASIL INTERNET LTDA | J27: Anúncios e campanhas digitais | K27: DOC 8276 | L27: Nubank PJ — C/C 9876543-2 | M27: Cartão de crédito | N27: Cartão Mastercard Nubank PJ | O27: 1 | P27: 1 | Q27: 1430.37 | R27: 1430.37 | V27: =IF(COUNTA($B27:$R27)=0,"",ROUND(N($R27)+N($S27)+N($T27)-N($U27),2)) | W27: =IF(COUNTA($B27:$R27)=0,"",IF(OR($X27="Pago",$X27="Recebido",$X27="Cancelado"),0,ROUND(N($Q27)+N($S27)+N($T27)-N($U27)-N($R27),2))) | X27: Pago | Y27: =IF(COUNTA($B27:$R27)=0,"",IF($X27="Cancelado","Cancelado",IF(OR($X27="Pago",$X27="Recebido"),$X27,IF(OR($X27="Parcial",N($R27)>0),"Parcial",IF($C27="","Sem vencimento",IF($C27<TODAY(),"Vencido",IF($C27=TODAY(),"Vence hoje",IF($C27<=TODAY()+7,"Vence em 7 dias",IF($C27<=TODAY()+30,"Vence em 30 dias","Futuro"))))))))) | Z27: =IF($B27="","",MONTH($B27)) | AA27: =IF($B27="","",YEAR($B27)) | AB27: =IF($B27="","",ISOWEEKNUM($B27)) | AC27: =IF($B27="","",CHOOSE(WEEKDAY($B27,2),"Segunda","Terça","Quarta","Quinta","Sexta","Sábado","Domingo")) | AD27: =IF($B27="","",TEXT($B27,"MM/AAAA")) | AE27: =IF(COUNTA($B27:$R27)=0,"",IF($X27="Cancelado",0,ROUND(N($Q27)+N($S27)+N($T27)-N($U27),2))) | AF27: =IF($G27="","",IFERROR(INDEX(LINHAS_DRE_PLANO,MATCH($G27,SUBCATEGORIAS_PLANO,0)),"Não classificado")) | AG27: =IF($G27="","",IFERROR(INDEX(TIPOS_FLUXO_PLANO,MATCH($G27,SUBCATEGORIAS_PLANO,0)),"Não classificado")) | AH27: =IF($G27="","",IFERROR(INDEX(GRUPOS_PLANO,MATCH($G27,SUBCATEGORIAS_PLANO,0)),"Não classificado")) | AI27: =IF(OR($C27="",$X27="Pago",$X27="Recebido",$X27="Cancelado"),"",$C27-TODAY()) | AJ27: =IF(OR($C27="",$X27="Pago",$X27="Recebido",$X27="Cancelado"),0,MAX(0,TODAY()-$C27)) | AK27: =IF($D27="","",$D27-$B27) | AL27: =IF(OR($D27="",$B27=""),"",ROUND(N($R27)*($D27-$B27),2)) | AM27: =IF(AND($E27="Saída",$W27>0,$C27<>""),$C27+ROW()/1000000,"") | AN27: =IF(AND($E27="Entrada",$W27>0,$C27<>""),$C27+ROW()/1000000,"") | AO27: =IF(COUNTA($B27:$R27)=0,"",IF(AND($I27<>"",COUNTIF(CLIENTES_NOMES,$I27)+COUNTIF(CLIENTES_FANTASIA,$I27)+COUNTIF(FORNECEDORES_NOMES,$I27)+COUNTIF(FORNECEDORES_FANTASIA,$I27)=0),"⚠ Cliente/Fornecedor não cadastrado",IF(AND($G27<>"",COUNTIF(SUBCATEGORIAS_PLANO,$G27)=0),"⚠ Subcategoria fora do plano de contas",IF(OR($Q27="",N($Q27)=0),"⚠ Valor previsto não informado",IF(AND(OR($X27="Pago",$X27="Recebido"),$D27=""),"⚠ Status pago/recebido sem data",IF(AND($D27<>"",N($R27)=0),"⚠ Data de pagamento sem valor realizado",IF(AND(N($P27)>1,N($O27)>N($P27)),"⚠ Nº da parcela maior que o total",IF(AND($C27<>"",$B27<>"",$C27<$B27),"⚠ Vencimento anterior à competência","OK"))))))))
A28: L0023 | B28: 46040 | C28: 46078 | D28: 46078 | E28: Saída | F28: Despesas Administrativas | G28: Manutenção e Conservação | H28: Logística | I28: Posto e oficina credenciados | J28: Combustível e manutenção da frota | K28: FROTA 01 | L28: Banco do Brasil — C/C 12345-6 | M28: Cartão de crédito | N28: Cartão Elo Banco do Brasil PJ | O28: 1 | P28: 1 | Q28: 924.75 | R28: 924.75 | V28: =IF(COUNTA($B28:$R28)=0,"",ROUND(N($R28)+N($S28)+N($T28)-N($U28),2)) | W28: =IF(COUNTA($B28:$R28)=0,"",IF(OR($X28="Pago",$X28="Recebido",$X28="Cancelado"),0,ROUND(N($Q28)+N($S28)+N($T28)-N($U28)-N($R28),2))) | X28: Pago | Y28: =IF(COUNTA($B28:$R28)=0,"",IF($X28="Cancelado","Cancelado",IF(OR($X28="Pago",$X28="Recebido"),$X28,IF(OR($X28="Parcial",N($R28)>0),"Parcial",IF($C28="","Sem vencimento",IF($C28<TODAY(),"Vencido",IF($C28=TODAY(),"Vence hoje",IF($C28<=TODAY()+7,"Vence em 7 dias",IF($C28<=TODAY()+30,"Vence em 30 dias","Futuro"))))))))) | Z28: =IF($B28="","",MONTH($B28)) | AA28: =IF($B28="","",YEAR($B28)) | AB28: =IF($B28="","",ISOWEEKNUM($B28)) | AC28: =IF($B28="","",CHOOSE(WEEKDAY($B28,2),"Segunda","Terça","Quarta","Quinta","Sexta","Sábado","Domingo")) | AD28: =IF($B28="","",TEXT($B28,"MM/AAAA")) | AE28: =IF(COUNTA($B28:$R28)=0,"",IF($X28="Cancelado",0,ROUND(N($Q28)+N($S28)+N($T28)-N($U28),2))) | AF28: =IF($G28="","",IFERROR(INDEX(LINHAS_DRE_PLANO,MATCH($G28,SUBCATEGORIAS_PLANO,0)),"Não classificado")) | AG28: =IF($G28="","",IFERROR(INDEX(TIPOS_FLUXO_PLANO,MATCH($G28,SUBCATEGORIAS_PLANO,0)),"Não classificado")) | AH28: =IF($G28="","",IFERROR(INDEX(GRUPOS_PLANO,MATCH($G28,SUBCATEGORIAS_PLANO,0)),"Não classificado")) | AI28: =IF(OR($C28="",$X28="Pago",$X28="Recebido",$X28="Cancelado"),"",$C28-TODAY()) | AJ28: =IF(OR($C28="",$X28="Pago",$X28="Recebido",$X28="Cancelado"),0,MAX(0,TODAY()-$C28)) | AK28: =IF($D28="","",$D28-$B28) | AL28: =IF(OR($D28="",$B28=""),"",ROUND(N($R28)*($D28-$B28),2)) | AM28: =IF(AND($E28="Saída",$W28>0,$C28<>""),$C28+ROW()/1000000,"") | AN28: =IF(AND($E28="Entrada",$W28>0,$C28<>""),$C28+ROW()/1000000,"") | AO28: =IF(COUNTA($B28:$R28)=0,"",IF(AND($I28<>"",COUNTIF(CLIENTES_NOMES,$I28)+COUNTIF(CLIENTES_FANTASIA,$I28)+COUNTIF(FORNECEDORES_NOMES,$I28)+COUNTIF(FORNECEDORES_FANTASIA,$I28)=0),"⚠ Cliente/Fornecedor não cadastrado",IF(AND($G28<>"",COUNTIF(SUBCATEGORIAS_PLANO,$G28)=0),"⚠ Subcategoria fora do plano de contas",IF(OR($Q28="",N($Q28)=0),"⚠ Valor previsto não informado",IF(AND(OR($X28="Pago",$X28="Recebido"),$D28=""),"⚠ Status pago/recebido sem data",IF(AND($D28<>"",N($R28)=0),"⚠ Data de pagamento sem valor realizado",IF(AND(N($P28)>1,N($O28)>N($P28)),"⚠ Nº da parcela maior que o total",IF(AND($C28<>"",$B28<>"",$C28<$B28),"⚠ Vencimento anterior à competência","OK"))))))))
A29: L0024 | B29: 46041 | C29: 46071 | D29: 46072 | E29: Entrada | F29: Vendas | G29: Vendas de Produtos | H29: Comercial | I29: MERCADO BOA COMPRA LTDA | J29: Venda de mercadorias para revenda | K29: NF-e 2001 | L29: Banco do Brasil — C/C 12345-6 | M29: Boleto | O29: 1 | P29: 1 | Q29: 26500.57 | R29: 26500.57 | V29: =IF(COUNTA($B29:$R29)=0,"",ROUND(N($R29)+N($S29)+N($T29)-N($U29),2)) | W29: =IF(COUNTA($B29:$R29)=0,"",IF(OR($X29="Pago",$X29="Recebido",$X29="Cancelado"),0,ROUND(N($Q29)+N($S29)+N($T29)-N($U29)-N($R29),2))) | X29: Pago | Y29: =IF(COUNTA($B29:$R29)=0,"",IF($X29="Cancelado","Cancelado",IF(OR($X29="Pago",$X29="Recebido"),$X29,IF(OR($X29="Parcial",N($R29)>0),"Parcial",IF($C29="","Sem vencimento",IF($C29<TODAY(),"Vencido",IF($C29=TODAY(),"Vence hoje",IF($C29<=TODAY()+7,"Vence em 7 dias",IF($C29<=TODAY()+30,"Vence em 30 dias","Futuro"))))))))) | Z29: =IF($B29="","",MONTH($B29)) | AA29: =IF($B29="","",YEAR($B29)) | AB29: =IF($B29="","",ISOWEEKNUM($B29)) | AC29: =IF($B29="","",CHOOSE(WEEKDAY($B29,2),"Segunda","Terça","Quarta","Quinta","Sexta","Sábado","Domingo")) | AD29: =IF($B29="","",TEXT($B29,"MM/AAAA")) | AE29: =IF(COUNTA($B29:$R29)=0,"",IF($X29="Cancelado",0,ROUND(N($Q29)+N($S29)+N($T29)-N($U29),2))) | AF29: =IF($G29="","",IFERROR(INDEX(LINHAS_DRE_PLANO,MATCH($G29,SUBCATEGORIAS_PLANO,0)),"Não classificado")) | AG29: =IF($G29="","",IFERROR(INDEX(TIPOS_FLUXO_PLANO,MATCH($G29,SUBCATEGORIAS_PLANO,0)),"Não classificado")) | AH29: =IF($G29="","",IFERROR(INDEX(GRUPOS_PLANO,MATCH($G29,SUBCATEGORIAS_PLANO,0)),"Não classificado")) | AI29: =IF(OR($C29="",$X29="Pago",$X29="Recebido",$X29="Cancelado"),"",$C29-TODAY()) | AJ29: =IF(OR($C29="",$X29="Pago",$X29="Recebido",$X29="Cancelado"),0,MAX(0,TODAY()-$C29)) | AK29: =IF($D29="","",$D29-$B29) | AL29: =IF(OR($D29="",$B29=""),"",ROUND(N($R29)*($D29-$B29),2)) | AM29: =IF(AND($E29="Saída",$W29>0,$C29<>""),$C29+ROW()/1000000,"") | AN29: =IF(AND($E29="Entrada",$W29>0,$C29<>""),$C29+ROW()/1000000,"") | AO29: =IF(COUNTA($B29:$R29)=0,"",IF(AND($I29<>"",COUNTIF(CLIENTES_NOMES,$I29)+COUNTIF(CLIENTES_FANTASIA,$I29)+COUNTIF(FORNECEDORES_NOMES,$I29)+COUNTIF(FORNECEDORES_FANTASIA,$I29)=0),"⚠ Cliente/Fornecedor não cadastrado",IF(AND($G29<>"",COUNTIF(SUBCATEGORIAS_PLANO,$G29)=0),"⚠ Subcategoria fora do plano de contas",IF(OR($Q29="",N($Q29)=0),"⚠ Valor previsto não informado",IF(AND(OR($X29="Pago",$X29="Recebido"),$D29=""),"⚠ Status pago/recebido sem data",IF(AND($D29<>"",N($R29)=0),"⚠ Data de pagamento sem valor realizado",IF(AND(N($P29)>1,N($O29)>N($P29)),"⚠ Nº da parcela maior que o total",IF(AND($C29<>"",$B29<>"",$C29<$B29),"⚠ Vencimento anterior à competência","OK"))))))))
A30: L0025 | B30: 46041 | C30: 46056 | D30: 46057 | E30: Entrada | F30: Vendas | G30: Vendas de Produtos | H30: Comercial | I30: RESTAURANTE SABOR CASEIRO LTDA | J30: Venda de mercadorias para revenda | K30: NF-e 2005 | L30: Itaú Unibanco — C/C 45678-9 | M30: Boleto | O30: 1 | P30: 1 | Q30: 12429.54 | R30: 12429.54 | V30: =IF(COUNTA($B30:$R30)=0,"",ROUND(N($R30)+N($S30)+N($T30)-N($U30),2)) | W30: =IF(COUNTA($B30:$R30)=0,"",IF(OR($X30="Pago",$X30="Recebido",$X30="Cancelado"),0,ROUND(N($Q30)+N($S30)+N($T30)-N($U30)-N($R30),2))) | X30: Pago | Y30: =IF(COUNTA($B30:$R30)=0,"",IF($X30="Cancelado","Cancelado",IF(OR($X30="Pago",$X30="Recebido"),$X30,IF(OR($X30="Parcial",N($R30)>0),"Parcial",IF($C30="","Sem vencimento",IF($C30<TODAY(),"Vencido",IF($C30=TODAY(),"Vence hoje",IF($C30<=TODAY()+7,"Vence em 7 dias",IF($C30<=TODAY()+30,"Vence em 30 dias","Futuro"))))))))) | Z30: =IF($B30="","",MONTH($B30)) | AA30: =IF($B30="","",YEAR($B30)) | AB30: =IF($B30="","",ISOWEEKNUM($B30)) | AC30: =IF($B30="","",CHOOSE(WEEKDAY($B30,2),"Segunda","Terça","Quarta","Quinta","Sexta","Sábado","Domingo")) | AD30: =IF($B30="","",TEXT($B30,"MM/AAAA")) | AE30: =IF(COUNTA($B30:$R30)=0,"",IF($X30="Cancelado",0,ROUND(N($Q30)+N($S30)+N($T30)-N($U30),2))) | AF30: =IF($G30="","",IFERROR(INDEX(LINHAS_DRE_PLANO,MATCH($G30,SUBCATEGORIAS_PLANO,0)),"Não classificado")) | AG30: =IF($G30="","",IFERROR(INDEX(TIPOS_FLUXO_PLANO,MATCH($G30,SUBCATEGORIAS_PLANO,0)),"Não classificado")) | AH30: =IF($G30="","",IFERROR(INDEX(GRUPOS_PLANO,MATCH($G30,SUBCATEGORIAS_PLANO,0)),"Não classificado")) | AI30: =IF(OR($C30="",$X30="Pago",$X30="Recebido",$X30="Cancelado"),"",$C30-TODAY()) | AJ30: =IF(OR($C30="",$X30="Pago",$X30="Recebido",$X30="Cancelado"),0,MAX(0,TODAY()-$C30)) | AK30: =IF($D30="","",$D30-$B30) | AL30: =IF(OR($D30="",$B30=""),"",ROUND(N($R30)*($D30-$B30),2)) | AM30: =IF(AND($E30="Saída",$W30>0,$C30<>""),$C30+ROW()/1000000,"") | AN30: =IF(AND($E30="Entrada",$W30>0,$C30<>""),$C30+ROW()/1000000,"") | AO30: =IF(COUNTA($B30:$R30)=0,"",IF(AND($I30<>"",COUNTIF(CLIENTES_NOMES,$I30)+COUNTIF(CLIENTES_FANTASIA,$I30)+COUNTIF(FORNECEDORES_NOMES,$I30)+COUNTIF(FORNECEDORES_FANTASIA,$I30)=0),"⚠ Cliente/Fornecedor não cadastrado",IF(AND($G30<>"",COUNTIF(SUBCATEGORIAS_PLANO,$G30)=0),"⚠ Subcategoria fora do plano de contas",IF(OR($Q30="",N($Q30)=0),"⚠ Valor previsto não informado",IF(AND(OR($X30="Pago",$X30="Recebido"),$D30=""),"⚠ Status pago/recebido sem data",IF(AND($D30<>"",N($R30)=0),"⚠ Data de pagamento sem valor realizado",IF(AND(N($P30)>1,N($O30)>N($P30)),"⚠ Nº da parcela maior que o total",IF(AND($C30<>"",$B30<>"",$C30<$B30),"⚠ Vencimento anterior à competência","OK"))))))))
A31: L0026 | B31: 46041 | C31: 46062 | D31: 46064 | E31: Entrada | F31: Vendas | G31: Vendas de Produtos | H31: Comercial | I31: EMPÓRIO NATURAL COMÉRCIO LTDA | J31: Venda de mercadorias para revenda | K31: NF-e 2009 | L31: Itaú Unibanco — C/C 45678-9 | M31: Boleto | O31: 1 | P31: 1 | Q31: 16862.21 | R31: 16862.21 | V31: =IF(COUNTA($B31:$R31)=0,"",ROUND(N($R31)+N($S31)+N($T31)-N($U31),2)) | W31: =IF(COUNTA($B31:$R31)=0,"",IF(OR($X31="Pago",$X31="Recebido",$X31="Cancelado"),0,ROUND(N($Q31)+N($S31)+N($T31)-N($U31)-N($R31),2))) | X31: Pago | Y31: =IF(COUNTA($B31:$R31)=0,"",IF($X31="Cancelado","Cancelado",IF(OR($X31="Pago",$X31="Recebido"),$X31,IF(OR($X31="Parcial",N($R31)>0),"Parcial",IF($C31="","Sem vencimento",IF($C31<TODAY(),"Vencido",IF($C31=TODAY(),"Vence hoje",IF($C31<=TODAY()+7,"Vence em 7 dias",IF($C31<=TODAY()+30,"Vence em 30 dias","Futuro"))))))))) | Z31: =IF($B31="","",MONTH($B31)) | AA31: =IF($B31="","",YEAR($B31)) | AB31: =IF($B31="","",ISOWEEKNUM($B31)) | AC31: =IF($B31="","",CHOOSE(WEEKDAY($B31,2),"Segunda","Terça","Quarta","Quinta","Sexta","Sábado","Domingo")) | AD31: =IF($B31="","",TEXT($B31,"MM/AAAA")) | AE31: =IF(COUNTA($B31:$R31)=0,"",IF($X31="Cancelado",0,ROUND(N($Q31)+N($S31)+N($T31)-N($U31),2))) | AF31: =IF($G31="","",IFERROR(INDEX(LINHAS_DRE_PLANO,MATCH($G31,SUBCATEGORIAS_PLANO,0)),"Não classificado")) | AG31: =IF($G31="","",IFERROR(INDEX(TIPOS_FLUXO_PLANO,MATCH($G31,SUBCATEGORIAS_PLANO,0)),"Não classificado")) | AH31: =IF($G31="","",IFERROR(INDEX(GRUPOS_PLANO,MATCH($G31,SUBCATEGORIAS_PLANO,0)),"Não classificado")) | AI31: =IF(OR($C31="",$X31="Pago",$X31="Recebido",$X31="Cancelado"),"",$C31-TODAY()) | AJ31: =IF(OR($C31="",$X31="Pago",$X31="Recebido",$X31="Cancelado"),0,MAX(0,TODAY()-$C31)) | AK31: =IF($D31="","",$D31-$B31) | AL31: =IF(OR($D31="",$B31=""),"",ROUND(N($R31)*($D31-$B31),2)) | AM31: =IF(AND($E31="Saída",$W31>0,$C31<>""),$C31+ROW()/1000000,"") | AN31: =IF(AND($E31="Entrada",$W31>0,$C31<>""),$C31+ROW()/1000000,"") | AO31: =IF(COUNTA($B31:$R31)=0,"",IF(AND($I31<>"",COUNTIF(CLIENTES_NOMES,$I31)+COUNTIF(CLIENTES_FANTASIA,$I31)+COUNTIF(FORNECEDORES_NOMES,$I31)+COUNTIF(FORNECEDORES_FANTASIA,$I31)=0),"⚠ Cliente/Fornecedor não cadastrado",IF(AND($G31<>"",COUNTIF(SUBCATEGORIAS_PLANO,$G31)=0),"⚠ Subcategoria fora do plano de contas",IF(OR($Q31="",N($Q31)=0),"⚠ Valor previsto não informado",IF(AND(OR($X31="Pago",$X31="Recebido"),$D31=""),"⚠ Status pago/recebido sem data",IF(AND($D31<>"",N($R31)=0),"⚠ Data de pagamento sem valor realizado",IF(AND(N($P31)>1,N($O31)>N($P31)),"⚠ Nº da parcela maior que o total",IF(AND($C31<>"",$B31<>"",$C31<$B31),"⚠ Vencimento anterior à competência","OK"))))))))
A32: L0027 | B32: 46042 | C32: 46052 | D32: 46053 | E32: Saída | F32: Custos Variáveis | G32: Outros Custos Diretos | H32: Produção | I32: APOIO OPERACIONAL SERVIÇOS LTDA | J32: Serviços de apoio à operação e expedição | K32: DOC 7165 | L32: Itaú Unibanco — C/C 45678-9 | M32: PIX | O32: 1 | P32: 1 | Q32: 880.23 | R32: 880.23 | V32: =IF(COUNTA($B32:$R32)=0,"",ROUND(N($R32)+N($S32)+N($T32)-N($U32),2)) | W32: =IF(COUNTA($B32:$R32)=0,"",IF(OR($X32="Pago",$X32="Recebido",$X32="Cancelado"),0,ROUND(N($Q32)+N($S32)+N($T32)-N($U32)-N($R32),2))) | X32: Pago | Y32: =IF(COUNTA($B32:$R32)=0,"",IF($X32="Cancelado","Cancelado",IF(OR($X32="Pago",$X32="Recebido"),$X32,IF(OR($X32="Parcial",N($R32)>0),"Parcial",IF($C32="","Sem vencimento",IF($C32<TODAY(),"Vencido",IF($C32=TODAY(),"Vence hoje",IF($C32<=TODAY()+7,"Vence em 7 dias",IF($C32<=TODAY()+30,"Vence em 30 dias","Futuro"))))))))) | Z32: =IF($B32="","",MONTH($B32)) | AA32: =IF($B32="","",YEAR($B32)) | AB32: =IF($B32="","",ISOWEEKNUM($B32)) | AC32: =IF($B32="","",CHOOSE(WEEKDAY($B32,2),"Segunda","Terça","Quarta","Quinta","Sexta","Sábado","Domingo")) | AD32: =IF($B32="","",TEXT($B32,"MM/AAAA")) | AE32: =IF(COUNTA($B32:$R32)=0,"",IF($X32="Cancelado",0,ROUND(N($Q32)+N($S32)+N($T32)-N($U32),2))) | AF32: =IF($G32="","",IFERROR(INDEX(LINHAS_DRE_PLANO,MATCH($G32,SUBCATEGORIAS_PLANO,0)),"Não classificado")) | AG32: =IF($G32="","",IFERROR(INDEX(TIPOS_FLUXO_PLANO,MATCH($G32,SUBCATEGORIAS_PLANO,0)),"Não classificado")) | AH32: =IF($G32="","",IFERROR(INDEX(GRUPOS_PLANO,MATCH($G32,SUBCATEGORIAS_PLANO,0)),"Não classificado")) | AI32: =IF(OR($C32="",$X32="Pago",$X32="Recebido",$X32="Cancelado"),"",$C32-TODAY()) | AJ32: =IF(OR($C32="",$X32="Pago",$X32="Recebido",$X32="Cancelado"),0,MAX(0,TODAY()-$C32)) | AK32: =IF($D32="","",$D32-$B32) | AL32: =IF(OR($D32="",$B32=""),"",ROUND(N($R32)*($D32-$B32),2)) | AM32: =IF(AND($E32="Saída",$W32>0,$C32<>""),$C32+ROW()/1000000,"") | AN32: =IF(AND($E32="Entrada",$W32>0,$C32<>""),$C32+ROW()/1000000,"") | AO32: =IF(COUNTA($B32:$R32)=0,"",IF(AND($I32<>"",COUNTIF(CLIENTES_NOMES,$I32)+COUNTIF(CLIENTES_FANTASIA,$I32)+COUNTIF(FORNECEDORES_NOMES,$I32)+COUNTIF(FORNECEDORES_FANTASIA,$I32)=0),"⚠ Cliente/Fornecedor não cadastrado",IF(AND($G32<>"",COUNTIF(SUBCATEGORIAS_PLANO,$G32)=0),"⚠ Subcategoria fora do plano de contas",IF(OR($Q32="",N($Q32)=0),"⚠ Valor previsto não informado",IF(AND(OR($X32="Pago",$X32="Recebido"),$D32=""),"⚠ Status pago/recebido sem data",IF(AND($D32<>"",N($R32)=0),"⚠ Data de pagamento sem valor realizado",IF(AND(N($P32)>1,N($O32)>N($P32)),"⚠ Nº da parcela maior que o total",IF(AND($C32<>"",$B32<>"",$C32<$B32),"⚠ Vencimento anterior à competência","OK"))))))))
A33: L0028 | B33: 46042 | C33: 46073 | D33: 46074 | E33: Saída | F33: Tributos | G33: Simples Nacional | H33: Financeiro | I33: RECEITA FEDERAL DO BRASIL | J33: Simples Nacional — competência 01/2026 | K33: DAS 01/2026 | L33: Banco do Brasil — C/C 12345-6 | M33: Transferência | O33: 1 | P33: 1 | Q33: 19010.58 | R33: 19010.58 | V33: =IF(COUNTA($B33:$R33)=0,"",ROUND(N($R33)+N($S33)+N($T33)-N($U33),2)) | W33: =IF(COUNTA($B33:$R33)=0,"",IF(OR($X33="Pago",$X33="Recebido",$X33="Cancelado"),0,ROUND(N($Q33)+N($S33)+N($T33)-N($U33)-N($R33),2))) | X33: Pago | Y33: =IF(COUNTA($B33:$R33)=0,"",IF($X33="Cancelado","Cancelado",IF(OR($X33="Pago",$X33="Recebido"),$X33,IF(OR($X33="Parcial",N($R33)>0),"Parcial",IF($C33="","Sem vencimento",IF($C33<TODAY(),"Vencido",IF($C33=TODAY(),"Vence hoje",IF($C33<=TODAY()+7,"Vence em 7 dias",IF($C33<=TODAY()+30,"Vence em 30 dias","Futuro"))))))))) | Z33: =IF($B33="","",MONTH($B33)) | AA33: =IF($B33="","",YEAR($B33)) | AB33: =IF($B33="","",ISOWEEKNUM($B33)) | AC33: =IF($B33="","",CHOOSE(WEEKDAY($B33,2),"Segunda","Terça","Quarta","Quinta","Sexta","Sábado","Domingo")) | AD33: =IF($B33="","",TEXT($B33,"MM/AAAA")) | AE33: =IF(COUNTA($B33:$R33)=0,"",IF($X33="Cancelado",0,ROUND(N($Q33)+N($S33)+N($T33)-N($U33),2))) | AF33: =IF($G33="","",IFERROR(INDEX(LINHAS_DRE_PLANO,MATCH($G33,SUBCATEGORIAS_PLANO,0)),"Não classificado")) | AG33: =IF($G33="","",IFERROR(INDEX(TIPOS_FLUXO_PLANO,MATCH($G33,SUBCATEGORIAS_PLANO,0)),"Não classificado")) | AH33: =IF($G33="","",IFERROR(INDEX(GRUPOS_PLANO,MATCH($G33,SUBCATEGORIAS_PLANO,0)),"Não classificado")) | AI33: =IF(OR($C33="",$X33="Pago",$X33="Recebido",$X33="Cancelado"),"",$C33-TODAY()) | AJ33: =IF(OR($C33="",$X33="Pago",$X33="Recebido",$X33="Cancelado"),0,MAX(0,TODAY()-$C33)) | AK33: =IF($D33="","",$D33-$B33) | AL33: =IF(OR($D33="",$B33=""),"",ROUND(N($R33)*($D33-$B33),2)) | AM33: =IF(AND($E33="Saída",$W33>0,$C33<>""),$C33+ROW()/1000000,"") | AN33: =IF(AND($E33="Entrada",$W33>0,$C33<>""),$C33+ROW()/1000000,"") | AO33: =IF(COUNTA($B33:$R33)=0,"",IF(AND($I33<>"",COUNTIF(CLIENTES_NOMES,$I33)+COUNTIF(CLIENTES_FANTASIA,$I33)+COUNTIF(FORNECEDORES_NOMES,$I33)+COUNTIF(FORNECEDORES_FANTASIA,$I33)=0),"⚠ Cliente/Fornecedor não cadastrado",IF(AND($G33<>"",COUNTIF(SUBCATEGORIAS_PLANO,$G33)=0),"⚠ Subcategoria fora do plano de contas",IF(OR($Q33="",N($Q33)=0),"⚠ Valor previsto não informado",IF(AND(OR($X33="Pago",$X33="Recebido"),$D33=""),"⚠ Status pago/recebido sem data",IF(AND($D33<>"",N($R33)=0),"⚠ Data de pagamento sem valor realizado",IF(AND(N($P33)>1,N($O33)>N($P33)),"⚠ Nº da parcela maior que o total",IF(AND($C33<>"",$B33<>"",$C33<$B33),"⚠ Vencimento anterior à competência","OK"))))))))
A34: L0029 | B34: 46044 | C34: 46076 | D34: 46077 | E34: Entrada | F34: Vendas | G34: Vendas de Serviços | H34: Comercial | I34: MERCADO BOA COMPRA LTDA | J34: Serviços de logística, montagem e reposição | K34: RPS 3002 | L34: Banco do Brasil — C/C 12345-6 | M34: Boleto | O34: 1 | P34: 1 | Q34: 11412.69 | R34: 11412.69 | V34: =IF(COUNTA($B34:$R34)=0,"",ROUND(N($R34)+N($S34)+N($T34)-N($U34),2)) | W34: =IF(COUNTA($B34:$R34)=0,"",IF(OR($X34="Pago",$X34="Recebido",$X34="Cancelado"),0,ROUND(N($Q34)+N($S34)+N($T34)-N($U34)-N($R34),2))) | X34: Pago | Y34: =IF(COUNTA($B34:$R34)=0,"",IF($X34="Cancelado","Cancelado",IF(OR($X34="Pago",$X34="Recebido"),$X34,IF(OR($X34="Parcial",N($R34)>0),"Parcial",IF($C34="","Sem vencimento",IF($C34<TODAY(),"Vencido",IF($C34=TODAY(),"Vence hoje",IF($C34<=TODAY()+7,"Vence em 7 dias",IF($C34<=TODAY()+30,"Vence em 30 dias","Futuro"))))))))) | Z34: =IF($B34="","",MONTH($B34)) | AA34: =IF($B34="","",YEAR($B34)) | AB34: =IF($B34="","",ISOWEEKNUM($B34)) | AC34: =IF($B34="","",CHOOSE(WEEKDAY($B34,2),"Segunda","Terça","Quarta","Quinta","Sexta","Sábado","Domingo")) | AD34: =IF($B34="","",TEXT($B34,"MM/AAAA")) | AE34: =IF(COUNTA($B34:$R34)=0,"",IF($X34="Cancelado",0,ROUND(N($Q34)+N($S34)+N($T34)-N($U34),2))) | AF34: =IF($G34="","",IFERROR(INDEX(LINHAS_DRE_PLANO,MATCH($G34,SUBCATEGORIAS_PLANO,0)),"Não classificado")) | AG34: =IF($G34="","",IFERROR(INDEX(TIPOS_FLUXO_PLANO,MATCH($G34,SUBCATEGORIAS_PLANO,0)),"Não classificado")) | AH34: =IF($G34="","",IFERROR(INDEX(GRUPOS_PLANO,MATCH($G34,SUBCATEGORIAS_PLANO,0)),"Não classificado")) | AI34: =IF(OR($C34="",$X34="Pago",$X34="Recebido",$X34="Cancelado"),"",$C34-TODAY()) | AJ34: =IF(OR($C34="",$X34="Pago",$X34="Recebido",$X34="Cancelado"),0,MAX(0,TODAY()-$C34)) | AK34: =IF($D34="","",$D34-$B34) | AL34: =IF(OR($D34="",$B34=""),"",ROUND(N($R34)*($D34-$B34),2)) | AM34: =IF(AND($E34="Saída",$W34>0,$C34<>""),$C34+ROW()/1000000,"") | AN34: =IF(AND($E34="Entrada",$W34>0,$C34<>""),$C34+ROW()/1000000,"") | AO34: =IF(COUNTA($B34:$R34)=0,"",IF(AND($I34<>"",COUNTIF(CLIENTES_NOMES,$I34)+COUNTIF(CLIENTES_FANTASIA,$I34)+COUNTIF(FORNECEDORES_NOMES,$I34)+COUNTIF(FORNECEDORES_FANTASIA,$I34)=0),"⚠ Cliente/Fornecedor não cadastrado",IF(AND($G34<>"",COUNTIF(SUBCATEGORIAS_PLANO,$G34)=0),"⚠ Subcategoria fora do plano de contas",IF(OR($Q34="",N($Q34)=0),"⚠ Valor previsto não informado",IF(AND(OR($X34="Pago",$X34="Recebido"),$D34=""),"⚠ Status pago/recebido sem data",IF(AND($D34<>"",N($R34)=0),"⚠ Data de pagamento sem valor realizado",IF(AND(N($P34)>1,N($O34)>N($P34)),"⚠ Nº da parcela maior que o total",IF(AND($C34<>"",$B34<>"",$C34<$B34),"⚠ Vencimento anterior à competência","OK"))))))))
A35: L0030 | B35: 46044 | C35: 46059 | D35: 46060 | E35: Entrada | F35: Vendas | G35: Vendas de Serviços | H35: Comercial | I35: RESTAURANTE SABOR CASEIRO LTDA | J35: Serviços de logística, montagem e reposição | K35: RPS 3006 | L35: Itaú Unibanco — C/C 45678-9 | M35: Boleto | O35: 1 | P35: 1 | Q35: 6735.82 | R35: 6735.82 | V35: =IF(COUNTA($B35:$R35)=0,"",ROUND(N($R35)+N($S35)+N($T35)-N($U35),2)) | W35: =IF(COUNTA($B35:$R35)=0,"",IF(OR($X35="Pago",$X35="Recebido",$X35="Cancelado"),0,ROUND(N($Q35)+N($S35)+N($T35)-N($U35)-N($R35),2))) | X35: Pago | Y35: =IF(COUNTA($B35:$R35)=0,"",IF($X35="Cancelado","Cancelado",IF(OR($X35="Pago",$X35="Recebido"),$X35,IF(OR($X35="Parcial",N($R35)>0),"Parcial",IF($C35="","Sem vencimento",IF($C35<TODAY(),"Vencido",IF($C35=TODAY(),"Vence hoje",IF($C35<=TODAY()+7,"Vence em 7 dias",IF($C35<=TODAY()+30,"Vence em 30 dias","Futuro"))))))))) | Z35: =IF($B35="","",MONTH($B35)) | AA35: =IF($B35="","",YEAR($B35)) | AB35: =IF($B35="","",ISOWEEKNUM($B35)) | AC35: =IF($B35="","",CHOOSE(WEEKDAY($B35,2),"Segunda","Terça","Quarta","Quinta","Sexta","Sábado","Domingo")) | AD35: =IF($B35="","",TEXT($B35,"MM/AAAA")) | AE35: =IF(COUNTA($B35:$R35)=0,"",IF($X35="Cancelado",0,ROUND(N($Q35)+N($S35)+N($T35)-N($U35),2))) | AF35: =IF($G35="","",IFERROR(INDEX(LINHAS_DRE_PLANO,MATCH($G35,SUBCATEGORIAS_PLANO,0)),"Não classificado")) | AG35: =IF($G35="","",IFERROR(INDEX(TIPOS_FLUXO_PLANO,MATCH($G35,SUBCATEGORIAS_PLANO,0)),"Não classificado")) | AH35: =IF($G35="","",IFERROR(INDEX(GRUPOS_PLANO,MATCH($G35,SUBCATEGORIAS_PLANO,0)),"Não classificado")) | AI35: =IF(OR($C35="",$X35="Pago",$X35="Recebido",$X35="Cancelado"),"",$C35-TODAY()) | AJ35: =IF(OR($C35="",$X35="Pago",$X35="Recebido",$X35="Cancelado"),0,MAX(0,TODAY()-$C35)) | AK35: =IF($D35="","",$D35-$B35) | AL35: =IF(OR($D35="",$B35=""),"",ROUND(N($R35)*($D35-$B35),2)) | AM35: =IF(AND($E35="Saída",$W35>0,$C35<>""),$C35+ROW()/1000000,"") | AN35: =IF(AND($E35="Entrada",$W35>0,$C35<>""),$C35+ROW()/1000000,"") | AO35: =IF(COUNTA($B35:$R35)=0,"",IF(AND($I35<>"",COUNTIF(CLIENTES_NOMES,$I35)+COUNTIF(CLIENTES_FANTASIA,$I35)+COUNTIF(FORNECEDORES_NOMES,$I35)+COUNTIF(FORNECEDORES_FANTASIA,$I35)=0),"⚠ Cliente/Fornecedor não cadastrado",IF(AND($G35<>"",COUNTIF(SUBCATEGORIAS_PLANO,$G35)=0),"⚠ Subcategoria fora do plano de contas",IF(OR($Q35="",N($Q35)=0),"⚠ Valor previsto não informado",IF(AND(OR($X35="Pago",$X35="Recebido"),$D35=""),"⚠ Status pago/recebido sem data",IF(AND($D35<>"",N($R35)=0),"⚠ Data de pagamento sem valor realizado",IF(AND(N($P35)>1,N($O35)>N($P35)),"⚠ Nº da parcela maior que o total",IF(AND($C35<>"",$B35<>"",$C35<$B35),"⚠ Vencimento anterior à competência","OK"))))))))
